Workbook
Name Óxido_de_cobalto_de_manganeso_y_litio: 'Fórmula 2'!$A$21:$A$23
Name Litio_ferrofosfato: 'Fórmula 2'!$A$17:$A$19
Name Óxido_cobalto_Litio: 'Fórmula 2'!$A$9:$A$11
Name Titanato_de_litio: 'Fórmula 2'!$C$9:$C$11
Name Una_sola_celda: 'Fórmula 2'!$K$5:$K$7
Name Sí: 'Fórmula 2'!$A$26:$A$47
Name Battery_Packaging: 'Fórmula 2'!$E$26:$E$37
Name Polímero_de_litio: 'Fórmula 2'!$C$5:$C$7
Name _18650_: 'Fórmula 2'!$A$5:$A$7
Name Ion_litio: 'Fórmula 2'!$A$13:$A$15
Name Varias_celdas: 'Fórmula 2'!$K$9:$K$12

Sheet Hoja 1
A1: 2970684658 | B1: Precio Mínimo
A2: MLM1411560745 | B2: 699
A3: MLM2096725416 | B3: 490
A4: MLM1945666421 | B4: 170
A5: MLM1976324961 | B5: 799

Sheet ML
A2: Mercado Libre
E3: Retenciónes
A4: ID Secuendario | B4: ID Principal | C4: Producto | D4: Precio OFERTA | E4: Retención IVA | F4: Retención ISR | G4: Costo | H4: Comision | I4: Comision | J4: Envio | K4: Utilidad | L4: ROI | M4: Ingreso x venta
B5: 608098925 | C5: Elevation Training Mask 2.0 Mascara Elevacion Mma Crossfit | D5: 399 | E5: =D5*0.069 -> 27.531 | F5: =D5*0.0215 -> 8.5785 | G5: 273.43 | H5: 0.1 | I5: =H5*D5 -> 39.9 | J5: 67.5 | K5: =D5-G5-I5-J5-E5-F5 -> -17.9395 | L5: =K5/G5 -> -0.065609114 | M5: =D5-E5-F5-I5-J5 -> 255.4905
B6: 682638186 | C6: Faja Chaleco Reductora Para Hombres Gym Sauna Neopreno | D6: 269 | E6: =D6*0.069 -> 18.561 | F6: =D6*0.0215 -> 5.7835 | G6: 92.61 | H6: 0.1 | I6: =H6*D6 -> 26.9 | K6: =D6-G6-I6-J6-E6-F6 -> 125.1455 | L6: =K6/G6 -> 1.3513174 | M6: =D6-E6-F6-I6-J6 -> 217.7555
B7: 3679281894 | D7: 4299 | E7: =D7*0.069 -> 296.631 | F7: =D7*0.0215 -> 92.4285 | G7: 3305.02 | H7: 0.145 | I7: =H7*D7 -> 623.355 | J7: 65 | K7: =D7-G7-I7-J7-E7-F7 -> -83.4345 | L7: =K7/G7 -> -0.025244779 | M7: =D7-E7-F7-I7-J7 -> 3221.5855
B8: 2910333802 | C8: Faja Chaleco Reductora Para Hombres Gym Sauna Neopreno | D8: 159 | E8: =D8*0.069 -> 10.971 | F8: =D8*0.0215 -> 3.4185 | G8: 92.61 | H8: 0.15 | I8: =H8*D8 -> 23.85 | J8: 30 | K8: =D8-G8-I8-J8-E8-F8 -> -1.8495 | L8: =K8/G8 -> -0.019970845 | M8: =D8-E8-F8-I8-J8 -> 90.7605
B9: 648656572 | C9: Brazalete Antebrazo Para Celular Giratorio 360 Grados | D9: 290 | E9: =D9*0.069 -> 20.01 | F9: =D9*0.0215 -> 6.235 | G9: 84.13 | H9: 0.1 | I9: =H9*D9 -> 29 | J9: 62.5 | K9: =D9-G9-I9-J9-E9-F9 -> 88.125 | L9: =K9/G9 -> 1.047486 | M9: =D9-E9-F9-I9-J9 -> 172.255
B10: 741040525 | C10: Playera Camiseta Pesas Gym Fisicoculturista Gimnasio | D10: 199 | E10: =D10*0.069 -> 13.731 | F10: =D10*0.0215 -> 4.2785 | G10: 99 | H10: 0.19 | I10: =H10*D10 -> 37.81 | J10: 37 | K10: =D10-G10-I10-J10-E10-F10 -> 7.1805 | L10: =K10/G10 -> 0.072530303 | M10: =D10-E10-F10-I10-J10 -> 106.1805
B11: 612395579 | C11: Máscara De Entrenamiento Training Mask 3.0 Para Correr Mask | D11: 799 | E11: =D11*0.069 -> 55.131 | F11: =D11*0.0215 -> 17.1785 | G11: 370.08 | H11: 0.1 | I11: =H11*D11 -> 79.9 | J11: 102.5 | K11: =D11-G11-I11-J11-E11-F11 -> 174.2105 | L11: =K11/G11 -> 0.47073741 | M11: =D11-E11-F11-I11-J11 -> 544.2905
B12: 832811198 | C12: Bandas Para Ejercicio De Resistencia De Cadera Yoga Bandas | D12: 199 | E12: =D12*0.069 -> 13.731 | F12: =D12*0.0215 -> 4.2785 | G12: 123.47 | H12: 0.1 | I12: =H12*D12 -> 19.9 | K12: =D12-G12-I12-J12-E12-F12 -> 37.6205 | L12: =K12/G12 -> 0.30469345 | M12: =D12-E12-F12-I12-J12 -> 161.0905
B13: 1347125652 | C13: Bocina Xiaomi Mi Compact Bluetooth Speaker 2 Portátil White | D13: 201 | E13: =D13*0.069 -> 13.869 | F13: =D13*0.0215 -> 4.3215 | G13: 120.87 | H13: 0.1 | I13: =H13*D13 -> 20.1 | K13: =D13-G13-I13-J13-E13-F13 -> 41.8395 | L13: =K13/G13 -> 0.34615289 | M13: =D13-E13-F13-I13-J13 -> 162.7095
B14: 663293921 | C14: Gorro Bufanda Cuello Unisex Invierno Frío Envío Gratis | D14: 157 | E14: =D14*0.069 -> 10.833 | F14: =D14*0.0215 -> 3.3755 | G14: 99.43 | H14: 0.1 | I14: =H14*D14 -> 15.7 | K14: =D14-G14-I14-J14-E14-F14 -> 27.6615 | L14: =K14/G14 -> 0.27820074 | M14: =D14-E14-F14-I14-J14 -> 127.0915
B15: 1309775400 | C15: 2 Clavija Convertidor Europeo A Americano Adaptador Cargador | D15: 43.64 | E15: =D15*0.069 -> 3.01116 | F15: =D15*0.0215 -> 0.93826 | G15: 10 | H15: 0.1 | I15: =H15*D15 -> 4.364 | K15: =D15-G15-I15-J15-E15-F15 -> 25.32658 | L15: =K15/G15 -> 2.532658 | M15: =D15-E15-F15-I15-J15 -> 35.32658
B16: 659287446 | C16: Chamarra Táctica Militar Contra Lluvia Campamentos Esdy | D16: 482 | E16: =D16*0.069 -> 33.258 | F16: =D16*0.0215 -> 10.363 | G16: 402.33 | H16: 0.1 | I16: =H16*D16 -> 48.2 | J16: 84 | K16: =D16-G16-I16-J16-E16-F16 -> -96.151 | L16: =K16/G16 -> -0.23898541 | M16: =D16-E16-F16-I16-J16 -> 306.179
B17: 1661515275 | C17: Bocina Inteligente Xiaomi Mi Smart Speaker L09g Con Asistente Virtual Google Assistant Blanca 100v/240v | D17: 707 | E17: =D17*0.069 -> 48.783 | F17: =D17*0.0215 -> 15.2005 | G17: 428.26 | H17: 0.1 | I17: =H17*D17 -> 70.7 | J17: 75 | K17: =D17-G17-I17-J17-E17-F17 -> 69.0565 | L17: =K17/G17 -> 0.16124901 | M17: =D17-E17-F17-I17-J17 -> 497.3165
B18: 921639303 | C18: Chamarra De Borrega Para Hombre Chaqueta Casual Moda | D18: 623 | E18: =D18*0.069 -> 42.987 | F18: =D18*0.0215 -> 13.3945 | G18: 410.8 | H18: 0.1 | I18: =H18*D18 -> 62.3 | J18: 91.5 | K18: =D18-G18-I18-J18-E18-F18 -> 2.0185 | L18: =K18/G18 -> 0.0049135833 | M18: =D18-E18-F18-I18-J18 -> 412.8185
B19: 598780987 | C19: Arnés Para Cuello Lastrado Head Harness Iq Sports | D19: 329 | E19: =D19*0.069 -> 22.701 | F19: =D19*0.0215 -> 7.0735 | G19: 115 | H19: 0.1 | I19: =H19*D19 -> 32.9 | J19: 62.5 | K19: =D19-G19-I19-J19-E19-F19 -> 88.8255 | L19: =K19/G19 -> 0.77239565 | M19: =D19-E19-F19-I19-J19 -> 203.8255
B20: 960650439 | C20: Audífonos In-ear Inalámbricos Xiaomi Redmi Airdots 2 Negro | D20: 279 | E20: =D20*0.069 -> 19.251 | F20: =D20*0.0215 -> 5.9985 | G20: 73.67 | H20: 0.15 | I20: =H20*D20+30 -> 71.85 | K20: =D20-G20-I20-J20-E20-F20 -> 108.2305 | L20: =K20/G20 -> 1.4691258 | M20: =D20-E20-F20-I20-J20 -> 181.9005
B21: 937333053 | C21: Sweater Cuello Alto Moda Hombre Invierno Tortuga Wimbledon | D21: 499 | E21: =D21*0.069 -> 34.431 | F21: =D21*0.0215 -> 10.7285 | G21: 236.9 | H21: 0.1 | I21: =H21*D21 -> 49.9 | J21: 102.5 | K21: =D21-G21-I21-J21-E21-F21 -> 64.5405 | L21: =K21/G21 -> 0.27243774 | M21: =D21-E21-F21-I21-J21 -> 301.4405
B22: 1304177930 | C22: Chamarra Vini Piel De Hombre Slim Fit Estilo Biker Cazadora | D22: 379 | E22: =D22*0.069 -> 26.151 | F22: =D22*0.0215 -> 8.1485 | G22: 294.92 | H22: 0.1 | I22: =H22*D22 -> 37.9 | J22: 72.5 | K22: =D22-G22-I22-J22-E22-F22 -> -60.6195 | L22: =K22/G22 -> -0.20554557 | M22: =D22-E22-F22-I22-J22 -> 234.3005
B23: 773727066 | C23: Trx Training Ligas Bandas De Suspensión Multifuncional Casa | D23: 549 | E23: =D23*0.069 -> 37.881 | F23: =D23*0.0215 -> 11.8035 | G23: 382 | H23: 0.1 | I23: =H23*D23 -> 54.9 | J23: 67.5 | K23: =D23-G23-I23-J23-E23-F23 -> -5.0845 | L23: =K23/G23 -> -0.013310209 | M23: =D23-E23-F23-I23-J23 -> 376.9155
B24: 673924123 | C24: Training Mask Mascara Elevación Mma Crossfit 4 Niveles | D24: 469 | E24: =D24*0.069 -> 32.361 | F24: =D24*0.0215 -> 10.0835 | G24: 290 | H24: 0.1 | I24: =H24*D24 -> 46.9 | J24: 78 | K24: =D24-G24-I24-J24-E24-F24 -> 11.6555 | L24: =K24/G24 -> 0.040191379 | M24: =D24-E24-F24-I24-J24 -> 301.6555
B25: 614600530 | C25: Chaleco Peso Crossfit Lastrado 27 Libras Correr | D25: 899 | E25: =D25*0.069 -> 62.031 | F25: =D25*0.0215 -> 19.3285 | G25: 450 | H25: 0.1 | I25: =H25*D25 -> 89.9 | J25: 151 | K25: =D25-G25-I25-J25-E25-F25 -> 126.7405 | L25: =K25/G25 -> 0.28164556 | M25: =D25-E25-F25-I25-J25 -> 576.7405
B26: 814514678 | C26: Corrector De Postura De Espalda Con Imanes | D26: 299 | E26: =D26*0.069 -> 20.631 | F26: =D26*0.0215 -> 6.4285 | G26: 175 | H26: 0.1 | I26: =H26*D26 -> 29.9 | J26: 78 | K26: =D26-G26-I26-J26-E26-F26 -> -10.9595 | L26: =K26/G26 -> -0.062625714 | M26: =D26-E26-F26-I26-J26 -> 164.0405
B27: 862256648 | C27: Falda Deportiva Short Licra Correr Gym Sexy Mujer Fitness | D27: 399 | E27: =D27*0.069 -> 27.531 | F27: =D27*0.0215 -> 8.5785 | G27: 239 | H27: 0.1 | I27: =H27*D27 -> 39.9 | J27: 72 | K27: =D27-G27-I27-J27-E27-F27 -> 11.9905 | L27: =K27/G27 -> 0.050169456 | M27: =D27-E27-F27-I27-J27 -> 250.9905
B28: 832509572 | C28: Licra Short Para Ciclismo Con Pad Anatómico Y Gel En Piernas | D28: 299 | E28: =D28*0.069 -> 20.631 | F28: =D28*0.0215 -> 6.4285 | G28: 123 | H28: 0.1 | I28: =H28*D28 -> 29.9 | J28: 78 | K28: =D28-G28-I28-J28-E28-F28 -> 41.0405 | L28: =K28/G28 -> 0.3336626 | M28: =D28-E28-F28-I28-J28 -> 164.0405
B29: 619668470 | C29: 4 Polainas 2 Kg Cada Una 8 Kg Lastradas Envío Gratis | D29: 499 | E29: =D29*0.069 -> 34.431 | F29: =D29*0.0215 -> 10.7285 | H29: 0.1 | I29: =H29*D29 -> 49.9 | J29: 116 | K29: =D29-G29-I29-J29-E29-F29 -> 287.9405 | L29: =K29/G29 -> #DIV/0! | M29: =D29-E29-F29-I29-J29 -> 287.9405
B30: 963461182 | C30: Control Joystick Razer Wolverine Ultimate Negro | D30: 1955 | E30: =D30*0.069 -> 134.895 | F30: =D30*0.0215 -> 42.0325 | G30: 1296.4 | H30: 0.1 | I30: =H30*D30 -> 195.5 | J30: 62.5 | K30: =D30-G30-I30-J30-E30-F30 -> 223.6725 | L30: =K30/G30 -> 0.17253355 | M30: =D30-E30-F30-I30-J30 -> 1520.0725
B31: 1410430551 | C31: Xiaomi Mi Watch 1.39 Caja De Polímero Reforzado Con Fibra De Vidrio Black, Malla Black De Tpu Xmwtcl02 | D31: 2599 | E31: =D31*0.069 -> 179.331 | F31: =D31*0.0215 -> 55.8785 | G31: 1800 | H31: 0.1 | I31: =H31*D31 -> 259.9 | J31: 62.5 | K31: =D31-G31-I31-J31-E31-F31 -> 241.3905 | L31: =K31/G31 -> 0.13410583 | M31: =D31-E31-F31-I31-J31 -> 2041.3905
B32: 956690848 | C32: Xiaomi Mi Watch Lite 1.4 Caja Navy Blue, Malla Navy Blue De Tpu Redmiwt02 | D32: 784 | E32: =D32*0.069 -> 54.096 | F32: =D32*0.0215 -> 16.856 | G32: 611.91 | H32: 0.1 | I32: =H32*D32 -> 78.4 | J32: 62 | K32: =D32-G32-I32-J32-E32-F32 -> -39.262 | L32: =K32/G32 -> -0.064163031 | M32: =D32-E32-F32-I32-J32 -> 572.648
B33: 1372361536 | C33: Audífonos In-ear Inalámbricos Xiaomi Mi Earphones 2 Basic Blanco | D33: 412 | E33: =D33*0.069 -> 28.428 | F33: =D33*0.0215 -> 8.858 | G33: 274.26 | H33: 0.1 | I33: =H33*D33 -> 41.2 | J33: 67.5 | K33: =D33-G33-I33-J33-E33-F33 -> -8.246 | L33: =K33/G33 -> -0.03006636 | M33: =D33-E33-F33-I33-J33 -> 266.014
B34: 1330421284 | C34: Audífonos In-ear Mi True Wireless Earbud Basic S | D34: 499 | E34: =D34*0.069 -> 34.431 | F34: =D34*0.0215 -> 10.7285 | G34: 127 | H34: 0.1 | I34: =H34*D34 -> 49.9 | J34: 116 | K34: =D34-G34-I34-J34-E34-F34 -> 160.9405 | L34: =K34/G34 -> 1.267248 | M34: =D34-E34-F34-I34-J34 -> 287.9405
B35: 1330452732 | C35: Apple AirPods Pro - Blanco | D35: 5999 | E35: =D35*0.069 -> 413.931 | F35: =D35*0.0215 -> 128.9785 | G35: 627.34 | H35: 0.1 | I35: =H35*D35 -> 599.9 | J35: 57 | K35: =D35-G35-I35-J35-E35-F35 -> 4171.8505 | L35: =K35/G35 -> 6.650063 | M35: =D35-E35-F35-I35-J35 -> 4799.1905
B36: 927019108 | C36: Aspiradora Trapeadora Robot Xiaomi Mi Robot Vacuum-mop Essential Blanca 100v/240v | D36: 3700 | E36: =D36*0.069 -> 255.3 | F36: =D36*0.0215 -> 79.55 | G36: 2800 | H36: 0.1 | I36: =H36*D36 -> 370 | J36: 130 | K36: =D36-G36-I36-J36-E36-F36 -> 65.15 | L36: =K36/G36 -> 0.023267857 | M36: =D36-E36-F36-I36-J36 -> 2865.15
B37: 1375071912 | C37: Cámara Vigilancia Xiaomi Mi 360° Camera 1080p Vision Nocturn | D37: 539 | E37: =D37*0.069 -> 37.191 | F37: =D37*0.0215 -> 11.5885 | G37: 317.24 | H37: 0.1 | I37: =H37*D37 -> 53.9 | J37: 91.5 | K37: =D37-G37-I37-J37-E37-F37 -> 27.5805 | L37: =K37/G37 -> 0.086938911 | M37: =D37-E37-F37-I37-J37 -> 344.8205
B38: 1314430762 | C38: Audífonos In-ear Inalámbricos Jbl Under Armour Ua Project Rock Black | D38: 1199 | E38: =D38*0.069 -> 82.731 | F38: =D38*0.0215 -> 25.7785 | G38: 566.17 | H38: 0.1 | I38: =H38*D38 -> 119.9 | J38: 60 | K38: =D38-G38-I38-J38-E38-F38 -> 344.4205 | L38: =K38/G38 -> 0.60833407 | M38: =D38-E38-F38-I38-J38 -> 910.5905
B39: 1353124983 | C39: Funda Silicona Compatible Con iPhone 7/8 X/s Max iPhone 11 | D39: 99 | E39: =D39*0.069 -> 6.831 | F39: =D39*0.0215 -> 2.1285 | G39: 62 | H39: 0.1 | I39: =H39*D39 -> 9.9 | K39: =D39-G39-I39-J39-E39-F39 -> 18.1405 | L39: =K39/G39 -> 0.29258871 | M39: =D39-E39-F39-I39-J39 -> 80.1405
A40: 1372355175 | B40: 1372871257 | C40: Router Xiaomi Mi 4a Blanco 110v/240v | D40: 399 | E40: =D40*0.069 -> 27.531 | F40: =D40*0.0215 -> 8.5785 | G40: 250 | H40: 0.1 | I40: =H40*D40 -> 39.9 | J40: 58.4 | K40: =D40-G40-I40-J40-E40-F40 -> 14.5905 | L40: =K40/G40 -> 0.058362 | M40: =D40-E40-F40-I40-J40 -> 264.5905
B41: 960684889 | C41: Guantes Venum Boxeo Contender White, Black, Silver, Boxing | D41: 989 | E41: =D41*0.069 -> 68.241 | F41: =D41*0.0215 -> 21.2635 | G41: 692.02 | H41: 0.1 | I41: =H41*D41 -> 98.9 | J41: 102 | K41: =D41-G41-I41-J41-E41-F41 -> 6.5755 | L41: =K41/G41 -> 0.009501893 | M41: =D41-E41-F41-I41-J41 -> 698.5955
B42: 1383712901 | C42: Xiaomi Redmi Watch 2 Lite 1.55 Caja Black, Malla Black De Tpu | D42: 1099 | E42: =D42*0.069 -> 75.831 | F42: =D42*0.0215 -> 23.6285 | G42: 815.4 | H42: 0.1 | I42: =H42*D42 -> 109.9 | J42: 60 | K42: =D42-G42-I42-J42-E42-F42 -> 14.2405 | L42: =K42/G42 -> 0.017464435 | M42: =D42-E42-F42-I42-J42 -> 829.6405
B43: 907154652 | C43: Amazon Echo Studio Con Asistente Virtual Alexa Charcoal 110v/240v | D43: 5499 | E43: =D43*0.069 -> 379.431 | F43: =D43*0.0215 -> 118.2285 | G43: 3704.46 | H43: 0.1 | I43: =H43*D43 -> 549.9 | J43: 84 | K43: =D43-G43-I43-J43-E43-F43 -> 662.9805 | L43: =K43/G43 -> 0.17896819 | M43: =D43-E43-F43-I43-J43 -> 4367.4405
B44: 938199143 | C44: Mini Wifi Cámara Full Hd Casa Videocámara De Visión Nocturna | D44: 251 | E44: =D44*0.069 -> 17.319 | F44: =D44*0.0215 -> 5.3965 | G44: 205.28 | H44: 0.1 | I44: =H44*D44 -> 25.1 | J44: 60 | K44: =D44-G44-I44-J44-E44-F44 -> -62.0955 | L44: =K44/G44 -> -0.30249172 | M44: =D44-E44-F44-I44-J44 -> 143.1845
B45: 666150440 | C45: Chalecos Con Peso Lastrado 20 Libras Crossfit Correr 2 Pzs | D45: 1799 | E45: =D45*0.069 -> 124.131 | F45: =D45*0.0215 -> 38.6785 | H45: 0.1 | I45: =H45*D45 -> 179.9 | J45: 175 | K45: =D45-G45-I45-J45-E45-F45 -> 1281.2905 | L45: =K45/G45 -> #DIV/0! | M45: =D45-E45-F45-I45-J45 -> 1281.2905
B46: 582138037 | C46: Fidget Cube Spinner Antiestres Ansiedad Enfoque Estres | D46: 39 | E46: =D46*0.069 -> 2.691 | F46: =D46*0.0215 -> 0.8385 | G46: 5 | H46: 0.1 | I46: =H46*D46 -> 3.9 | K46: =D46-G46-I46-J46-E46-F46 -> 26.5705 | L46: =K46/G46 -> 5.3141 | M46: =D46-E46-F46-I46-J46 -> 31.5705
B47: 1385997177 | C47: Audífonos In-ear Inalámbricos Bose Soundsport Free Oem- | D47: 999 | E47: =D47*0.069 -> 68.931 | F47: =D47*0.0215 -> 21.4785 | G47: 701.25 | H47: 0.1 | I47: =H47*D47 -> 99.9 | J47: 62.5 | K47: =D47-G47-I47-J47-E47-F47 -> 44.9405 | L47: =K47/G47 -> 0.064086275 | M47: =D47-E47-F47-I47-J47 -> 746.1905
B48: 823886475 | C48: Polainas Tobilleras 2kg Y Chaleco Con Peso Lastrado 20 Lb | D48: 999 | E48: =D48*0.069 -> 68.931 | F48: =D48*0.0215 -> 21.4785 | H48: 0.1 | I48: =H48*D48 -> 99.9 | J48: 116 | K48: =D48-G48-I48-J48-E48-F48 -> 692.6905 | L48: =K48/G48 -> #DIV/0! | M48: =D48-E48-F48-I48-J48 -> 692.6905
B49: 887037959 | C49: Laptop Samsung Chromebook 4 11.6' Intel Celeron N4000 | D49: 4999 | E49: =D49*0.069 -> 344.931 | F49: =D49*0.0215 -> 107.4785 | G49: 4299 | H49: 0.1 | I49: =H49*D49 -> 499.9 | J49: 84 | K49: =D49-G49-I49-J49-E49-F49 -> -336.3095 | L49: =K49/G49 -> -0.078229705 | M49: =D49-E49-F49-I49-J49 -> 3962.6905
B50: 887097971 | C50: Laptop Lenovo Chromebook S330 Lenovo 14 Mt 4g 32crm | D50: 5399 | E50: =D50*0.069 -> 372.531 | F50: =D50*0.0215 -> 116.0785 | G50: 4699 | H50: 0.1 | I50: =H50*D50 -> 539.9 | J50: 78 | K50: =D50-G50-I50-J50-E50-F50 -> -406.5095 | L50: =K50/G50 -> -0.086509789 | M50: =D50-E50-F50-I50-J50 -> 4292.4905
B51: 960673272 | C51: Guantes Venum Boxeo Contender 2.0 8oz / 10oz Boxing Original | D51: 1070 | E51: =D51*0.069 -> 73.83 | F51: =D51*0.0215 -> 23.005 | G51: 692.02 | H51: 0.1 | I51: =H51*D51 -> 107 | J51: 102 | K51: =D51-G51-I51-J51-E51-F51 -> 72.145 | L51: =K51/G51 -> 0.10425277 | M51: =D51-E51-F51-I51-J51 -> 764.165
B52: 1358559558 | C52: iPad Mini Apple Generation 2012 A1432 7.9 16gb Sin Caja | D52: 1699 | E52: =D52*0.069 -> 117.231 | F52: =D52*0.0215 -> 36.5285 | G52: 1329.87 | H52: 0.1 | I52: =H52*D52 -> 169.9 | J52: 125 | K52: =D52-G52-I52-J52-E52-F52 -> -79.5295 | L52: =K52/G52 -> -0.059802462 | M52: =D52-E52-F52-I52-J52 -> 1250.3405
B53: 1326707103 | C53: Laptop Hp 14 - Intel Celeron N4020 4gb - 64gb Emmc Wind 10 | D53: 6999 | E53: =D53*0.069 -> 482.931 | F53: =D53*0.0215 -> 150.4785 | H53: 0.1 | I53: =H53*D53 -> 699.9 | J53: 84 | K53: =D53-G53-I53-J53-E53-F53 -> 5581.6905 | L53: =K53/G53 -> #DIV/0! | M53: =D53-E53-F53-I53-J53 -> 5581.6905
B54: 1325920238 | C54: Roku Streambar 9102eu De Voz 4k Negro Con 1gb De Memoria | D54: 2999 | E54: =D54*0.069 -> 206.931 | F54: =D54*0.0215 -> 64.4785 | G54: 2528.36 | H54: 0.1 | I54: =H54*D54 -> 299.9 | J54: 116 | K54: =D54-G54-I54-J54-E54-F54 -> -216.6695 | L54: =K54/G54 -> -0.085695668 | M54: =D54-E54-F54-I54-J54 -> 2311.6905
B55: 1364825803 | C55: Apple AirPods (3ª Generación) Con Caja De Carga Magsafe | D55: 5999 | E55: =D55*0.069 -> 413.931 | F55: =D55*0.0215 -> 128.9785 | G55: 629.34 | H55: 0.1 | I55: =H55*D55 -> 599.9 | J55: 57 | K55: =D55-G55-I55-J55-E55-F55 -> 4169.8505 | L55: =K55/G55 -> 6.6257516 | M55: =D55-E55-F55-I55-J55 -> 4799.1905
B56: 1325867747 | C56: Apple Magic Trackpad 2 Panel Óptico Táctil | D56: 2899 | E56: =D56*0.069 -> 200.031 | F56: =D56*0.0215 -> 62.3285 | G56: 2005.79 | H56: 0.1 | I56: =H56*D56 -> 289.9 | J56: 78 | K56: =D56-G56-I56-J56-E56-F56 -> 262.9505 | L56: =K56/G56 -> 0.13109573 | M56: =D56-E56-F56-I56-J56 -> 2268.7405
B57: 1372374697 | C57: Audífonos In-ear Gamer Inalámbricos Xiaomi Redmi Airdots 3 Pro Negro Grafito | D57: 821 | E57: =D57*0.069 -> 56.649 | F57: =D57*0.0215 -> 17.6515 | G57: 674.42 | H57: 0.1 | I57: =H57*D57 -> 82.1 | J57: 60 | K57: =D57-G57-I57-J57-E57-F57 -> -69.8205 | L57: =K57/G57 -> -0.10352673 | M57: =D57-E57-F57-I57-J57 -> 604.5995
B58: 1944780561 | C58: Audifonos Bluetooth Xiaomi Redmi Buds 3 Ip54 Blancos | D58: 399 | E58: =D58*0.069 -> 27.531 | F58: =D58*0.0215 -> 8.5785 | G58: 252.74 | H58: 0.15 | I58: =H58*D58+30 -> 89.85 | K58: =D58-G58-I58-J58-E58-F58 -> 20.3005 | L58: =K58/G58 -> 0.080321674 | M58: =D58-E58-F58-I58-J58 -> 273.0405
B59: 877495219 | C59: Laptop Chomebook Hp 11 Procesador Amd A4 4gb Ram 32gb | D59: 6999 | E59: =D59*0.069 -> 482.931 | F59: =D59*0.0215 -> 150.4785 | G59: 5527.89 | H59: 0.1 | I59: =H59*D59 -> 699.9 | J59: 78 | K59: =D59-G59-I59-J59-E59-F59 -> 59.8005 | L59: =K59/G59 -> 0.010817961 | M59: =D59-E59-F59-I59-J59 -> 5587.6905
B60: 908570482 | C60: Laptop Lenovo Chromebook Intel Dual Core 4gb 32gb Wifi | D60: 4999 | E60: =D60*0.069 -> 344.931 | F60: =D60*0.0215 -> 107.4785 | G60: 4100.9 | H60: 0.1 | I60: =H60*D60 -> 499.9 | J60: 78 | K60: =D60-G60-I60-J60-E60-F60 -> -132.2095 | L60: =K60/G60 -> -0.032239143 | M60: =D60-E60-F60-I60-J60 -> 3968.6905
B61: 1367956900 | C61: Apple Watch Series 6 (gps) - Caja De Aluminio (product)red De 40 Mm - Correa Deportiva (product)red | D61: 7799 | E61: =D61*0.069 -> 538.131 | F61: =D61*0.0215 -> 167.6785 | G61: 6090.72 | H61: 0.1 | I61: =H61*D61 -> 779.9 | J61: 62.5 | K61: =D61-G61-I61-J61-E61-F61 -> 160.0705 | L61: =K61/G61 -> 0.026281047 | M61: =D61-E61-F61-I61-J61 -> 6250.7905
B62: 960286366 | C62: Playera Para Hombre Cuello V Pronunciado Muscle Fit | D62: 199 | E62: =D62*0.069 -> 13.731 | F62: =D62*0.0215 -> 4.2785 | G62: 99 | H62: 0.1 | I62: =H62*D62 -> 19.9 | K62: =D62-G62-I62-J62-E62-F62 -> 62.0905 | L62: =K62/G62 -> 0.62717677 | M62: =D62-E62-F62-I62-J62 -> 161.0905
B63: 1362959852 | C63: Apple Watch Series 6 (gps) - Caja De Aluminio (product)red De 44 Mm - Correa Deportiva (product)red | D63: 9499 | E63: =D63*0.069 -> 655.431 | F63: =D63*0.0215 -> 204.2285 | G63: 7173.15 | H63: 0.1 | I63: =H63*D63 -> 949.9 | J63: 62.5 | K63: =D63-G63-I63-J63-E63-F63 -> 453.7905 | L63: =K63/G63 -> 0.063262374 | M63: =D63-E63-F63-I63-J63 -> 7626.9405
B64: 1370641518 | C64: Magsafe Cargador Inalámbrico iPhone 12 12 Pro Max Magnetico | D64: 359 | E64: =D64*0.069 -> 24.771 | F64: =D64*0.0215 -> 7.7185 | G64: 171.07 | H64: 0.1 | I64: =H64*D64 -> 35.9 | J64: 78 | K64: =D64-G64-I64-J64-E64-F64 -> 41.5405 | L64: =K64/G64 -> 0.2428275 | M64: =D64-E64-F64-I64-J64 -> 212.6105
B65: 1379890846 | C65: Xiaomi Smartwatch Watch Reloj S1 Active Ocean Blue Llamada | D65: 2899 | E65: =D65*0.069 -> 200.031 | F65: =D65*0.0215 -> 62.3285 | G65: 1829.1 | H65: 0.1 | I65: =H65*D65 -> 289.9 | J65: 62.5 | K65: =D65-G65-I65-J65-E65-F65 -> 455.1405 | L65: =K65/G65 -> 0.24883303 | M65: =D65-E65-F65-I65-J65 -> 2284.2405
B66: 1381059438 | C66: Audífonos Oem AirPods Pro Generación Compatible iPhone Andro | D66: 899 | E66: =D66*0.069 -> 62.031 | F66: =D66*0.0215 -> 19.3285 | G66: 627.34 | H66: 0.1 | I66: =H66*D66 -> 89.9 | J66: 67.5 | K66: =D66-G66-I66-J66-E66-F66 -> 32.9005 | L66: =K66/G66 -> 0.052444448 | M66: =D66-E66-F66-I66-J66 -> 660.2405
B67: 1319142008 | C67: Laptop Samsung Chromebook 4 Os 15.6 Intel N4000 4gb Ram 32 | D67: 8199 | E67: =D67*0.069 -> 565.731 | F67: =D67*0.0215 -> 176.2785 | H67: 0.1 | I67: =H67*D67 -> 819.9 | J67: 64 | K67: =D67-G67-I67-J67-E67-F67 -> 6573.0905 | L67: =K67/G67 -> #DIV/0! | M67: =D67-E67-F67-I67-J67 -> 6573.0905
B68: 1320625599 | C68: Laptop Samsung Chromebook 4 + 15.6´ Intel N4000 4gb Ram 64g | D68: 8999 | E68: =D68*0.069 -> 620.931 | F68: =D68*0.0215 -> 193.4785 | H68: 0.1 | I68: =H68*D68 -> 899.9 | J68: 130 | K68: =D68-G68-I68-J68-E68-F68 -> 7154.6905 | L68: =K68/G68 -> #DIV/0! | M68: =D68-E68-F68-I68-J68 -> 7154.6905
B69: 1325868037 | C69: Apple Watch Series 6 (gps+cellular) - Caja De Aluminio (product)red De 44 Mm - Correa Deportiva (product)red | D69: 12999 | E69: =D69*0.069 -> 896.931 | F69: =D69*0.0215 -> 279.4785 | G69: 10376.43 | H69: 0.1 | I69: =H69*D69 -> 1299.9 | J69: 62.5 | K69: =D69-G69-I69-J69-E69-F69 -> 83.7605 | L69: =K69/G69 -> 0.0080721886 | M69: =D69-E69-F69-I69-J69 -> 10460.191
B70: 1385992873 | C70: Laptop Hp Stream 14-cb174wm Brilliant Black 14 , Intel Celeron N4000 4gb De Ram 64gb Ssd, Intel Uhd Graphics 600 | D70: 6942 | E70: =D70*0.069 -> 478.998 | F70: =D70*0.0215 -> 149.253 | H70: 0.1 | I70: =H70*D70 -> 694.2 | J70: 78 | K70: =D70-G70-I70-J70-E70-F70 -> 5541.549 | L70: =K70/G70 -> #DIV/0! | M70: =D70-E70-F70-I70-J70 -> 5541.549
B71: 1309775400 | C71: Clavija | D71: 41.84 | E71: =D71*0.069 -> 2.88696 | F71: =D71*0.0215 -> 0.89956 | G71: =4.2*2 -> #ERROR! | H71: 0.1 | I71: =H71*D71 -> 4.184 | K71: =D71-G71-I71-J71-E71-F71 -> #ERROR! | L71: =K71/G71 -> #ERROR! | M71: =D71-E71-F71-I71-J71 -> 33.86948
B72: 1399695510 | C72: Lampara Amazon Echo Glow Wifi Rgb Compatible Alexa /u | D72: 549 | E72: =D72*0.069 -> 37.881 | F72: =D72*0.0215 -> 11.8035 | G72: 384.93 | H72: 0.1 | I72: =H72*D72 -> 54.9 | J72: 60 | K72: =D72-G72-I72-J72-E72-F72 -> -0.5145 | L72: =K72/G72 -> -0.0013366067 | M72: =D72-E72-F72-I72-J72 -> 384.4155
B73: 1399082547 | C73: Lentes De Realidad Virtual Oculus Quest 2 64gb 2022 New | D73: 7299 | E73: =D73*0.069 -> 503.631 | F73: =D73*0.0215 -> 156.9285 | G73: 5157.41 | H73: 0.1 | I73: =H73*D73 -> 729.9 | J73: 102.5 | K73: =D73-G73-I73-J73-E73-F73 -> 648.6305 | L73: =K73/G73 -> 0.12576671 | M73: =D73-E73-F73-I73-J73 -> 5806.0405
B74: 1325998574 | C74: Lentes De Realidad Virtual Oculus Quest 2 128gb Nuevo Sellad | D74: 6089 | E74: =D74*0.069 -> 420.141 | F74: =D74*0.0215 -> 130.9135 | G74: 4345.97 | H74: 0.195 | I74: =H74*D74 -> 1187.355 | J74: 110 | K74: =D74-G74-I74-J74-E74-F74 -> -105.3795 | L74: =K74/G74 -> -0.024247636 | M74: =D74-E74-F74-I74-J74 -> 4240.5905
B75: 2792817840 | C75: Oculus Quest 2 256gb Lentes Realidad Virtual All In One Vr * | D75: 6999 | E75: =D75*0.069 -> 482.931 | F75: =D75*0.0215 -> 150.4785 | G75: 5441.76 | H75: 0.1 | I75: =H75*D75 -> 699.9 | J75: 102.5 | K75: =D75-G75-I75-J75-E75-F75 -> 121.4305 | L75: =K75/G75 -> 0.022314564 | M75: =D75-E75-F75-I75-J75 -> 5563.1905
B76: 1379511873 | C76: Cargador Xiaomi Mi 20w Usb Tipo C Adaptador Carga Rapida Us | D76: 199 | E76: =D76*0.069 -> 13.731 | F76: =D76*0.0215 -> 4.2785 | G76: 123.11 | H76: 0.15 | I76: =H76*D76+30 -> 59.85 | K76: =D76-G76-I76-J76-E76-F76 -> -1.9695 | L76: =K76/G76 -> -0.015997888 | M76: =D76-E76-F76-I76-J76 -> 121.1405
B77: 1314416289 | C77: Cargador APPLE CREAR | E77: =D77*0.069 -> 0 | F77: =D77*0.0215 -> 0 | H77: 0.1 | I77: =H77*D77 -> 0 | J77: 78 | K77: =D77-G77-I77-J77-E77-F77 -> -78 | L77: =K77/G77 -> #DIV/0! | M77: =D77-E77-F77-I77-J77 -> -78
B78: 1400806060 | C78: Audífonos In-ear Inalámbricos Lenovo Livepods Lp40 Negro | D78: 290 | E78: =D78*0.069 -> 20.01 | F78: =D78*0.0215 -> 6.235 | G78: 168.47 | H78: 0.1 | I78: =H78*D78 -> 29 | J78: 57 | K78: =D78-G78-I78-J78-E78-F78 -> 9.285 | L78: =K78/G78 -> 0.05511367 | M78: =D78-E78-F78-I78-J78 -> 177.755
B79: 1400848064 | C79: Audífonos in-ear gamer inalámbricos Lenovo XG01 gris con luz LED | D79: 496 | E79: =D79*0.069 -> 34.224 | F79: =D79*0.0215 -> 10.664 | G79: 328.1 | H79: 0.1 | I79: =H79*D79 -> 49.6 | J79: 57 | K79: =D79-G79-I79-J79-E79-F79 -> 16.412 | L79: =K79/G79 -> 0.050021335 | M79: =D79-E79-F79-I79-J79 -> 344.512
B80: 1401274995 | C80: tablet Amazon Fire HD 10 32GB | D80: 2461 | E80: =D80*0.069 -> 169.809 | F80: =D80*0.0215 -> 52.9115 | G80: 2047.68 | H80: 0.1 | I80: =H80*D80 -> 246.1 | J80: 67.5 | K80: =D80-G80-I80-J80-E80-F80 -> -123.0005 | L80: =K80/G80 -> -0.060068224 | M80: =D80-E80-F80-I80-J80 -> 1924.6795
B81: 1401318947 | C81: tablet Amazon Fire HD 10 2021 KFTRWI 10.1" 32GB olive | D81: 2777 | E81: =D81*0.069 -> 191.613 | F81: =D81*0.0215 -> 59.7055 | G81: 2047.68 | H81: 0.1 | I81: =H81*D81 -> 277.7 | J81: 67.5 | K81: =D81-G81-I81-J81-E81-F81 -> 132.8015 | L81: =K81/G81 -> 0.064854616 | M81: =D81-E81-F81-I81-J81 -> 2180.4815
B82: 1401343631 | C82: tablet Amazon Fire HD 10 2021 KFTRWI 10.1" 32GB pink | D82: 2650 | E82: =D82*0.069 -> 182.85 | F82: =D82*0.0215 -> 56.975 | G82: 2047.68 | H82: 0.1 | I82: =H82*D82 -> 265 | J82: 67.5 | K82: =D82-G82-I82-J82-E82-F82 -> 29.995 | L82: =K82/G82 -> 0.014648285 | M82: =D82-E82-F82-I82-J82 -> 2077.675
B83: 1401343734 | C83: tablet Amazon Fire HD 10 2021 KFTRWI 10.1" 32GB | D83: 2800 | E83: =D83*0.069 -> 193.2 | F83: =D83*0.0215 -> 60.2 | G83: 2047.68 | H83: 0.1 | I83: =H83*D83 -> 280 | J83: 67.5 | K83: =D83-G83-I83-J83-E83-F83 -> 151.42 | L83: =K83/G83 -> 0.073947101 | M83: =D83-E83-F83-I83-J83 -> 2199.1
B84: 1404241750 | C84: Smartwatch Fitbit Sense 1.59 Caja De Aluminio Anodizado Graphite Stainless Steel, Malla Carbon De Elastómero Y Aluminio Anodizado Fb512 | D84: 5399 | E84: =D84*0.069 -> 372.531 | F84: =D84*0.0215 -> 116.0785 | G84: 4358.93 | H84: 0.1 | I84: =H84*D84 -> 539.9 | J84: 62.5 | K84: =D84-G84-I84-J84-E84-F84 -> -50.9395 | L84: =K84/G84 -> -0.01168624 | M84: =D84-E84-F84-I84-J84 -> 4307.9905
B85: 1404254755 | C85: Audífonos gamer inalámbricos HyperX Cloud Flight S shadow gray | D85: 3099 | E85: =D85*0.069 -> 213.831 | F85: =D85*0.0215 -> 66.6285 | G85: 2471.56 | H85: 0.1 | I85: =H85*D85 -> 309.9 | J85: 62.5 | K85: =D85-G85-I85-J85-E85-F85 -> -25.4195 | L85: =K85/G85 -> -0.0102848 | M85: =D85-E85-F85-I85-J85 -> 2446.1405
B86: 1404918760 | C86: Adaptador De Corriente Clavija Universal Internacional Viaje | D86: 49.99 | E86: =D86*0.069 -> 3.44931 | F86: =D86*0.0215 -> 1.074785 | G86: 10.17 | H86: 0.1 | I86: =H86*D86 -> 4.999 | K86: =D86-G86-I86-J86-E86-F86 -> 30.296905 | L86: =K86/G86 -> 2.9790467 | M86: =D86-E86-F86-I86-J86 -> 40.466905
B87: 1404952116 | C87: Tv Stick Xiaomi Mi 4k Con Chromecast Integrado Para Android | D87: 1199 | E87: =D87*0.069 -> 82.731 | F87: =D87*0.0215 -> 25.7785 | G87: 924.83 | H87: 0.1 | I87: =H87*D87 -> 119.9 | J87: 68 | K87: =D87-G87-I87-J87-E87-F87 -> -22.2395 | L87: =K87/G87 -> -0.024047122 | M87: =D87-E87-F87-I87-J87 -> 902.5905
B88: 1372374697 | C88: Audífonos in-ear gamer inalámbricos Xiaomi Redmi AirDots 3 Pro negro grafito | D88: 1314 | E88: =D88*0.069 -> 90.666 | F88: =D88*0.0215 -> 28.251 | G88: 989.55 | H88: 0.1 | I88: =H88*D88 -> 131.4 | J88: 62.5 | K88: =D88-G88-I88-J88-E88-F88 -> 11.633 | L88: =K88/G88 -> 0.011755849 | M88: =D88-E88-F88-I88-J88 -> 1001.183
C89: Lenovo He05x Audífonos Blutetooth Deportivos Ipx5 Micrófono | D89: 189 | E89: =D89*0.069 -> 13.041 | F89: =D89*0.0215 -> 4.0635 | G89: 102.8 | H89: 0.1 | I89: =H89*D89 -> 18.9 | K89: =D89-G89-I89-J89-E89-F89 -> 50.1955 | L89: =K89/G89 -> 0.48828307 | M89: =D89-E89-F89-I89-J89 -> 152.9955
B90: 962408543 | C90: Amazon Alexa Echo-auto Auto Inteligente Nuevo Asistente | D90: 782 | E90: =D90*0.069 -> 53.958 | F90: =D90*0.0215 -> 16.813 | G90: 544.38 | H90: 0.1 | I90: =H90*D90 -> 78.2 | J90: 78 | K90: =D90-G90-I90-J90-E90-F90 -> 10.649 | L90: =K90/G90 -> 0.019561703 | M90: =D90-E90-F90-I90-J90 -> 555.029
B91: 1416232026 | C91: Haylou GT7 | D91: 442 | E91: =D91*0.069 -> 30.498 | F91: =D91*0.0215 -> 9.503 | G91: 320.13 | H91: 0.1 | I91: =H91*D91 -> 44.2 | J91: 84 | K91: =D91-G91-I91-J91-E91-F91 -> -46.331 | L91: =K91/G91 -> -0.14472558 | M91: =D91-E91-F91-I91-J91 -> 273.799
B92: 2114085232 | C92: Buds 3 lite | D92: 190 | E92: =D92*0.069 -> 13.11 | F92: =D92*0.0215 -> 4.085 | G92: 163.64 | H92: 0.1 | I92: =H92*D92 -> 19 | K92: =D92-G92-I92-J92-E92-F92 -> -9.835 | L92: =K92/G92 -> -0.060101442 | M92: =D92-E92-F92-I92-J92 -> 153.805
B93: 1385992873 | C93: HP-14-CB174WM NEGRO | D93: 5259 | E93: =D93*0.069 -> 362.871 | F93: =D93*0.0215 -> 113.0685 | G93: 3907.81 | H93: 0.1 | I93: =H93*D93 -> 525.9 | J93: 78 | K93: =D93-G93-I93-J93-E93-F93 -> 271.3505 | L93: =K93/G93 -> 0.069437997 | M93: =D93-E93-F93-I93-J93 -> 4179.1605
B94: 1416256466 | C94: Alexa 4 hub | D94: 1980 | E94: =D94*0.069 -> 136.62 | F94: =D94*0.0215 -> 42.57 | G94: 1588.13 | H94: 0.1 | I94: =H94*D94 -> 198 | J94: 67 | K94: =D94-G94-I94-J94-E94-F94 -> -52.32 | L94: =K94/G94 -> -0.032944406 | M94: =D94-E94-F94-I94-J94 -> 1535.81
B95: 5457683929 | C95: Clavija x2 | D95: 42.99 | E95: =D95*0.069 -> 2.96631 | F95: =D95*0.0215 -> 0.924285 | G95: 8.5 | H95: 0.1 | I95: =H95*D95 -> 4.299 | K95: =D95-G95-I95-J95-E95-F95 -> 26.300405 | L95: =K95/G95 -> 3.0941653 | M95: =D95-E95-F95-I95-J95 -> 34.800405
B96: 905167527 | C96: Laptop Acer 315 Chromebook 15.6 Celeron 4gb Ram 32gb | D96: 6299 | E96: =D96*0.069 -> 434.631 | F96: =D96*0.0215 -> 135.4285 | G96: 4648.06 | H96: 0.1 | I96: =H96*D96 -> 629.9 | J96: 84 | K96: =D96-G96-I96-J96-E96-F96 -> 366.9805 | L96: =K96/G96 -> 0.078953477 | M96: =D96-E96-F96-I96-J96 -> 5015.0405
B97: 963489127 | C97: Laptop Hp 14´´hd Chromebook Celeron 4gb Ram 32gb N3350 Intel | D97: 4999 | E97: =D97*0.069 -> 344.931 | F97: =D97*0.0215 -> 107.4785 | G97: 3631.37 | H97: 0.1 | I97: =H97*D97 -> 499.9 | J97: 84 | K97: =D97-G97-I97-J97-E97-F97 -> 331.3205 | L97: =K97/G97 -> 0.091238431 | M97: =D97-E97-F97-I97-J97 -> 3962.6905
B98: 1419045776 | C98: Mi band 6 | D98: 688 | E98: =D98*0.069 -> 47.472 | F98: =D98*0.0215 -> 14.792 | G98: 519 | H98: 0.1 | I98: =H98*D98 -> 68.8 | J98: 66.5 | K98: =D98-G98-I98-J98-E98-F98 -> -28.564 | L98: =K98/G98 -> -0.055036609 | M98: =D98-E98-F98-I98-J98 -> 490.436
B99: 958290599 | C99: Tv stick Xiaomi | D99: 710 | E99: =D99*0.069 -> 48.99 | F99: =D99*0.0215 -> 15.265 | G99: 516.44 | H99: 0.15 | I99: =H99*D99 -> 106.5 | K99: =D99-G99-I99-J99-E99-F99 -> 22.805 | L99: =K99/G99 -> 0.044158082 | M99: =D99-E99-F99-I99-J99 -> 539.245
A100: 1422756437 | B100: 1422781291 | C100: Router 4C | D100: 284 | E100: =D100*0.069 -> 19.596 | F100: =D100*0.0215 -> 6.106 | G100: 200 | H100: 0.1 | I100: =H100*D100 -> 28.4 | J100: 35 | K100: =D100-G100-I100-J100-E100-F100 -> -5.102 | L100: =K100/G100 -> -0.02551 | M100: =D100-E100-F100-I100-J100 -> 194.898
B101: 1422756437 | C101: Router 4C | D101: 266 | E101: =D101*0.069 -> 18.354 | F101: =D101*0.0215 -> 5.719 | G101: 200 | H101: 0.1 | I101: =H101*D101 -> 26.6 | J101: 35 | K101: =D101-G101-I101-J101-E101-F101 -> -19.673 | L101: =K101/G101 -> -0.098365 | M101: =D101-E101-F101-I101-J101 -> 180.327
...

Sheet AMZ
A2: Amazon
A3: Producto | B3: ASIN | C3: SKU | D3: Precio de venta | E3: Estatus | F3: Retenciones | H3: Costo | I3: Comision | J3: Comison | K3: Sin iVA | L3: Envio | M3: Utilidad | N3: ROI | O3: Ingreso x venta
A4: Mi Box | B4: B07KB1KLYN | D4: 1199 | F4: =D4*0.069 -> 82.731 | H4: 849.99 | I4: 0.1 | J4: =I4*D4 -> 119.9 | K4: =J4/1.16 -> 103.36207 | L4: 66.04 | M4: =D4-H4-J4-L4-F4-G4 -> 80.339 | N4: =M4/H4 -> 0.094517583
A5: Mi Band 5 | B5: B089NS9JW2 | D5: 532 | F5: =D5*0.069 -> 36.708 | H5: 400 | I5: 0.15 | J5: =I5*D5 -> 79.8 | K5: =J5/1.16 -> 68.793103 | M5: =D5-H5-J5-L5-F5-G5 -> 15.492 | N5: =M5/H5 -> 0.03873
A6: Mi Projector 2 | B6: B08RMX5XVR | F6: =D6*0.069 -> 0 | H6: 8350.23 | I6: 0.1 | J6: =I6*D6 -> 0 | K6: =J6/1.16 -> 0 | M6: =D6-H6-J6-L6-F6-G6 -> -8350.23 | N6: =M6/H6 -> -1
A7: Roku 4k+ | B7: B0916TKFF2 | D7: 859 | F7: =D7*0.069 -> 59.271 | H7: 629.71 | I7: 0.1 | J7: =I7*D7 -> 85.9 | K7: =J7/1.16 -> 74.051724 | M7: =D7-H7-J7-L7-F7-G7 -> 84.119 | N7: =M7/H7 -> 0.13358371
A8: Roku exprees | B8: B07WVFCVJN | D8: 699 | F8: =D8*0.069 -> 48.231 | H8: 472.46 | I8: 0.1 | J8: =I8*D8 -> 69.9 | K8: =J8/1.16 -> 60.258621 | M8: =D8-H8-J8-L8-F8-G8 -> 108.409 | N8: =M8/H8 -> 0.22945646
A9: Aura | B9: B0C4FYKW24 | D9: 4399 | F9: =D9*0.069 -> 303.531 | H9: 3488.27 | I9: 0.1 | J9: =I9*D9 -> 439.9 | K9: =J9/1.16 -> 379.22414 | L9: 109.85 | M9: =D9-H9-J9-L9-F9-G9 -> 57.449 | N9: =M9/H9 -> 0.016469195
A10: Roku4k streaming | B10: B09BKCDXZC | D10: 770 | F10: =D10*0.069 -> 53.13 | H10: 623.52 | I10: 0.1 | J10: =I10*D10 -> 77 | K10: =J10/1.16 -> 66.37931 | L10: 66.04 | M10: =D10-H10-J10-L10-F10-G10 -> -49.69 | N10: =M10/H10 -> -0.079692712
A11: Scooter essential | B11: B089NR5WZ8 | D11: 7999 | F11: =D11*0.069 -> 551.931 | H11: 5200 | I11: 0.15 | J11: =I11*D11 -> 1199.85 | K11: =J11/1.16 -> 1034.3534 | L11: 400 | M11: =D11-H11-J11-L11-F11-G11 -> 647.219 | N11: =M11/H11 -> 0.12446519
A12: Clavija | B12: B091V6V2CL | D12: 99 | F12: =D12*0.069 -> 6.831 | H12: 9 | I12: 0.15 | J12: =I12*D12 -> 14.85 | K12: =J12/1.16 -> 12.801724 | M12: =D12-H12-J12-L12-F12-G12 -> 68.319 | N12: =M12/H12 -> 7.591
A13: Aspiradora Mop 1C | B13: B086W5Y1CG | D13: 6399 | F13: =D13*0.069 -> 441.531 | H13: 4500 | I13: 0.15 | J13: =I13*D13 -> 959.85 | K13: =J13/1.16 -> 827.4569 | M13: =D13-H13-J13-L13-F13-G13 -> 497.619 | N13: =M13/H13 -> 0.110582
A14: Earphones Blancos | B14: B08BRGH7S3 | D14: 545 | F14: =D14*0.069 -> 37.605 | H14: 347.85 | I14: 0.15 | J14: =I14*D14 -> 81.75 | K14: =J14/1.16 -> 70.474138 | M14: =D14-H14-J14-L14-F14-G14 -> 77.795 | N14: =M14/H14 -> 0.22364525
A15: Buds 3 PRO | B15: B09C3W56FC | D15: 759 | F15: =D15*0.069 -> 52.371 | H15: 530.77 | I15: 0.1 | J15: =I15*D15 -> 75.9 | K15: =J15/1.16 -> 65.431034 | M15: =D15-H15-J15-L15-F15-G15 -> 99.959 | N15: =M15/H15 -> 0.18832828
A16: Router 4A | B16: B085G5CDY7 | D16: 419 | F16: =D16*0.069 -> 28.911 | H16: 270.12 | I16: 0.1 | J16: =I16*D16 -> 41.9 | K16: =J16/1.16 -> 36.12069 | M16: =D16-H16-J16-L16-F16-G16 -> 78.069 | N16: =M16/H16 -> 0.28901599
A17: Router 4c | B17: B09HSV3JZ5 | C17: B09HSV3JZ5-new4c | D17: 339 | F17: =D17*0.069 -> 23.391 | H17: 200 | I17: 0.1 | J17: =I17*D17 -> 33.9 | K17: =J17/1.16 -> 29.224138 | L17: 67.45 | M17: =D17-H17-J17-L17-F17-G17 -> 14.259 | N17: =M17/H17 -> 0.071295
A18: Tablet ONN | B18: B09FBZ4D9T | D18: 1599 | F18: =D18*0.069 -> 110.331 | H18: 1021.82 | I18: 0.1 | J18: =I18*D18 -> 159.9 | K18: =J18/1.16 -> 137.84483 | M18: =D18-H18-J18-L18-F18-G18 -> 306.949 | N18: =M18/H18 -> 0.30039439
A19: Mi Speaker 2 | B19: B07RD3FNTN | D19: 232 | F19: =D19*0.069 -> 16.008 | H19: 179.45 | I19: 0.1 | J19: =I19*D19 -> 23.2 | K19: =J19/1.16 -> 20 | M19: =D19-H19-J19-L19-F19-G19 -> 13.342 | N19: =M19/H19 -> 0.074349401
A20: Razer Tournament | B20: B075M47H3H | F20: =D20*0.069 -> 0 | I20: 0.1 | J20: =I20*D20 -> 0 | K20: =J20/1.16 -> 0 | M20: =D20-H20-J20-L20-F20-G20 -> 0 | N20: =M20/H20 -> #DIV/0!
A21: Mi Band 6 | B21: B091G3FLL7 | D21: 799 | F21: =D21*0.069 -> 55.131 | H21: 519 | I21: 0.15 | J21: =I21*D21 -> 119.85 | K21: =J21/1.16 -> 103.31897 | M21: =D21-H21-J21-L21-F21-G21 -> 105.019 | N21: =M21/H21 -> 0.20234875
A22: Buds 3 lite | B22: B09NQKCQWS | D22: 479 | F22: =D22*0.069 -> 33.051 | H22: 163.64 | I22: 0.15 | J22: =I22*D22 -> 71.85 | K22: =J22/1.16 -> 61.939655 | M22: =D22-H22-J22-L22-F22-G22 -> 210.459 | N22: =M22/H22 -> 1.2861098
A23: Aspiradora Mop P | B23: B085BP7ZC5 | D23: 8499 | F23: =D23*0.069 -> 586.431 | H23: 6161.78 | I23: 0.15 | J23: =I23*D23 -> 1274.85 | K23: =J23/1.16 -> 1099.0086 | M23: =D23-H23-J23-L23-F23-G23 -> 475.939 | N23: =M23/H23 -> 0.077240505
A24: Watch S1 | B24: B09S8BKKHB | D24: 1977 | F24: =D24*0.069 -> 136.413 | H24: 1183.46 | I24: 0.16 | J24: =I24*D24 -> 316.32 | K24: =J24/1.16 -> 272.68966 | M24: =D24-H24-J24-L24-F24-G24 -> 340.807 | N24: =M24/H24 -> 0.28797509
A25: Buds 3 | B25: B09J4T4JF5 | D25: 439 | F25: =D25*0.069 -> 30.291 | H25: 274.78 | I25: 0.15 | J25: =I25*D25 -> 65.85 | K25: =J25/1.16 -> 56.767241 | M25: =D25-H25-J25-L25-F25-G25 -> 68.079 | N25: =M25/H25 -> 0.24775821
A26: Repetidor Xiaomi | B26: B0762SH6WG | D26: 329 | F26: =D26*0.069 -> 22.701 | H26: 229.36 | I26: 0.1 | J26: =I26*D26 -> 32.9 | K26: =J26/1.16 -> 28.362069 | M26: =D26-H26-J26-L26-F26-G26 -> 44.039 | N26: =M26/H26 -> 0.1920082
A27: Repetidor Xiaomi | B27: B084WT4WWK | D27: 299 | F27: =D27*0.069 -> 20.631 | H27: 180 | I27: 0.1 | J27: =I27*D27 -> 29.9 | K27: =J27/1.16 -> 25.775862 | L27: 69 | M27: =D27-H27-J27-L27-F27-G27 -> -0.531 | N27: =M27/H27 -> -0.00295
A28: Cargador Xiaomi Tipo c 20W | B28: B0969PK3SG | D28: 359 | F28: =D28*0.069 -> 24.771 | H28: 207.48 | I28: 0.15 | J28: =I28*D28 -> 53.85 | K28: =J28/1.16 -> 46.422414 | M28: =D28-H28-J28-L28-F28-G28 -> 72.899 | N28: =M28/H28 -> 0.35135435
A29: Xiaomi Pad 5 256 gb | B29: B09JBZQG49 | D29: 10599 | F29: =D29*0.069 -> 731.331 | H29: 8689.0468 | I29: 0.1 | J29: =I29*D29 -> 1059.9 | K29: =J29/1.16 -> 913.7069 | M29: =D29-H29-J29-L29-F29-G29 -> 118.7222 | N29: =M29/H29 -> 0.013663432
A30: Xiaomi Pad 5 128 gb | B30: B09JBZP2WR | D30: 9590 | F30: =D30*0.069 -> 661.71 | H30: 7847.8477 | I30: 0.1 | J30: =I30*D30 -> 959 | K30: =J30/1.16 -> 826.72414 | M30: =D30-H30-J30-L30-F30-G30 -> 121.4423 | N30: =M30/H30 -> 0.015474599
A31: Mi watch | B31: B08P5J7KGH | D31: 2599 | F31: =D31*0.069 -> 179.331 | H31: 1488 | I31: 0.15 | J31: =I31*D31 -> 389.85 | K31: =J31/1.16 -> 336.07759 | M31: =D31-H31-J31-L31-F31-G31 -> 541.819 | N31: =M31/H31 -> 0.36412567
A32: Camara 360 | B32: B093C8S6B1 | D32: 599 | F32: =D32*0.069 -> 41.331 | H32: 391 | I32: 0.15 | J32: =I32*D32 -> 89.85 | K32: =J32/1.16 -> 77.456897 | L32: 66.04 | M32: =D32-H32-J32-L32-F32-G32 -> 10.779 | N32: =M32/H32 -> 0.027567775
A33: Camara 360 | B33: B07P12T1G3 | D33: 999 | F33: =D33*0.069 -> 68.931 | H33: 340 | I33: 0.15 | J33: =I33*D33 -> 149.85 | K33: =J33/1.16 -> 129.18103 | M33: =D33-H33-J33-L33-F33-G33 -> 440.219 | N33: =M33/H33 -> 1.2947618
A34: Xiaomi Smart Camera C300 White bhr6540gl… | B34: B0B6PG6S81 | D34: 1199 | F34: =D34*0.069 -> 82.731 | H34: 789 | I34: 0.15 | J34: =I34*D34 -> 179.85 | K34: =J34/1.16 -> 155.0431 | L34: 67 | M34: =D34-H34-J34-L34-F34-G34 -> 80.419 | N34: =M34/H34 -> 0.10192522
A35: Mop 2 nueva 1c | B35: B09R8WM46V | D35: 5999 | F35: =D35*0.069 -> 413.931 | H35: 4324.97 | I35: 0.15 | J35: =I35*D35 -> 899.85 | K35: =J35/1.16 -> 775.73276 | M35: =D35-H35-J35-L35-F35-G35 -> 360.249 | N35: =M35/H35 -> 0.083295144
A36: Pilas AAA | B36: B00VQVVOTS | D36: 149 | F36: =D36*0.069 -> 10.281 | H36: 65.54 | I36: 0.15 | J36: =I36*D36 -> 22.35 | K36: =J36/1.16 -> 19.267241 | M36: =D36-H36-J36-L36-F36-G36 -> 50.829 | N36: =M36/H36 -> 0.77554165
A37: Pilas AA | B37: B00V7FQUOM | D37: 172 | F37: =D37*0.069 -> 11.868 | H37: 82.59 | I37: 0.15 | J37: =I37*D37 -> 25.8 | K37: =J37/1.16 -> 22.241379 | M37: =D37-H37-J37-L37-F37-G37 -> 51.742 | N37: =M37/H37 -> 0.62649231
A38: Cargador de Pilas | B38: B078XL37LQ | D38: 259 | F38: =D38*0.069 -> 17.871 | H38: 149.64 | I38: 0.15 | J38: =I38*D38 -> 38.85 | K38: =J38/1.16 -> 33.491379 | M38: =D38-H38-J38-L38-F38-G38 -> 52.639 | N38: =M38/H38 -> 0.35177092
A39: Aspiradora Xiaomi Mop 2 Lite | B39: B09TFYRVG9 | D39: 4999 | F39: =D39*0.069 -> 344.931 | H39: 3675.8 | I39: 0.15 | J39: =I39*D39 -> 749.85 | K39: =J39/1.16 -> 646.42241 | M39: =D39-H39-J39-L39-F39-G39 -> 228.419 | N39: =M39/H39 -> 0.062141303
A40: Acer Chromebook Spin 311, CP311-2H-C7QD, 4 GB, 64 GB, Plateado | B40: B08NTP5RTN | D40: 5699 | F40: =D40*0.069 -> 393.231 | H40: 4048.08 | I40: 0.1 | J40: =I40*D40 -> 569.9 | K40: =J40/1.16 -> 491.2931 | M40: =D40-H40-J40-L40-F40-G40 -> 687.789 | N40: =M40/H40 -> 0.16990499
A41: Samsund Laptop | B41: B07XQQTVS3 | D41: 4499 | F41: =D41*0.069 -> 310.431 | H41: 3596.22 | I41: 0.1 | J41: =I41*D41 -> 449.9 | K41: =J41/1.16 -> 387.84483 | M41: =D41-H41-J41-L41-F41-G41 -> 142.449 | N41: =M41/H41 -> 0.039610758
A42: Xiaomi Smartwatch Redmi Watch 2 Lite… | B42: B09PF98LX4 | D42: 1299 | F42: =D42*0.069 -> 89.631 | H42: 943.02 | I42: 0.15 | J42: =I42*D42 -> 194.85 | K42: =J42/1.16 -> 167.97414 | M42: =D42-H42-J42-L42-F42-G42 -> 71.499 | N42: =M42/H42 -> 0.075819177
A43: Xiaomi Redmi AirDots 2 auriculares básicos 2 auriculares inalámbricos Bluetooth 5.0 estéreo Touch Control S 1PX4 impermeable con funda de carga TWSEJ061LS | B43: B08GNXRGVX | D43: 519 | F43: =D43*0.069 -> 35.811 | H43: 294.35 | I43: 0.15 | J43: =I43*D43 -> 77.85 | K43: =J43/1.16 -> 67.112069 | M43: =D43-H43-J43-L43-F43-G43 -> 110.989 | N43: =M43/H43 -> 0.37706472
A44: Razer Hammerhead True Wireless X - Auriculares de baja latencia (60 ms modo de juego de baja latencia, personalización de aplicaciones móviles, controladores personalizados de 13 mm, Bluetooth 5.2 con emparejamiento automático, Google Fast Pair), col… | B44: B08Z4GQS4X | D44: 799 | F44: =D44*0.069 -> 55.131 | H44: 546.49 | I44: 0.15 | J44: =I44*D44 -> 119.85 | K44: =J44/1.16 -> 103.31897 | M44: =D44-H44-J44-L44-F44-G44 -> 77.529 | N44: =M44/H44 -> 0.14186719
A45: Tv stick 4k | B45: B09RZHVDGS | D45: 999 | F45: =D45*0.069 -> 68.931 | H45: 773.8 | I45: 0.15 | J45: =I45*D45 -> 149.85 | K45: =J45/1.16 -> 129.18103 | M45: =D45-H45-J45-L45-F45-G45 -> 6.419 | N45: =M45/H45 -> 0.0082954252
A46: Haylou gt7 | B46: B09HXSW5ZX | D46: 499 | F46: =D46*0.069 -> 34.431 | H46: 320.13 | I46: 0.15 | J46: =I46*D46 -> 74.85 | K46: =J46/1.16 -> 64.525862 | M46: =D46-H46-J46-L46-F46-G46 -> 69.589 | N46: =M46/H46 -> 0.21737732
A47: Clavija Blanca | B47: B07FFBD8XP | D47: 107 | F47: =D47*0.069 -> 7.383 | H47: =10.17*2 -> #ERROR! | I47: 0.15 | J47: =I47*D47 -> 16.05 | K47: =J47/1.16 -> 13.836207 | M47: =D47-H47-J47-L47-F47-G47 -> #ERROR! | N47: =M47/H47 -> #ERROR!
A48: Speaker azul | B48: B08MKQ6DXJ | D48: 629 | F48: =D48*0.069 -> 43.401 | H48: 425 | I48: 0.1 | J48: =I48*D48 -> 62.9 | K48: =J48/1.16 -> 54.224138 | L48: 72 | M48: =D48-H48-J48-L48-F48-G48 -> 25.699 | N48: =M48/H48 -> 0.060468235 | P48: DEAL
A49: Monitor Bar | B49: B09X13LS7F | D49: 939 | F49: =D49*0.069 -> 64.791 | H49: 608.73 | I49: 0.1 | J49: =I49*D49 -> 93.9 | K49: =J49/1.16 -> 80.948276 | L49: 75.38 | M49: =D49-H49-J49-L49-F49-G49 -> 96.199 | N49: =M49/H49 -> 0.1580323
A50: Samsung Tab A8 | B50: B08QQTQNDC | D50: 4299 | F50: =D50*0.069 -> 296.631 | H50: 3177.28 | I50: 0.1 | J50: =I50*D50 -> 429.9 | K50: =J50/1.16 -> 370.60345 | M50: =D50-H50-J50-L50-F50-G50 -> 395.189 | N50: =M50/H50 -> 0.12437966
A51: Tv stick | B51: B09LPTSRMH | D51: 849 | F51: =D51*0.069 -> 58.581 | H51: 614.8 | I51: 0.15 | J51: =I51*D51 -> 127.35 | K51: =J51/1.16 -> 109.78448 | M51: =D51-H51-J51-L51-F51-G51 -> 48.269 | N51: =M51/H51 -> 0.078511711
A52: aspiradora Mini Xiaomi | B52: B08MPQQJHQ | D52: 899 | F52: =D52*0.069 -> 62.031 | H52: 560 | I52: 0.15 | J52: =I52*D52 -> 134.85 | K52: =J52/1.16 -> 116.25 | L52: 70 | M52: =D52-H52-J52-L52-F52-G52 -> 72.119 | N52: =M52/H52 -> 0.12878393
A53: Scooter S1 | B53: B076KKX4BC | D53: 10599 | F53: =D53*0.069 -> 731.331 | H53: 6325 | I53: 0.15 | J53: =I53*D53 -> 1589.85 | K53: =J53/1.16 -> 1370.5603 | M53: =D53-H53-J53-L53-F53-G53 -> 1952.819 | N53: =M53/H53 -> 0.30874609
A54: Teclado Cyrosa V2 | B54: B089KLHYG3 | D54: 1199 | F54: =D54*0.069 -> 82.731 | H54: 845.234 | I54: 0.1 | J54: =I54*D54 -> 119.9 | K54: =J54/1.16 -> 103.36207 | M54: =D54-H54-J54-L54-F54-G54 -> 151.135 | N54: =M54/H54 -> 0.17880847
A55: Audifono Blackshark V2 | F55: =D55*0.069 -> 0 | H55: 997.6 | J55: =I55*D55 -> 0 | K55: =J55/1.16 -> 0 | M55: =D55-H55-J55-L55-F55-G55 -> -997.6
A56: Teclado Ornata V2 | B56: B086TKHRSN | D56: 1799 | F56: =D56*0.069 -> 124.131 | H56: 1305.3712 | I56: 0.15 | J56: =I56*D56 -> 269.85 | K56: =J56/1.16 -> 232.62931 | M56: =D56-H56-J56-L56-F56-G56 -> 99.6478 | N56: =M56/H56 -> 0.076336754
A57: Microfono Seiren | B57: B08HGJ8M4N | D57: 799 | F57: =D57*0.069 -> 55.131 | H57: 500 | I57: 0.1 | J57: =I57*D57 -> 79.9 | K57: =J57/1.16 -> 68.87931 | M57: =D57-H57-J57-L57-F57-G57 -> 163.969 | N57: =M57/H57 -> 0.327938
A58: Audifono Kraken Xlite | B58: B081GJ938B | D58: 494 | F58: =D58*0.069 -> 34.086 | H58: 350 | I58: 0.1 | J58: =I58*D58 -> 49.4 | K58: =J58/1.16 -> 42.586207 | M58: =D58-H58-J58-L58-F58-G58 -> 60.514 | N58: =M58/H58 -> 0.17289714
A59: Razer DeathAdder V2 Mini - Ratón gaming ergonómico con cable - Edición Negro EstándarWindows Vista; Windows XP; Mac; linux… | B59: B08B3K9K6P | D59: 449 | F59: =D59*0.069 -> 30.981 | H59: 234.09 | I59: 0.1 | J59: =I59*D59 -> 44.9 | K59: =J59/1.16 -> 38.706897 | M59: =D59-H59-J59-L59-F59-G59 -> 139.029 | N59: =M59/H59 -> 0.5939126
A60: Razer Blackshark V 2 X GREEN | B60: B09CLWQ45V | D60: 799 | F60: =D60*0.069 -> 55.131 | H60: 423 | I60: 0.15 | J60: =I60*D60 -> 119.85 | K60: =J60/1.16 -> 103.31897 | M60: =D60-H60-J60-L60-F60-G60 -> 201.019 | N60: =M60/H60 -> 0.47522222
A61: Razer Game wolverine V2 white | B61: B09C13DWYL | D61: 1799 | F61: =D61*0.069 -> 124.131 | H61: 1350 | I61: 0.1 | J61: =I61*D61 -> 179.9 | K61: =J61/1.16 -> 155.08621 | M61: =D61-H61-J61-L61-F61-G61 -> 144.969 | N61: =M61/H61 -> 0.10738444
A62: Razer kiyo webcam | B62: B09FNX2PLL | D62: 1199 | F62: =D62*0.069 -> 82.731 | H62: =1319-619 -> 700 | I62: 0.15 | J62: =I62*D62 -> 179.85 | K62: =J62/1.16 -> 155.0431 | M62: =D62-H62-J62-L62-F62-G62 -> 236.419 | N62: =M62/H62 -> 0.33774143
A63: Razer Headset v2 x Negro | B63: B086PKMZ21 | D63: 799 | F63: =D63*0.069 -> 55.131 | H63: 549 | I63: 0.1 | J63: =I63*D63 -> 79.9 | K63: =J63/1.16 -> 68.87931 | M63: =D63-H63-J63-L63-F63-G63 -> 114.969 | N63: =M63/H63 -> 0.2094153
A64: Buds 3 lite blancos | B64: B09NY2HZFQ | D64: 449 | F64: =D64*0.069 -> 30.981 | H64: 278.45 | I64: 0.15 | J64: =I64*D64 -> 67.35 | K64: =J64/1.16 -> 58.060345 | M64: =D64-H64-J64-L64-F64-G64 -> 72.219 | N64: =M64/H64 -> 0.25936075
A65: Mi bODY Scale composition | B65: B07VD9F419 | D65: 459 | F65: =D65*0.069 -> 31.671 | H65: 266.05 | I65: 0.15 | J65: =I65*D65 -> 68.85 | K65: =J65/1.16 -> 59.353448 | M65: =D65-H65-J65-L65-F65-G65 -> 92.429 | N65: =M65/H65 -> 0.34741214
A66: Xiaomi Reloj Inteligente Smartwatch Watch S1 Active GL (Moon White)… | B66: B09S8RCGSC | D66: 1699 | F66: =D66*0.069 -> 117.231 | H66: 1183.46 | I66: 0.15 | J66: =I66*D66 -> 254.85 | K66: =J66/1.16 -> 219.69828 | M66: =D66-H66-J66-L66-F66-G66 -> 143.459 | N66: =M66/H66 -> 0.12121998
A67: Reloj Inteligente Smartwatch Xiaomi Watch S1 (Silver)… | B67: B09TR69KGF | D67: 3999 | F67: =D67*0.069 -> 275.931 | H67: 3207.61 | I67: 0.1 | J67: =I67*D67 -> 399.9 | K67: =J67/1.16 -> 344.74138 | M67: =D67-H67-J67-L67-F67-G67 -> 115.559 | N67: =M67/H67 -> 0.036026512
A68: Reloj Inteligente Smartwatch Xiaomi Watch S1 (Black)… | B68: B09TR5XVML | D68: 3499 | F68: =D68*0.069 -> 241.431 | H68: 1970 | I68: 0.14 | J68: =I68*D68 -> 489.86 | K68: =J68/1.16 -> 422.2931 | M68: =D68-H68-J68-L68-F68-G68 -> 797.709 | N68: =M68/H68 -> 0.40492843
A69: Arlo | B69: B08NTGL8MB | D69: 7599 | F69: =D69*0.069 -> 524.331 | H69: 4840.06 | I69: 0.15 | J69: =I69*D69 -> 1139.85 | K69: =J69/1.16 -> 982.62931 | M69: =D69-H69-J69-L69-F69-G69 -> 1094.759 | N69: =M69/H69 -> 0.22618707
A70: Xiaomi Mi 360° Home Security Camera 2K Pro… | B70: B08P5G51GN | D70: 799 | F70: =D70*0.069 -> 55.131 | H70: 558.75 | I70: 0.1 | J70: =I70*D70 -> 79.9 | K70: =J70/1.16 -> 68.87931 | M70: =D70-H70-J70-L70-F70-G70 -> 105.219 | N70: =M70/H70 -> 0.18831141
A71: Kraken Mercury | B71: B07SKCLW2G | D71: 799 | F71: =D71*0.069 -> 55.131 | H71: 580 | I71: 0.1 | J71: =I71*D71 -> 79.9 | K71: =J71/1.16 -> 68.87931 | M71: =D71-H71-J71-L71-F71-G71 -> 83.969 | N71: =M71/H71 -> 0.14477414
A72: Razer Gigantus v2 -Mouse mat para Videojuegos mediano… | B72: B088539GLT | D72: 249 | F72: =D72*0.069 -> 17.181 | H72: 134.36 | I72: 0.1 | J72: =I72*D72 -> 24.9 | K72: =J72/1.16 -> 21.465517 | M72: =D72-H72-J72-L72-F72-G72 -> 72.559 | N72: =M72/H72 -> 0.54003424
A73: Xiaomi Audífonos Inálambricos Buds 3T Pro Carbon Grey… | B73: B09R9JY2RZ | D73: 2299 | F73: =D73*0.069 -> 158.631 | H73: 1731.07 | I73: 0.14 | J73: =I73*D73 -> 321.86 | K73: =J73/1.16 -> 277.46552 | M73: =D73-H73-J73-L73-F73-G73 -> 87.439 | N73: =M73/H73 -> 0.050511533
A74: Wolverine Control V2 | B74: B08LRTTGM6 | D74: 1240 | F74: =D74*0.069 -> 85.56 | H74: 882.46 | I74: 0.15 | J74: =I74*D74 -> 186 | K74: =J74/1.16 -> 160.34483 | M74: =D74-H74-J74-L74-F74-G74 -> 85.98 | N74: =M74/H74 -> 0.097432178
... A76: Xiaomi Audífonos Inalámbricos Buds 3 Carbon Black | B76: B09S2Z86R4 | D76: 1860 | F76: =D76*0.069 -> 128.34 | H76: 1360.49 | I76: 0.15 | J76: =I76*D76 -> 279 | K76: =J76/1.16 -> 240.51724 | M76: =D76-H76-J76-L76-F76-G76 -> 92.17 | N76: =M76/H76 -> 0.06774765
A77: Bomba | B77: B09JZWJ2QY | D77: 799 | F77: =D77*0.069 -> 55.131 | H77: 530 | I77: 0.15 | J77: =I77*D77 -> 119.85 | K77: =J77/1.16 -> 103.31897 | L77: 69.87 | M77: =D77-H77-J77-L77-F77-G77 -> 24.149 | N77: =M77/H77 -> 0.045564151
A78: Razer Kraken color negro - Audifonos Gaming 3.5 mm multiplataforma ( PC, XBOX , PS4,SWITCH, MOBIL , TABLET) | B78: B07N85FY1G | D78: 652 | F78: =D78*0.069 -> 44.988 | H78: 330.99 | I78: 0.16 | J78: =I78*D78 -> 104.32 | K78: =J78/1.16 -> 89.931034 | M78: =D78-H78-J78-L78-F78-G78 -> 171.702 | N78: =M78/H78 -> 0.51875283
A79: Razer Razer BlackShark V2 - Headset Multi plataforma con Tarjeta de Sonido Negro StandardWindows Vista; Windows XP; Mac; Linux… | B79: B086PKMZ1Q | D79: 1319 | F79: =D79*0.069 -> 91.011 | H79: 1002 | I79: 0.1 | J79: =I79*D79 -> 131.9 | K79: =J79/1.16 -> 113.7069 | M79: =D79-H79-J79-L79-F79-G79 -> 94.089 | N79: =M79/H79 -> 0.093901198
A80: Xiaomi Audífonos Inalámbricos Redmi Buds 3 Pro Glacier Gray… | B80: B09C3WHL7P | D80: 700 | F80: =D80*0.069 -> 48.3 | H80: 379.2 | I80: 0.15 | J80: =I80*D80 -> 105 | K80: =J80/1.16 -> 90.517241 | M80: =D80-H80-J80-L80-F80-G80 -> 167.5 | N80: =M80/H80 -> 0.44171941
A81: Pasa el mouse encima de la imagen para aplicar zoom Xiaomi Mi Portable Bluetooth Speaker Gris | B81: B08N4BFTL9 | D81: 419 | F81: =D81*0.069 -> 28.911 | H81: 316.94 | I81: 0.1 | J81: =I81*D81 -> 41.9 | K81: =J81/1.16 -> 36.12069 | L81: 54 | M81: =D81-H81-J81-L81-F81-G81 -> -22.751 | N81: =M81/H81 -> -0.071783303
A82: Xiaomi Bascula Inteligente Mi Smart Scale 2 Blanca… | B82: B07VLN38BL | D82: 399 | F82: =D82*0.069 -> 27.531 | H82: 250 | I82: 0.1 | J82: =I82*D82 -> 39.9 | K82: =J82/1.16 -> 34.396552 | L82: 67 | M82: =D82-H82-J82-L82-F82-G82 -> 14.569 | N82: =M82/H82 -> 0.058276
A83: Xiaomi Foco Inteligente Mi Smart Led Bulb Essential… | B83: B0859NF38S | D83: 329 | F83: =D83*0.069 -> 22.701 | H83: 194.7 | I83: 0.15 | J83: =I83*D83 -> 49.35 | K83: =J83/1.16 -> 42.543103 | M83: =D83-H83-J83-L83-F83-G83 -> 62.249 | N83: =M83/H83 -> 0.31971751
A84: Xiaomi Mouse Mi Dual Mode Wireless Silent Edition Blanco | B84: B08868HFW2 | D84: 394 | F84: =D84*0.069 -> 27.186 | H84: 192.88 | I84: 0.1 | J84: =I84*D84 -> 39.4 | K84: =J84/1.16 -> 33.965517 | M84: =D84-H84-J84-L84-F84-G84 -> 134.534 | N84: =M84/H84 -> 0.69750104
A85: Mi robot juguete | B85: B0769LNZFM | D85: 1999 | F85: =D85*0.069 -> 137.931 | H85: 1490.85 | I85: 0.15 | J85: =I85*D85 -> 299.85 | K85: =J85/1.16 -> 258.49138 | M85: =D85-H85-J85-L85-F85-G85 -> 70.369 | N85: =M85/H85 -> 0.04720059
A86: Roku Streaming Stick+ | B86: B075XLWML4 | D86: 999 | F86: =D86*0.069 -> 68.931 | H86: 768.84 | I86: 0.15 | J86: =I86*D86 -> 149.85 | K86: =J86/1.16 -> 129.18103 | M86: =D86-H86-J86-L86-F86-G86 -> 11.379 | N86: =M86/H86 -> 0.014800219
A87: Tab A8 sAMSUNG | B87: B09N41RC6L | D87: 4399 | F87: =D87*0.069 -> 303.531 | H87: 3548.93 | I87: 0.1 | J87: =I87*D87 -> 439.9 | K87: =J87/1.16 -> 379.22414 | M87: =D87-H87-J87-L87-F87-G87 -> 106.639 | N87: =M87/H87 -> 0.030048212
A88: Instax mORADA | B88: B0858B1HRR | D88: 1999 | F88: =D88*0.069 -> 137.931 | H88: 1374 | I88: 0.1 | J88: =I88*D88 -> 199.9 | K88: =J88/1.16 -> 172.32759 | M88: =D88-H88-J88-L88-F88-G88 -> 287.169 | N88: =M88/H88 -> 0.20900218
A89: iNTSAX Rosa | B89: B085282C1R | D89: 1799 | F89: =D89*0.069 -> 124.131 | H89: 1374 | I89: 0.1 | J89: =I89*D89 -> 179.9 | K89: =J89/1.16 -> 155.08621 | M89: =D89-H89-J89-L89-F89-G89 -> 120.969 | N89: =M89/H89 -> 0.088041485
A90: Razer Basilisk X HyperSpeed - Gaming Mouse -Wireless Ergonomico color Negro StandardWindows Vista; Windows XP; Mac; Linux… | B90: B07YPBQSCK | D90: 799 | F90: =D90*0.069 -> 55.131 | H90: 575 | I90: 0.1 | J90: =I90*D90 -> 79.9 | K90: =J90/1.16 -> 68.87931 | M90: =D90-H90-J90-L90-F90-G90 -> 88.969 | N90: =M90/H90 -> 0.1547287
A91: Blackmagic Design - Conmutador ATEM Mini HDMI de transmisión en vivo… | B91: B07XZKRDLB | D91: 8629 | F91: =D91*0.069 -> 595.401 | H91: 5924.8 | I91: 0.1 | J91: =I91*D91 -> 862.9 | K91: =J91/1.16 -> 743.87931 | M91: =D91-H91-J91-L91-F91-G91 -> 1245.899 | N91: =M91/H91 -> 0.21028541
A92: insta360 GO 2 Cámara de acción pequeña, 28 g, Impermeable, estabilización, Captura POV, Sensor de 1.27 cm, Estuche de Carga y Accesorios de cámara portátil para Viajes, Deportes, vlog | B92: B08Y1P3CQ8 | D92: 6500 | F92: =D92*0.069 -> 448.5 | H92: 5262.81 | I92: 0.1 | J92: =I92*D92 -> 650 | K92: =J92/1.16 -> 560.34483 | M92: =D92-H92-J92-L92-F92-G92 -> 138.69 | N92: =M92/H92 -> 0.026352842
A93: Motorola HK375-S - Auriculares inalámbricos intraurales mono con tecn | B93: B09J1N9KBR | D93: 799 | F93: =D93*0.069 -> 55.131 | H93: =436.75*1.1 -> 480.425 | I93: 0.1 | J93: =I93*D93 -> 79.9 | K93: =J93/1.16 -> 68.87931 | M93: =D93-H93-J93-L93-F93-G93 -> 183.544 | N93: =M93/H93 -> 0.38204506
A94: MI WIRELESS OUTDOOR SECURITY CAMERA 1080P | B94: B09DQ24TGX | D94: 1119 | F94: =D94*0.069 -> 77.211 | H94: 840.16 | I94: 0.15 | J94: =I94*D94 -> 167.85 | K94: =J94/1.16 -> 144.69828 | M94: =D94-H94-J94-L94-F94-G94 -> 33.779 | N94: =M94/H94 -> 0.040205437
A95: MI WIRELESS OUTDOOR SECURITY CAMERA 1080P SET | B95: B09DQ21SBC | D95: 1559 | F95: =D95*0.069 -> 107.571 | H95: 1142.13 | I95: 0.16 | J95: =I95*D95 -> 249.44 | K95: =J95/1.16 -> 215.03448 | M95: =D95-H95-J95-L95-F95-G95 -> 59.859 | N95: =M95/H95 -> 0.052409971
A96: Camara 2k 360 | B96: B08R8LKBV9 | D96: 1080 | F96: =D96*0.069 -> 74.52 | H96: 764.63 | I96: 0.15 | J96: =I96*D96 -> 162 | K96: =J96/1.16 -> 139.65517 | M96: =D96-H96-J96-L96-F96-G96 -> 78.85 | N96: =M96/H96 -> 0.10312177
A97: Xiaomi Smartwatch Redmi Watch 2 Lite Ivory… | B97: B09LHGP5JF | D97: 987 | F97: =D97*0.069 -> 68.103 | H97: 641.37 | I97: 0.15 | J97: =I97*D97 -> 148.05 | K97: =J97/1.16 -> 127.62931 | M97: =D97-H97-J97-L97-F97-G97 -> 129.477 | N97: =M97/H97 -> 0.20187567
A98: Xiaomi Mi Watch Lite Azul US… | B98: B08Q3WDC9J | D98: 835 | F98: =D98*0.069 -> 57.615 | H98: 524.09 | I98: 0.15 | J98: =I98*D98 -> 125.25 | K98: =J98/1.16 -> 107.97414 | M98: =D98-H98-J98-L98-F98-G98 -> 128.045 | N98: =M98/H98 -> 0.24431872
A99: Xiaomi Smartwatch Redmi Watch 2 Lite Azul… | B99: B09R8SD6G5 | D99: 899 | F99: =D99*0.069 -> 62.031 | H99: 590 | I99: 0.15 | J99: =I99*D99 -> 134.85 | K99: =J99/1.16 -> 116.25 | M99: =D99-H99-J99-L99-F99-G99 -> 112.119 | N99: =M99/H99 -> 0.1900322
A100: Tune 500 bt azul | B100: B08WM1V5P1 | D100: 899 | F100: =D100*0.069 -> 62.031 | H100: 623.09 | I100: 0.15 | J100: =I100*D100 -> 134.85 | K100: =J100/1.16 -> 116.25 | M100: =D100-H100-J100-L100-F100-G100 -> 79.029 | N100: =M100/H100 -> 0.126834
B101: B08WM298TV | D101: 609 | F101: =D101*0.069 -> 42.021 | H101: 623.09 | I101: 0.15 | J101: =I101*D101 -> 91.35 | K101: =J101/1.16 -> 78.75 | M101: =D101-H101-J101-L101-F101-G101 -> -147.461 | N101: =M101/H101 -> -0.23666084
B102: B08WM3LJQB | D102: 899 | F102: =D102*0.069 -> 62.031 | H102: 623.09 | I102: 0.15 | J102: =I102*D102 -> 134.85 | K102: =J102/1.16 -> 116.25 | M102: =D102-H102-J102-L102-F102-G102 -> 79.029 | N102: =M102/H102 -> 0.126834
...

Sheet Hoja 18
A1: 3750270288 | B1: BL710WM | H1: ASIN | I1: Referral Fee Nivel 1
A2: 3750335524 | H2: B0D3P8ZP21 | I2: 0.099
A3: 2503498501 | H3: B07VGT69TG | I3: 0.099
A4: 3826490638 | B4: BL610 | H4: B0F7SJ9MT8 | I4: 0.098934
A5: 4317244286 | H5: B0FFN6NRTZ | I5: 0.083292
A6: 2347926527 | B6: BN401 | H6: B003NF40OG | I6: 0.099
A7: 2517923221 | B7: BN300 | H7: B0CBBP8BQX | I7: 0.079134
A8: 2340764625 | B8: BN801 | H8: B0DDN2JNSV | I8: 0.098802
A9: 4165765140 | H9: B0B6FHKKHP | I9: 0.099
B10: BN400 | H10: B0D9H19PBL | I10: 0.098274
A11: 3793815784 | B11: ES601 | H11: B0F3JWFL56 | I11: 0.065934
B12: SL401 | H12: B09FM6PDHP | I12: 0.099
A13: 3793946112 | B13: JC151 | H13: B0F58Q4CM9 | I13: 0.065868
A14: 3793946198 | B14: TB401LAA | H14: B0DSG3MMDZ | I14: 0.065934
A15: 3795266826 | B15: CM401 | H15: B0DNV41CHB | I15: 0.066
B16: QB3000SS | H16: B085FVKSMC | I16: 0.066
A17: 2359818339 | B17: HD435LAA Shark Flex Style Blanco | H17: B0FN7VLZCH | I17: 0.065736
B18: HD442BP Shark Malibu Pink | H18: B0FKBDT8FR | I18: 0.065934
A19: 2359684899 | B19: HD450TL Shark Flex Style Teal | H19: B0CF7LY4XZ | I19: 0.066
A20: 2386343109 | B20: BN701LAA | H20: B0CZRMRQ3Y | I20: 0.065802
A21: 3750659954 | H21: B09HGGV5R5 | I21: 0.098934
A22: 2426721105 | H22: B09XSDMT4F | I22: 0.070488
A23: 4016269482 | B23: CT800 | H23: B0FN7XC2J7 | I23: 0.066
A24: 2386376891 | B24: FW312LAA | H24: B0CF7GCG6F | I24: 0.065934
B25: IX141LAA | H25: B0DK6ZC5ZC | I25: 0.096558
A26: 2475112999 | B26: CT610 | H26: B0D9YYQ7X9 | I26: 0.098934
A27: 3550149464 | B27: NC301LAA | H27: B0BHT7NX51 | I27: 0.099
A28: 4016385322
A29: 4095291968 | B29: Cl305A
A30: 4139036224 | B30: CO905KS
A31: 4180187602 | B31: SS101
A32: 2475353115 | B32: FA222
A33: 4180157156 | B33: BL660
A34: 2475086533 | B34: TB201LAA
A35: 2475035161 | B35: BL480
A36: 4330026978 | B36: CN501COLAA
B37: WV201CO
A38: 2492015425 | B38: TB400LAA
B39: IZ492HLAA
A40: 2492030151 | B40: FA200
B41: DW2401GY
B42: DW2401WH
B43: BU3120L
B44: AF161
B45: DW2401MT
A46: 3591793650 | B46: FS301LAA
A47: 2419012707
B48: S1000LAA
B49: CH951
B50: CFN601
B51: CT672A
B52: DW2401BL
B53: DW2401BK
B54: DT201
A55: 2524112383 | B55: IZ142

Sheet Remates AMZ 
A4: Producto | B4: ASIN | C4: Precio de venta | E4: Costo | F4: Comision | G4: Comison IVa | H4: Envio | I4: Utilidad | J4: ROI
A5: Mi Box | B5: B07KB1KLYN | C5: 1130 | E5: 849.99 | F5: 0.1 | G5: =F5*C5 -> 113 | H5: 68.324 | I5: =C5-E5-G5-H5 -> 98.686 | J5: =I5/E5 -> 0.11610254
A6: Mi Band 5 | B6: B089NS9JW2 | C6: 532 | E6: 400 | F6: 0.15 | G6: =F6*C6 -> 79.8 | H6: 68.324 | I6: =C6-E6-G6-H6 -> -16.124 | J6: =I6/E6 -> -0.04031
A7: Mi Projector 2 | B7: B08RMX5XVR | E7: 8350.23 | F7: 0.1 | G7: =F7*C7 -> 0 | H7: 54.56 | I7: =C7-E7-G7-H7 -> -8404.79 | J7: =I7/E7 -> -1.006534
A8: Roku 4k+ | B8: B0916TKFF2 | C8: 859 | E8: 629.71 | F8: 0.1 | G8: =F8*C8 -> 85.9 | H8: 67.164 | I8: =C8-E8-G8-H8 -> 76.226 | J8: =I8/E8 -> 0.12104937
A9: Roku exprees | B9: B07WVFCVJN | C9: 699 | E9: 472.46 | F9: 0.1 | G9: =F9*C9 -> 69.9 | H9: 67.164 | I9: =C9-E9-G9-H9 -> 89.476 | J9: =I9/E9 -> 0.18938323
A10: Roku4k streaming | B10: B09BKCDXZC | C10: 878 | E10: 622 | F10: 0.15 | G10: =F10*C10 -> 131.7 | H10: =66*1.16 -> 76.56 | I10: =C10-E10-G10-H10 -> 47.74 | J10: =I10/E10 -> 0.076752412
A11: Scooter essential | B11: B089NR5WZ8 | C11: 8299 | E11: 6199.42 | F11: 0.15 | G11: =F11*C11 -> 1244.85 | H11: 254.04 | I11: =C11-E11-G11-H11 -> 600.69 | J11: =I11/E11 -> 0.096894548
A12: Clavija | B12: B091V6V2CL | C12: 99 | E12: 9 | F12: 0.15 | G12: =F12*C12 -> 14.85 | H12: 67.28 | I12: =C12-E12-G12-H12 -> 7.87 | J12: =I12/E12 -> 0.87444444
A13: Aspiradora Mop 1C | B13: B086W5Y1CG | C13: 6399 | E13: 4500 | F13: 0.15 | G13: =F13*C13 -> 959.85 | H13: 101.31 | I13: =C13-E13-G13-H13 -> 837.84 | J13: =I13/E13 -> 0.18618667
A14: Earphones Blancos | B14: B08BRGH7S3 | C14: 545 | E14: 347.85 | F14: 0.15 | G14: =F14*C14 -> 81.75 | H14: 67.164 | I14: =C14-E14-G14-H14 -> 48.236 | J14: =I14/E14 -> 0.13866897
A15: Buds 3 PRO | B15: B09C3W56FC | C15: 759 | E15: 530.77 | F15: 0.1 | G15: =F15*C15 -> 75.9 | H15: 67.6164 | I15: =C15-E15-G15-H15 -> 84.7136 | J15: =I15/E15 -> 0.1596051
A16: Router 4A | B16: B085G5CDY7 | C16: 419 | E16: 270.12 | F16: 0.1 | G16: =F16*C16 -> 41.9 | H16: 78.88 | I16: =C16-E16-G16-H16 -> 28.1 | J16: =I16/E16 -> 0.10402784
A17: Router 4c | B17: B09HSV3JZ5 | C17: 359 | E17: 200 | F17: 0.15 | G17: =F17*C17 -> 53.85 | H17: 78.88 | I17: =C17-E17-G17-H17 -> 26.27 | J17: =I17/E17 -> 0.13135
A18: Tablet ONN | B18: B09FBZ4D9T | C18: 1599 | E18: 1021.82 | F18: 0.1 | G18: =F18*C18 -> 159.9 | H18: 65.58 | I18: =C18-E18-G18-H18 -> 351.7 | J18: =I18/E18 -> 0.34418978
A19: Mi Speaker 2 | B19: B07RD3FNTN | C19: 232 | E19: 179.45 | F19: 0.1 | G19: =F19*C19 -> 23.2 | I19: =C19-E19-G19-H19 -> 29.35 | J19: =I19/E19 -> 0.16355531
A20: Razer Tournament | B20: B075M47H3H | F20: 0.1 | G20: =F20*C20 -> 0 | H20: 210.32 | I20: =C20-E20-G20-H20 -> -210.32 | J20: =I20/E20 -> #DIV/0!
A21: Mi Band 6 | B21: B091G3FLL7 | C21: 799 | E21: 519 | F21: 0.15 | G21: =F21*C21 -> 119.85 | H21: 62.64 | I21: =C21-E21-G21-H21 -> 97.51 | J21: =I21/E21 -> 0.18788054
A22: Buds 3 lite | B22: B09NQKCQWS | C22: 479 | E22: 163.64 | F22: 0.15 | G22: =F22*C22 -> 71.85 | H22: 67.6164 | I22: =C22-E22-G22-H22 -> 175.8936 | J22: =I22/E22 -> 1.0748814
A23: Aspiradora Mop P | B23: B085BP7ZC5 | C23: 8499 | E23: 6161.78 | F23: 0.15 | G23: =F23*C23 -> 1274.85 | H23: 125.28 | I23: =C23-E23-G23-H23 -> 937.09 | J23: =I23/E23 -> 0.15208105
A24: Watch S1 | B24: B09S8BKKHB | C24: 1977 | E24: 1183.46 | F24: 0.16 | G24: =F24*C24 -> 316.32 | H24: 67.28 | I24: =C24-E24-G24-H24 -> 409.94 | J24: =I24/E24 -> 0.34639109
A25: Buds 3 | B25: B09J4T4JF5 | C25: 439 | E25: 274.78 | F25: 0.15 | G25: =F25*C25 -> 65.85 | H25: 67.28 | I25: =C25-E25-G25-H25 -> 31.09 | J25: =I25/E25 -> 0.11314506
A26: Repetidor Xiaomi | B26: B0762SH6WG | C26: 329 | E26: 229.36 | F26: 0.1 | G26: =F26*C26 -> 32.9 | H26: 58 | I26: =C26-E26-G26-H26 -> 8.74 | J26: =I26/E26 -> 0.038106034
A27: Repetidor Xiaomi | B27: B084WT4WWK | C27: 359 | E27: 229.36 | F27: 0.1 | G27: =F27*C27 -> 35.9 | H27: 58 | I27: =C27-E27-G27-H27 -> 35.74 | J27: =I27/E27 -> 0.1558249
A28: Cargador Xiaomi Tipo c 20W | B28: B0969PK3SG | C28: 359 | E28: 207.48 | F28: 0.15 | G28: =F28*C28 -> 53.85 | H28: 70.76 | I28: =C28-E28-G28-H28 -> 26.91 | J28: =I28/E28 -> 0.12969925
A29: Xiaomi Pad 5 256 gb | B29: B09JBZQG49 | C29: 10599 | E29: 8689.0468 | F29: 0.1 | G29: =F29*C29 -> 1059.9 | H29: 69.71 | I29: =C29-E29-G29-H29 -> 780.3432 | J29: =I29/E29 -> 0.089807688
A30: Xiaomi Pad 5 128 gb | B30: B09JBZP2WR | C30: 9590 | E30: 7847.8477 | F30: 0.1 | G30: =F30*C30 -> 959 | H30: 69.71 | I30: =C30-E30-G30-H30 -> 713.4423 | J30: =I30/E30 -> 0.090909295
A31: Mi watch | B31: B08P5J7KGH | C31: 2599 | E31: 1488 | F31: 0.15 | G31: =F31*C31 -> 389.85 | H31: 58 | I31: =C31-E31-G31-H31 -> 663.15 | J31: =I31/E31 -> 0.44566532
A32: Camara 360 | B32: B093C8S6B1 | C32: 599 | E32: 340 | F32: 0.15 | G32: =F32*C32 -> 89.85 | H32: 70.76 | I32: =C32-E32-G32-H32 -> 98.39 | J32: =I32/E32 -> 0.28938235
... A45: Haylou gt7 | B45: B09HXSW5ZX | C45: 499 | E45: 320.13 | F45: 0.15 | G45: =F45*C45 -> 74.85 | H45: 67.6164 | I45: =C45-E45-G45-H45 -> 36.4036 | J45: =I45/E45 -> 0.11371505
A46: Clavija Blanca | B46: B07FFBD8XP | C46: 107 | E46: =10.17*2 -> #ERROR! | F46: 0.15 | G46: =F46*C46 -> 16.05 | H46: 67.6164 | I46: =C46-E46-G46-H46 -> #ERROR! | J46: =I46/E46 -> #ERROR!
A47: Speaker azul | B47: B08MKQ6DXJ | C47: 795 | E47: 470.69 | F47: 0.1 | G47: =F47*C47 -> 79.5 | H47: 75.4 | I47: =C47-E47-G47-H47 -> 169.41 | J47: =I47/E47 -> 0.35991842
A48: Monitor Bar | B48: B08W2C5W59 | C48: 1011 | E48: 550.03 | F48: 0.1 | G48: =F48*C48 -> 101.1 | H48: 87 | I48: =C48-E48-G48-H48 -> 272.87 | J48: =I48/E48 -> 0.49610021
A49: Samsung Tab A8 | B49: B08QQTQNDC | C49: 4299 | E49: 3177.28 | F49: 0.1 | G49: =F49*C49 -> 429.9 | H49: 67.6164 | I49: =C49-E49-G49-H49 -> 624.2036 | J49: =I49/E49 -> 0.19645848
A50: Tv stick | B50: B09LPTSRMH | C50: 849 | E50: 614.8 | F50: 0.15 | G50: =F50*C50 -> 127.35 | H50: 68.092 | I50: =C50-E50-G50-H50 -> 38.758 | J50: =I50/E50 -> 0.06304164
A51: aspiradora Mini Xiaomi | B51: B08MPQQJHQ | C51: 899 | E51: 523.64 | F51: 0.15 | G51: =F51*C51 -> 134.85 | H51: 172.84 | I51: =C51-E51-G51-H51 -> 67.67 | J51: =I51/E51 -> 0.12923001
A52: Scooter S1 | B52: B076KKX4BC | C52: 10599 | E52: 6325 | F52: 0.15 | G52: =F52*C52 -> 1589.85 | H52: 261 | I52: =C52-E52-G52-H52 -> 2423.15 | J52: =I52/E52 -> 0.38310672
A53: Teclado Cyrosa V2 | B53: B089KLHYG3 | C53: 1199 | E53: 845.234 | F53: 0.1 | G53: =F53*C53 -> 119.9 | H53: 102.4048 | I53: =C53-E53-G53-H53 -> 131.4612 | J53: =I53/E53 -> 0.15553231
A54: Audifono Blackshark V2 | E54: 997.6 | G54: =F54*C54 -> 0
A55: Teclado Ornata V2 | B55: B086TKHRSN | C55: 1799 | E55: 1305.3712 | F55: 0.15 | G55: =F55*C55 -> 269.85 | H55: 102.08 | I55: =C55-E55-G55-H55 -> 121.6988 | J55: =I55/E55 -> 0.093229267
A56: Microfono Seiren | B56: B08HGJ8M4N | C56: 799 | E56: 500 | F56: 0.1 | G56: =F56*C56 -> 79.9 | H56: 70.76 | I56: =C56-E56-G56-H56 -> 148.34 | J56: =I56/E56 -> 0.29668
A57: Audifono Kraken Xlite | B57: B081GJ938B | C57: 494 | E57: 350 | F57: 0.1 | G57: =F57*C57 -> 49.4 | H57: 80.8636 | I57: =C57-E57-G57-H57 -> 13.7364 | J57: =I57/E57 -> 0.039246857
A58: Razer DeathAdder V2 Mini - Ratón gaming ergonómico con cable - Edición Negro EstándarWindows Vista; Windows XP; Mac; linux… | B58: B08B3K9K6P | C58: 449 | E58: 234.09 | F58: 0.1 | G58: =F58*C58 -> 44.9 | H58: 67.6164 | I58: =C58-E58-G58-H58 -> 102.3936 | J58: =I58/E58 -> 0.43741125
A59: Razer Blackshark V 2 X GREEN | B59: B09CLWQ45V | C59: 799 | E59: 423 | F59: 0.15 | G59: =F59*C59 -> 119.85 | H59: 80.8636 | I59: =C59-E59-G59-H59 -> 175.2864 | J59: =I59/E59 -> 0.41438865
A60: Razer Game wolverine V2 white | B60: B09C13DWYL | C60: 1799 | E60: 1350 | F60: 0.1 | G60: =F60*C60 -> 179.9 | H60: 76.0728 | I60: =C60-E60-G60-H60 -> 193.0272 | J60: =I60/E60 -> 0.14298311
A61: Razer kiyo webcam | B61: B09FNX2PLL | C61: 1199 | E61: =1319-619 -> 700 | F61: 0.15 | G61: =F61*C61 -> 179.85 | H61: 68.4168 | I61: =C61-E61-G61-H61 -> 250.7332 | J61: =I61/E61 -> 0.35819029
A62: Razer Headset v2 x Negro | B62: B086PKMZ21 | C62: 799 | E62: 549 | F62: 0.1 | G62: =F62*C62 -> 79.9 | H62: 80.8636 | I62: =C62-E62-G62-H62 -> 89.2364 | J62: =I62/E62 -> 0.16254353
A63: Buds 3 lite blancos | B63: B09NY2HZFQ | C63: 449 | E63: 278.45 | F63: 0.15 | G63: =F63*C63 -> 67.35 | H63: 67.5816 | I63: =C63-E63-G63-H63 -> 35.6184 | J63: =I63/E63 -> 0.12791668
A64: Mi bODY Scale composition | B64: B07VD9F419 | C64: 459 | E64: 266.05 | F64: 0.15 | G64: =F64*C64 -> 68.85 | H64: 96.5816 | I64: =C64-E64-G64-H64 -> 27.5184 | J64: =I64/E64 -> 0.10343319
A65: Xiaomi Reloj Inteligente Smartwatch Watch S1 Active GL (Moon White)… | B65: B09S8RCGSC | C65: 1699 | E65: 1183.46 | F65: 0.15 | G65: =F65*C65 -> 254.85 | H65: 70.76 | I65: =C65-E65-G65-H65 -> 189.93 | J65: =I65/E65 -> 0.16048705
A66: Reloj Inteligente Smartwatch Xiaomi Watch S1 (Silver)… | B66: B09TR69KGF | C66: 3999 | E66: 3207.61 | F66: 0.1 | G66: =F66*C66 -> 399.9 | H66: 68.44 | I66: =C66-E66-G66-H66 -> 323.05 | J66: =I66/E66 -> 0.10071362
A67: Reloj Inteligente Smartwatch Xiaomi Watch S1 (Black)… | B67: B09TR5XVML | C67: 2599 | E67: 1970 | F67: 0.1 | G67: =F67*C67 -> 259.9 | H67: 68.44 | I67: =C67-E67-G67-H67 -> 300.66 | J67: =I67/E67 -> 0.15261929
A68: Arlo | B68: B08NTGL8MB | C68: 7599 | E68: 4840.06 | F68: 0.15 | G68: =F68*C68 -> 1139.85 | H68: 80.04 | I68: =C68-E68-G68-H68 -> 1539.05 | J68: =I68/E68 -> 0.3179816
A69: Xiaomi Mi 360° Home Security Camera 2K Pro… | B69: B08P5G51GN | C69: 799 | E69: 558.75 | F69: 0.1 | G69: =F69*C69 -> 79.9 | H69: 78.88 | I69: =C69-E69-G69-H69 -> 81.47 | J69: =I69/E69 -> 0.14580761
A70: Kraken Mercury | B70: B07SKCLW2G | C70: 799 | E70: 580 | F70: 0.1 | G70: =F70*C70 -> 79.9 | H70: 80.8636 | I70: =C70-E70-G70-H70 -> 58.2364 | J70: =I70/E70 -> 0.10040759
A71: Razer Gigantus v2 -Mouse mat para Videojuegos mediano… | B71: B088539GLT | C71: 249 | E71: 134.36 | F71: 0.1 | G71: =F71*C71 -> 24.9 | H71: 70.76 | I71: =C71-E71-G71-H71 -> 18.98 | J71: =I71/E71 -> 0.14126228
A72: Xiaomi Audífonos Inálambricos Buds 3T Pro Carbon Grey… | B72: B09R9JY2RZ | C72: 2299 | E72: 1731.07 | F72: 0.14 | G72: =F72*C72 -> 321.86 | H72: 68.44 | I72: =C72-E72-G72-H72 -> 177.63 | J72: =I72/E72 -> 0.10261283
A73: Wolverine Control V2 | B73: B08LRTTGM6 | C73: 1240 | E73: 882.46 | F73: 0.15 | G73: =F73*C73 -> 186 | H73: 78.88 | I73: =C73-E73-G73-H73 -> 92.66 | J73: =I73/E73 -> 0.10500193
... A91: insta360 GO 2 Cámara de acción pequeña, 28 g, Impermeable, estabilización, Captura POV, Sensor de 1.27 cm, Estuche de Carga y Accesorios de cámara portátil para Viajes, Deportes, vlog | B91: B08Y1P3CQ8 | C91: 6500 | E91: 5262.81 | F91: 0.1 | G91: =F91*C91 -> 650 | H91: 68.44 | I91: =C91-E91-G91-H91 -> 518.75 | J91: =I91/E91 -> 0.098569015
A92: Motorola HK375-S - Auriculares inalámbricos intraurales mono con tecn | B92: B09J1N9KBR | C92: 799 | E92: =436.75*1.1 -> #ERROR! | F92: 0.1 | G92: =F92*C92 -> 79.9 | H92: 68.44 | I92: =C92-E92-G92-H92 -> #ERROR! | J92: =I92/E92 -> #ERROR!
A93: MI WIRELESS OUTDOOR SECURITY CAMERA 1080P | B93: B09DQ24TGX | C93: 1119 | E93: 840.16 | F93: 0.15 | G93: =F93*C93 -> 167.85 | H93: 75.4 | I93: =C93-E93-G93-H93 -> 35.59 | J93: =I93/E93 -> 0.042360979
A94: MI WIRELESS OUTDOOR SECURITY CAMERA 1080P SET | B94: B09DQ21SBC | C94: 1559 | E94: 1142.13 | F94: 0.16 | G94: =F94*C94 -> 249.44 | H94: 75.4 | I94: =C94-E94-G94-H94 -> 92.03 | J94: =I94/E94 -> 0.080577517
A95: Camara 2k 360 | B95: B08R8LKBV9 | C95: 1080 | E95: 764.63 | F95: 0.15 | G95: =F95*C95 -> 162 | H95: 67.28 | I95: =C95-E95-G95-H95 -> 86.09 | J95: =I95/E95 -> 0.1125904
A96: Xiaomi Smartwatch Redmi Watch 2 Lite Ivory… | B96: B09LHGP5JF | C96: 987 | E96: 641.37 | F96: 0.15 | G96: =F96*C96 -> 148.05 | H96: 75.4 | I96: =C96-E96-G96-H96 -> 122.18 | J96: =I96/E96 -> 0.19049846
A97: Xiaomi Mi Watch Lite Azul US… | B97: B08Q3WDC9J | C97: 835 | E97: 524.09 | F97: 0.15 | G97: =F97*C97 -> 125.25 | H97: 75.4 | I97: =C97-E97-G97-H97 -> 110.26 | J97: =I97/E97 -> 0.21038371
A98: Xiaomi Smartwatch Redmi Watch 2 Lite Azul… | B98: B09R8SD6G5 | C98: 899 | E98: 590 | F98: 0.15 | G98: =F98*C98 -> 134.85 | H98: 75.4 | I98: =C98-E98-G98-H98 -> 98.75 | J98: =I98/E98 -> 0.16737288
A99: Tune 500 bt azul | B99: B08WM1V5P1 | C99: 899 | E99: 623.09 | F99: 0.15 | G99: =F99*C99 -> 134.85 | H99: 67.28 | I99: =C99-E99-G99-H99 -> 73.78 | J99: =I99/E99 -> 0.11840986
B100: B08WM298TV | C100: 899 | E100: 623.09 | F100: 0.15 | G100: =F100*C100 -> 134.85 | H100: 67.28 | I100: =C100-E100-G100-H100 -> 73.78 | J100: =I100/E100 -> 0.11840986
B101: B08WM3LJQB | C101: 899 | E101: 623.09 | F101: 0.15 | G101: =F101*C101 -> 134.85 | H101: 67.28 | I101: =C101-E101-G101-H101 -> 73.78 | J101: =I101/E101 -> 0.11840986
A102: SAMSUNG Proyector portátil Inteligente Freestyle de 30 a 100 Pulgadas, FHD, HDR, Uso doméstico, Experiencia de Pantalla Grande, Sonido 360, SP-LSP3BLAXZA, Modelo 2022 | B102: B09NDXB72V | C102: 13749 | E102: 11423.99 | F102: 0.15 | G102: =F102*C102 -> 2062.35 | H102: 67.28 | I102: =C102-E102-G102-H102 -> 195.38 | J102: =I102/E102 -> 0.017102606
A103: Freidora de Aire | B103: B098BRGZW1 | C103: 1499 | E103: 919.35 | F103: 0.15 | G103: =F103*C103 -> 224.85 | H103: 153.12 | I103: =C103-E103-G103-H103 -> 201.68 | J103: =I103/E103 -> 0.21937238
A104: Mi watch lite 2 | B104: B09LHFW2NL | C104: 1149 | E104: 815.4 | F104: 0.15 | G104: =F104*C104 -> 172.35 | H104: 68.44 | I104: =C104-E104-G104-H104 -> 92.81 | J104: =I104/E104 -> 0.11382144
A105: Xiaomi Mi Portable Photo Printer Paper (2x3-inch, 20-Sheets) | B105: B08BY35N8L | C105: 215 | E105: 75.13 | F105: 0.15 | G105: =F105*C105 -> 32.25 | H105: 68.44 | I105: =C105-E105-G105-H105 -> 39.18 | J105: =I105/E105 -> 0.52149607
B106: B09S3B442Z | C106: 1698 | E106: 1183.46 | F106: 0.15 | G106: =F106*C106 -> 254.7 | H106: 68.44 | I106: =C106-E106-G106-H106 -> 191.4 | J106: =I106/E106 -> 0.16172917
B107: B09HY1LGZ2 | C107: 950 | E107: 719.21 | F107: 0.1 | G107: =F107*C107 -> 95 | H107: 68.44 | I107: =C107-E107-G107-H107 -> 67.35 | J107: =I107/E107 -> 0.093644415
A108: RazerRZ04-02980100-R3M1Razer Kraken Kitty Edition Razer Chroma USB Gaming Headset Black… | B108: B07WC9KLFZ | C108: 1920 | E108: 1500.01 | F108: 0.1 | G108: =F108*C108 -> 192 | H108: 80.04 | I108: =C108-E108-G108-H108 -> 147.95 | J108: =I108/E108 -> 0.098632676
F109: 0.1 | G109: =F109*C109 -> 0
A110: Xiaomi Tetera Hervidor de agua inteligente con función de mantener caliente y programación desde el celular… | B110: B08MPXN672 | C110: 1039 | E110: 766.62 | F110: 0.1 | G110: =F110*C110 -> 103.9 | H110: 112.52 | I110: =C110-E110-G110-H110 -> 55.96 | J110: =I110/E110 -> 0.072995748
A111: Razer Kraken Kitty - Audífonos Gaming con iluminación Chroma RGB USB Rosa | B111: B07XYPXB9Q | C111: 1999 | E111: 1499.97 | F111: 0.1 | G111: =F111*C111 -> 199.9 | H111: 80.04 | I111: =C111-E111-G111-H111 -> 219.09 | J111: =I111/E111 -> 0.14606292
A112: Mi Box 4K | B112: B09NMT7NXY | C112: 1299 | E112: 886.31 | F112: 0.1 | G112: =F112*C112 -> 129.9 | H112: 70.76 | I112: =C112-E112-G112-H112 -> 212.03 | J112: =I112/E112 -> 0.23922781
A113: Razer DeathAdder Essential Gaming Mouse - Ratón óptico de 6400 PPP, 5 Botones programables, interruptores mecánicos, empuñaduras Laterales de Goma, Color Negro clásico | B113: B094PS5RZQ | C113: 449 | E113: 298 | F113: 0.1 | G113: =F113*C113 -> 44.9 | H113: 67.28 | I113: =C113-E113-G113-H113 -> 38.82 | J113: =I113/E113 -> 0.13026846
A114: Xiaomi Banco de energía Redmi de 20000 mAh, carga rápida, carga rápida bidireccional de 18 W, puertos de entrada y salida duales, alta capacidad de 74 Wh, batería externa comp | B114: B08LN1YV1X | C114: 539 | E114: 344.21 | F114: 0.15 | G114: =F114*C114 -> 80.85 | H114: 75.4 | I114: =C114-E114-G114-H114 -> 38.54 | J114: =I114/E114 -> 0.11196653
A115: Kishi | B115: B0B16NGTCT | C115: 1699 | E115: 1289.29 | F115: 0.16 | G115: =F115*C115 -> 271.84 | H115: 67.28 | I115: =C115-E115-G115-H115 -> 70.59 | J115: =I115/E115 -> 0.054751065
A116: Razer Razer Basilisk V2 - Mouse Gamer Ergonómico Negro StandardWindows Vista; Windows XP; Mac; Linux… | B116: B082G5BDNC | C116: 1192 | E116: 895 | F116: 0.1 | G116: =F116*C116 -> 119.2 | H116: 67.28 | I116: =C116-E116-G116-H116 -> 110.52 | J116: =I116/E116 -> 0.12348603
A117: Xiaomi Purificador de Aire Mi Air Purifier 3C… | B117: B09NB1X529 | C117: 2499 | E117: 1260 | F117: 0.15 | G117: =F117*C117 -> 374.85 | H117: 156.6 | I117: =C117-E117-G117-H117 -> 707.55 | J117: =I117/E117 -> 0.56154762
A118: Xiaomi Mi Air Purifier 3H, Blanco… | B118: B07ZV7BDXZ | C118: 2799 | E118: 1260 | F118: 0.15 | G118: =F118*C118 -> 419.85 | H118: 156.6 | I118: =C118-E118-G118-H118 -> 962.55 | J118: =I118/E118 -> 0.76392857
A119: Xiaomi Mi Smart LED Desk Lamp Pro Blanco… | B119: B08H5JN5BM | C119: 1249 | E119: 782.32 | F119: 0.15 | G119: =F119*C119 -> 187.35 | H119: 133.4 | I119: =C119-E119-G119-H119 -> 145.93 | J119: =I119/E119 -> 0.18653492
A120: Xiaomi Mi Destornillador inalámbrico de 3,6 V, batería recargable de 2000 mAh, cuerpo patentado de una sola pieza con puerto de carga USB-C. Destornillador | B120: B07XZNJDGG | C120: 680 | E120: 465.03 | F120: 0.12 | G120: =F120*C120 -> 81.6 | H120: 80.04 | I120: =C120-E120-G120-H120 -> 53.33 | J120: =I120/E120 -> 0.11468077
A121: Razer BlackWidow V3 Mechanical Gaming Keyboard: Green Mechanical Switches - Tactile & Clicky - Chroma RGB Lighting - Compact Form Factor - Programmable Macros - Halo Infinite… | B121: B08F2YY8JV | C121: 2899 | E121: =2499.96-209.93 -> #ERROR! | F121: 0.1 | G121: =F121*C121 -> 289.9 | H121: 102.08 | I121: =C121-E121-G121-H121 -> #ERROR! | J121: =I121/E121 -> #ERROR!
A122: Auriculares para juegos USB con cable Razer Kraken V3 HyperSense con tecnología háptica: Controladores Triforce Titanium de 50 mm - Audio espacial THX - Cojines de espuma viscoelástica de tela híbrida y cuero sintético - Micrófono desmontable… | B122: B09HJC1X9P | C122: 1999 | E122: =1871.68- 371.68 -> #ERROR! | F122: 0.13 | G122: =F122*C122 -> 259.87 | H122: 84.68 | I122: =C122-E122-G122-H122 -> #ERROR! | J122: =I122/E122 -> #ERROR!
A123: Razer BlackShark V2 X - Auriculares para videojuegos: sonido envolvente 7.1, controladores de 50 mm, cojín de espuma viscoelástica, para PC, Mac, PS4, PS5, S | B123: B09PZG4R17 | C123: 793 | E123: 568.21 | F123: 0.1 | G123: =F123*C123 -> 79.3 | H123: 84.68 | I123: =C123-E123-G123-H123 -> 60.81 | J123: =I123/E123 -> 0.10702029
A124: Razer Kraken V3 X Auriculares gaming USB con iluminación Chroma Negro StandardWindows Vista; Windows XP; Mac; linux… | B124: B08WYN93RJ | C124: 999 | E124: 737.84 | F124: 0.1 | G124: =F124*C124 -> 99.9 | H124: 84.68 | I124: =C124-E124-G124-H124 -> 76.58 | J124: =I124/E124 -> 0.10378944
A125: Razer BlackShark V2 - Auriculares para videojuegos: sonido envolvente espacial THX 7.1, controladores de 50 mm, micrófono desmontable, para PC, PS4, PS5, Switch, Xbox One, X | B125: B099MRQKY2 | C125: 1929 | E125: 1513.5 | F125: 0.1 | G125: =F125*C125 -> 192.9 | H125: 84.68 | I125: =C125-E125-G125-H125 -> 137.92 | J125: =I125/E125 -> 0.091126528
A126: azerRZ04-02980100-R3M1Razer Kraken Kitty Edition Razer Chroma USB Auriculares para juegos Negro… | B126: B07WC9KLFZ | C126: 1992 | E126: 1500.01 | F126: 0.1 | G126: =F126*C126 -> 199.2 | H126: 84.68 | I126: =C126-E126-G126-H126 -> 208.11 | J126: =I126/E126 -> 0.13873908
A127: Buds Air 3 | B127: B018LW032S | C127: 965 | E127: 755.61 | F127: 0.15 | G127: =F127*C127 -> 144.75 | H127: 71.804 | I127: =C127-E127-G127-H127 -> -7.164 | J127: =I127/E127 -> -0.0094810815
A128: Buds 3 Air Neo Realme | B128: B0B4DDZQ97 | C128: 497 | E128: 425.22 | F128: 0.15 | G128: =F128*C128 -> 74.55 | H128: 71.804 | I128: =C128-E128-G128-H128 -> -74.574 | J128: =I128/E128 -> -0.17537745
A129: Redmi Buds 4 pro | B129: B0B8ZMGK7D | C129: 1114 | E129: 827.35 | F129: 0.15 | G129: =F129*C129 -> 167.1 | H129: 71.804 | I129: =C129-E129-G129-H129 -> 47.746 | J129: =I129/E129 -> 0.057709555 | K129: Remate
A130: - JBL Vibe 200 Earbuds fo | B130: B097F4V3FJ | C130: 879 | E130: 605.02 | F130: 0.15 | G130: =F130*C130 -> 131.85 | H130: 71.804 | I130: =C130-E130-G130-H130 -> 70.326 | J130: =I130/E130 -> 0.11623748
A131: Razer Seiren Mini Condenser Microphone - Mercury | B131: B08HGLTNDM | C131: 699 | E131: 499 | F131: 0.1 | G131: =F131*C131 -> 69.9 | H131: 71.804 | I131: =C131-E131-G131-H131 -> 58.296 | J131: =I131/E131 -> 0.11682565
A132: azer Razer BlackWidow V3 - Teclado mecánico para juegos (interruptor verde) - Diseño ES Negro clásico EstándarWindows Vista;Windows XP;Mac;Linux… | B132: B08FQPLCNC | C132: 2220 | E132: 1709.93 | F132: 0.1 | G132: =F132*C132 -> 222 | H132: 102.08 | I132: =C132-E132-G132-H132 -> 185.99 | J132: =I132/E132 -> 0.10877053
...

Sheet Analisis Reembolso Parcial 
A1: Catalogo | B1: ID | C1: Producto | D1: Precio OFERTA | E1: Precio Minimo | F1: Costo | G1: Comision | H1: Comision | I1: Envio | J1: Utilidad | K1: ROI | L1: Estatus
A2: Catalogo | B2: 2019878109 | C2: Audífonos In-ear Inalámbricos Skullcandy Indy Black | D2: 539 | E2: 499 | F2: 308.83 | G2: 0.1 | H2: =G2*D2 -> 53.9 | I2: 62.5 | J2: =D2-F2-H2-I2 -> 113.77 | K2: =J2/F2 -> 0.36839038 | L2: Activa
A4: Si se concretara la venta
A5: Utilidad esperada de esta venta | B5: =J2 -> 113.77
A6: ROI | B6: =K2 -> 0.36839038
A8: Descuento al comprador | B8: 0.2
A9: Si aplicamos Reembolso | D9: No aplicamos Reembolso
A10: Precio Venta | B10: =D2 -> 539 | D10: Precio de venta | E10: =D2 -> 539 | F10: Si lo vendemos al mismo precio
A11: Si aplicamos %20 de reembolso | B11: =B10*B8 -> 107.8 | D11: Devolucion | E11: 125 | F11: Quedamos a dever por aceptarlo
A12: Fee de Ml | B12: =(1-B8)*H2 -> 43.12 | D12: Nueva comision de envio | E12: =H2 -> 53.9
A13: Envio | B13: =I2 -> 62.5
A14: Costo del producto | B14: =F2 -> 308.83 | D14: Nuevo Fee | E14: =I2 -> 62.5
A15: Utilidad | B15: =B10-B11-B12-B13-B14 -> 16.75 | D15: Costo | E15: =F2 -> 308.83
D16: Utilidad | E16: =E10-E11-E12-E14-E15 -> -11.23 | F16: Si no lo regresa

Sheet Fórmula
A1: ¿El producto incluye baterías o es una batería en sí mismo? | B1: Composición química / tipo de la celda de la batería | C1: Embalaje de la batería | D1: Vatios/hora | E1: Potencial de derrame | I1: ¿El producto incluye baterías o es una batería en sí mismo? | J1: Composición química / tipo de la celda de la batería | K1: Embalaje de la batería | L1: Número de celdas | M1: Vatios/hora | N1: Potencial de derrame | O1: Statut de validation des détails
A2: Sí | B2: _18650_ | C2: En el aparato | D2: WH <= 100 | E2: Derramable | F2: _18650_ | H2: =I2&J2&K2&L2&M2&N2 -> No | I2: No | O2: Completo
A3: No | B3: Óxido_cobalto_Litio | C3: Con el equipo | D3: 101 - 300 WH | E3: No derramable | F3: Óxido_cobalto_Litio | H3: =I3&J3&K3&L3&M3&N3 -> SíAlcalina | I3: Sí | J3: Alcalina | O3: Completo
B4: Ion_litio | C4: Independiente | D4: WH > 300 | F4: Ion_litio | H4: =I4&J4&K4&L4&M4&N4 -> SíNíquel_metal_hidruro | I4: Sí | J4: Níquel_metal_hidruro | O4: Completo
B5: Litio_ferrofosfato | F5: Litio_ferrofosfato | H5: =I5&J5&K5&L5&M5&N5 -> SíNíquel_cadmio | I5: Sí | J5: Níquel_cadmio | O5: Completo
B6: Óxido_de_cobalto_de_manganeso_y_litio | F6: Óxido_de_cobalto_de_manganeso_y_litio | H6: =I6&J6&K6&L6&M6&N6 -> SíZinc_carbono | I6: Sí | J6: Zinc_carbono | O6: Completo
B7: Polímero_de_litio | F7: Polímero_de_litio | H7: =I7&J7&K7&L7&M7&N7 -> SíZinc_aire | I7: Sí | J7: Zinc_aire | O7: Completo
B8: Titanato_de_litio | F8: Titanato_de_litio | H8: =I8&J8&K8&L8&M8&N8 -> SíÓxido_de_plata | I8: Sí | J8: Óxido_de_plata | O8: Completo
B9: Litio_Metal | F9: Litio_Metal | H9: =I9&J9&K9&L9&M9&N9 -> SíIon_litioEn el aparato | I9: Sí | J9: Ion_litio | K9: En el aparato | O9: Incompleto
B10: Litio_Cloruro_de_Tionilo | F10: Litio_Cloruro_de_Tionilo | H10: =I10&J10&K10&L10&M10&N10 -> SíLitio_MetalEn el aparato | I10: Sí | J10: Litio_Metal | K10: En el aparato | O10: Completo
B11: _LR44_ | F11: _LR44_ | H11: =I11&J11&K11&L11&M11&N11 -> SíIon_litioCon el equipo | I11: Sí | J11: Ion_litio | K11: Con el equipo | O11: Incompleto
B12: Alcalina | F12: Alcalina | H12: =I12&J12&K12&L12&M12&N12 -> SíLitio_MetalCon el equipo | I12: Sí | J12: Litio_Metal | K12: Con el equipo | O12: Completo
B13: Carbono_zinc | F13: Carbono_zinc | H13: =I13&J13&K13&L13&M13&N13 -> SíIon_litioIndependiente | I13: Sí | J13: Ion_litio | K13: Independiente | O13: Incompleto
B14: _CR2032_ | F14: _CR2032_ | H14: =I14&J14&K14&L14&M14&N14 -> SíLitio_MetalIndependiente | I14: Sí | J14: Litio_Metal | K14: Independiente | O14: Completo
B15: Plomo_ácido | F15: Plomo_ácido | H15: =I15&J15&K15&L15&M15&N15 -> #REF! | I15: Sí | J15: Ion_litio | M15: =IF('Ficha de exención para baterías'!$P$13>0,'Ficha de exención para baterías'!$P$13," ") -> #REF! | O15: Incompleto
B16: Plomo_calcio | F16: Plomo_calcio | H16: =I16&J16&K16&L16&M16&N16 -> SíIon_litio | I16: Sí | J16: Ion_litio | O16: Incompleto
B17: Níquel_cadmio | F17: Níquel_cadmio | H17: =I17&J17&K17&L17&M17&N17 -> SíLitio_Metal | I17: Sí | J17: Litio_Metal | O17: Incompleto
B18: Níquel_metal_hidruro | F18: Níquel_metal_hidruro | H18: =I18&J18&K18&L18&M18&N18 -> SíPlomo_ácidoEn el aparatoNo derramable | I18: Sí | J18: Plomo_ácido | K18: En el aparato | N18: No derramable | O18: Completo
B19: Óxido_de_plata | F19: Óxido_de_plata | H19: =I19&J19&K19&L19&M19&N19 -> SíPlomo_ácidoEn el aparatoDerramable | I19: Sí | J19: Plomo_ácido | K19: En el aparato | N19: Derramable | O19: Completo
B20: Zinc | F20: Zinc | H20: =I20&J20&K20&L20&M20&N20 -> SíPlomo_ácido | I20: Sí | J20: Plomo_ácido | O20: Incompleto
B21: Zinc_aire | F21: Zinc_aire | H21: =I21&J21&K21&L21&M21&N21 -> SíPlomo_calcioEn el aparatoNo derramable | I21: Sí | J21: Plomo_calcio | K21: En el aparato | N21: No derramable | O21: Completo
B22: Zinc_carbono | F22: Zinc_carbono | H22: =I22&J22&K22&L22&M22&N22 -> SíPlomo_calcioEn el aparatoDerramable | I22: Sí | J22: Plomo_calcio | K22: En el aparato | N22: Derramable | O22: Completo
H23: =I23&J23&K23&L23&M23&N23 -> SíPlomo_calcio | I23: Sí | J23: Plomo_calcio | O23: Incompleto
H24: =I24&J24&K24&L24&M24&N24 -> SíLitio_Metal | I24: Sí | J24: Litio_Metal | O24: Incompleto
H25: =I25&J25&K25&L25&M25&N25 -> SíPolímero_de_litioEn el aparato | I25: Sí | J25: Polímero_de_litio | K25: En el aparato | O25: Incompleto
A26: ! | H26: =I26&J26&K26&L26&M26&N26 -> SíPolímero_de_litioCon el equipo | I26: Sí | J26: Polímero_de_litio | K26: Con el equipo | O26: Incompleto
A27: @ | H27: =I27&J27&K27&L27&M27&N27 -> SíPolímero_de_litioIndependiente | I27: Sí | J27: Polímero_de_litio | K27: Independiente | O27: Incompleto
A28: # | H28: =I28&J28&K28&L28&M28&N28 -> #REF! | I28: Sí | J28: Polímero_de_litio | M28: =IF('Ficha de exención para baterías'!$P$13>0,'Ficha de exención para baterías'!$P$13," ") -> #REF! | O28: Incompleto
A29: $ | H29: =I29&J29&K29&L29&M29&N29 -> SíPolímero_de_litio | I29: Sí | J29: Polímero_de_litio | O29: Incompleto
A30: % | H30: =I30&J30&K30&L30&M30&N30 -> SíZinc | I30: Sí | J30: Zinc | O30: Completo
A31: ^ | H31: =I31&J31&K31&L31&M31&N31 -> NoAlcalina | I31: No | J31: Alcalina | O31: Incompleto
A32: & | H32: =I32&J32&K32&L32&M32&N32 -> NoNíquel_metal_hidruro | I32: No | J32: Níquel_metal_hidruro | O32: Incompleto
A33: * | H33: =I33&J33&K33&L33&M33&N33 -> NoNíquel_cadmio | I33: No | J33: Níquel_cadmio | O33: Incompleto
H34: =I34&J34&K34&L34&M34&N34 -> NoZinc_carbono | I34: No | J34: Zinc_carbono | O34: Incompleto
H35: =I35&J35&K35&L35&M35&N35 -> NoZinc_aire | I35: No | J35: Zinc_aire | O35: Incompleto
H36: =I36&J36&K36&L36&M36&N36 -> NoÓxido_de_plata | I36: No | J36: Óxido_de_plata | O36: Incompleto
H37: =I37&J37&K37&L37&M37&N37 -> #REF! | I37: No | J37: Ion_litio | K37: En el aparato | M37: =IF('Ficha de exención para baterías'!$P$13>0,'Ficha de exención para baterías'!$P$13," ") -> #REF! | O37: Incompleto
H38: =I38&J38&K38&L38&M38&N38 -> NoIon_litioEn el aparato | I38: No | J38: Ion_litio | K38: En el aparato | O38: Incompleto
H39: =I39&J39&K39&L39&M39&N39 -> NoLitio_MetalEn el aparato | I39: No | J39: Litio_Metal | K39: En el aparato | O39: Incompleto
H40: =I40&J40&K40&L40&M40&N40 -> NoIon_litioCon el equipo | I40: No | J40: Ion_litio | K40: Con el equipo | O40: Incompleto
H41: =I41&J41&K41&L41&M41&N41 -> NoLitio_MetalCon el equipo | I41: No | J41: Litio_Metal | K41: Con el equipo | O41: Incompleto
H42: =I42&J42&K42&L42&M42&N42 -> #REF! | I42: No | J42: Ion_litio | K42: Con el equipo | M42: =IF('Ficha de exención para baterías'!$P$13>0,'Ficha de exención para baterías'!$P$13," ") -> #REF! | O42: Incompleto
H43: =I43&J43&K43&L43&M43&N43 -> #REF! | I43: No | J43: Ion_litio | K43: Independiente | M43: =IF('Ficha de exención para baterías'!$P$13>0,'Ficha de exención para baterías'!$P$13," ") -> #REF! | O43: Incompleto
H44: =I44&J44&K44&L44&M44&N44 -> NoIon_litioIndependiente | I44: No | J44: Ion_litio | K44: Independiente | O44: Incompleto
H45: =I45&J45&K45&L45&M45&N45 -> NoLitio_MetalIndependiente | I45: No | J45: Litio_Metal | K45: Independiente | O45: Incompleto
H46: =I46&J46&K46&L46&M46&N46 -> #REF! | I46: No | J46: Ion_litio | M46: =IF('Ficha de exención para baterías'!$P$13>0,'Ficha de exención para baterías'!$P$13," ") -> #REF! | O46: Incompleto
H47: =I47&J47&K47&L47&M47&N47 -> NoIon_litio | I47: No | J47: Ion_litio | O47: Incompleto
H48: =I48&J48&K48&L48&M48&N48 -> NoLitio_Metal | I48: No | J48: Litio_Metal | O48: Incompleto
H49: =I49&J49&K49&L49&M49&N49 -> NoPlomo_ácidoNo derramable | I49: No | J49: Plomo_ácido | N49: No derramable | O49: Incompleto
H50: =I50&J50&K50&L50&M50&N50 -> NoPlomo_ácidoDerramable | I50: No | J50: Plomo_ácido | N50: Derramable | O50: Incompleto
H51: =I51&J51&K51&L51&M51&N51 -> NoPlomo_ácido | I51: No | J51: Plomo_ácido | O51: Incompleto
H52: =I52&J52&K52&L52&M52&N52 -> NoPlomo_calcioNo derramable | I52: No | J52: Plomo_calcio | N52: No derramable | O52: Incompleto
H53: =I53&J53&K53&L53&M53&N53 -> NoPlomo_calcioDerramable | I53: No | J53: Plomo_calcio | N53: Derramable | O53: Incompleto
H54: =I54&J54&K54&L54&M54&N54 -> NoPlomo_calcio | I54: No | J54: Plomo_calcio | O54: Incompleto
H55: =I55&J55&K55&L55&M55&N55 -> NoLitio_Metal | I55: No | J55: Litio_Metal | O55: Incompleto
H56: =I56&J56&K56&L56&M56&N56 -> #REF! | I56: No | J56: Polímero_de_litio | K56: En el aparato | M56: =IF('Ficha de exención para baterías'!$P$13>0,'Ficha de exención para baterías'!$P$13," ") -> #REF! | O56: Incompleto
H57: =I57&J57&K57&L57&M57&N57 -> NoPolímero_de_litioEn el aparato | I57: No | J57: Polímero_de_litio | K57: En el aparato | O57: Incompleto
H58: =I58&J58&K58&L58&M58&N58 -> NoPolímero_de_litioCon el equipo | I58: No | J58: Polímero_de_litio | K58: Con el equipo | O58: Incompleto
H59: =I59&J59&K59&L59&M59&N59 -> #REF! | I59: No | J59: Polímero_de_litio | K59: Con el equipo | M59: =IF('Ficha de exención para baterías'!$P$13>0,'Ficha de exención para baterías'!$P$13," ") -> #REF! | O59: Incompleto
H60: =I60&J60&K60&L60&M60&N60 -> #REF! | I60: No | J60: Polímero_de_litio | K60: Independiente | M60: =IF('Ficha de exención para baterías'!$P$13>0,'Ficha de exención para baterías'!$P$13," ") -> #REF! | O60: Incompleto
H61: =I61&J61&K61&L61&M61&N61 -> NoPolímero_de_litioIndependiente | I61: No | J61: Polímero_de_litio | K61: Independiente | O61: Incompleto
H62: =I62&J62&K62&L62&M62&N62 -> #REF! | I62: No | J62: Polímero_de_litio | M62: =IF('Ficha de exención para baterías'!$P$13>0,'Ficha de exención para baterías'!$P$13," ") -> #REF! | O62: Incompleto
H63: =I63&J63&K63&L63&M63&N63 -> NoPolímero_de_litio | I63: No | J63: Polímero_de_litio | O63: Incompleto
H64: =I64&J64&K64&L64&M64&N64 -> NoZinc | I64: No | J64: Zinc | O64: Incompleto
H65: =I65&J65&K65&L65&M65&N65 -> NoZinc_carbonoEn el aparato | I65: No | J65: Zinc_carbono | K65: En el aparato | O65: Incompleto
H66: =I66&J66&K66&L66&M66&N66 -> NoZinc_carbonoCon el equipo | I66: No | J66: Zinc_carbono | K66: Con el equipo | O66: Incompleto
H67: =I67&J67&K67&L67&M67&N67 -> NoZinc_carbonoIndependiente | I67: No | J67: Zinc_carbono | K67: Independiente | O67: Incompleto
H68: =I68&J68&K68&L68&M68&N68 -> NoIndependiente | I68: No | K68: Independiente | O68: Incompleto
H69: =I69&J69&K69&L69&M69&N69 -> NoEn el aparato | I69: No | K69: En el aparato | O69: Incompleto
H70: =I70&J70&K70&L70&M70&N70 -> NoCon el equipo | I70: No | K70: Con el equipo | O70: Incompleto
H71: =I71&J71&K71&L71&M71&N71 -> NoDerramable | I71: No | N71: Derramable | O71: Incompleto
H72: =I72&J72&K72&L72&M72&N72 -> NoNo derramable | I72: No | N72: No derramable | O72: Incompleto
H73: =I73&J73&K73&L73&M73&N73 -> NoIndependienteDerramable | I73: No | K73: Independiente | N73: Derramable | O73: Incompleto
H74: =I74&J74&K74&L74&M74&N74 -> NoEn el aparatoDerramable | I74: No | K74: En el aparato | N74: Derramable | O74: Incompleto
H75: =I75&J75&K75&L75&M75&N75 -> NoCon el equipoDerramable | I75: No | K75: Con el equipo | N75: Derramable | O75: Incompleto
H76: =I76&J76&K76&L76&M76&N76 -> NoIndependienteNo derramable | I76: No | K76: Independiente | N76: No derramable | O76: Incompleto
H77: =I77&J77&K77&L77&M77&N77 -> NoEn el aparatoNo derramable | I77: No | K77: En el aparato | N77: No derramable | O77: Incompleto
H78: =I78&J78&K78&L78&M78&N78 -> NoCon el equipoNo derramable | I78: No | K78: Con el equipo | N78: No derramable | O78: Incompleto
H79: =I79&J79&K79&L79&M79&N79 -> SíZincEn el aparato | I79: Sí | J79: Zinc | K79: En el aparato | O79: Completo
H80: =I80&J80&K80&L80&M80&N80 -> SíAlcalinaEn el aparato | I80: Sí | J80: Alcalina | K80: En el aparato | O80: Completo
H81: =I81&J81&K81&L81&M81&N81 -> SíNíquel_metal_hidruroEn el aparato | I81: Sí | J81: Níquel_metal_hidruro | K81: En el aparato | O81: Completo
H82: =I82&J82&K82&L82&M82&N82 -> SíNíquel_cadmioEn el aparato | I82: Sí | J82: Níquel_cadmio | K82: En el aparato | O82: Completo
H83: =I83&J83&K83&L83&M83&N83 -> SíZinc_carbonoEn el aparato | I83: Sí | J83: Zinc_carbono | K83: En el aparato | O83: Completo
H84: =I84&J84&K84&L84&M84&N84 -> SíZinc_aireEn el aparato | I84: Sí | J84: Zinc_aire | K84: En el aparato | O84: Completo
H85: =I85&J85&K85&L85&M85&N85 -> SíÓxido_de_plataEn el aparato | I85: Sí | J85: Óxido_de_plata | K85: En el aparato | O85: Completo
H86: =I86&J86&K86&L86&M86&N86 -> SíZincCon el equipo | I86: Sí | J86: Zinc | K86: Con el equipo | O86: Completo
H87: =I87&J87&K87&L87&M87&N87 -> SíAlcalinaCon el equipo | I87: Sí | J87: Alcalina | K87: Con el equipo | O87: Completo
H88: =I88&J88&K88&L88&M88&N88 -> SíNíquel_metal_hidruroCon el equipo | I88: Sí | J88: Níquel_metal_hidruro | K88: Con el equipo | O88: Completo
H89: =I89&J89&K89&L89&M89&N89 -> SíNíquel_cadmioCon el equipo | I89: Sí | J89: Níquel_cadmio | K89: Con el equipo | O89: Completo
H90: =I90&J90&K90&L90&M90&N90 -> SíZinc_carbonoCon el equipo | I90: Sí | J90: Zinc_carbono | K90: Con el equipo | O90: Completo
... H99: =I99&J99&K99&L99&M99&N99 -> SíÓxido_de_plataIndependiente | I99: Sí | J99: Óxido_de_plata | K99: Independiente | O99: Completo
H100: =I100&J100&K100&L100&M100&N100 -> Alcalina | J100: Alcalina | O100: Incompleto
H101: =I101&J101&K101&L101&M101&N101 -> Níquel_metal_hidruro | J101: Níquel_metal_hidruro | O101: Incompleto
H102: =I102&J102&K102&L102&M102&N102 -> Níquel_cadmio | J102: Níquel_cadmio | O102: Incompleto
H103: =I103&J103&K103&L103&M103&N103 -> Zinc_carbono | J103: Zinc_carbono | O103: Incompleto
H104: =I104&J104&K104&L104&M104&N104 -> Zinc_aire | J104: Zinc_aire | O104: Incompleto
H105: =I105&J105&K105&L105&M105&N105 -> Óxido_de_plata | J105: Óxido_de_plata | O105: Incompleto
H106: =I106&J106&K106&L106&M106&N106 -> Ion_litioEn el aparato | J106: Ion_litio | K106: En el aparato | O106: Incompleto
H107: =I107&J107&K107&L107&M107&N107 -> Ion_litioCon el equipo | J107: Ion_litio | K107: Con el equipo | O107: Incompleto
H108: =I108&J108&K108&L108&M108&N108 -> Ion_litioIndependiente | J108: Ion_litio | K108: Independiente | O108: Incompleto
...

Sheet Fórmula 2
A4: _18650_ | C4: Polímero_de_litio | E4: Plomo_ácido | K4: Una_sola_celda
A5: Una_sola_celda | C5: Una_sola_celda | E5: Derramable | K5: WH <= 20
A6: Varias_celdas | C6: Varias_celdas | E6: No derramable | K6: WH > 20
A8: Óxido_cobalto_Litio | C8: Titanato_de_litio | E8: Plomo_calcio | K8: Varias_celdas
A9: Una_sola_celda | C9: Una_sola_celda | E9: Derramable | K9: WH <= 100
A10: Varias_celdas | C10: Varias_celdas | E10: No derramable | K10: 101 - 300 WH
K11: WH > 300
A12: Ion_litio
A13: Una_sola_celda
A14: Varias_celdas
A16: Litio_ferrofosfato
A17: Una_sola_celda
A18: Varias_celdas | E18: Battery Packaging ON/OFF | G18: Spillability | I18: ASIN/Title
E19: =OR('Ficha de exención para baterías'!M13="_18650_",'Ficha de exención para baterías'!M13="Óxido_cobalto_Litio",'Ficha de exención para baterías'!M13="Ion_litio",'Ficha de exención para baterías'!M13="Litio_ferrofosfato",'Ficha de exención para baterías'!M13="Óxido_de_cobalto_de_manganeso_y_litio",'Ficha de exención para baterías'!M13="Polímero_de_litio",'Ficha de exención para baterías'!M13="Titanato_de_litio",'Ficha de exención para baterías'!M13="Litio_Metal",'Ficha de exención para baterías'!M13="_CR2032_",'Ficha de exención para baterías'!M13="Litio_Cloruro_de_Tionilo",'Ficha de exención para baterías'!M13="Plomo_ácido",'Ficha de exención para baterías'!M13="Plomo_calcio") -> #REF! | G19: =OR('Ficha de exención para baterías'!M13="Plomo_ácido",'Ficha de exención para baterías'!M13="Plomo_calcio") -> #REF! | I19: =OR(LEN('Ficha de exención para baterías'!K13)>0) -> #REF!
A20: Óxido_de_cobalto_de_manganeso_y_litio | E20: =OR('Ficha de exención para baterías'!M14="_18650_",'Ficha de exención para baterías'!M14="Óxido_cobalto_Litio",'Ficha de exención para baterías'!M14="Ion_litio",'Ficha de exención para baterías'!M14="Litio_ferrofosfato",'Ficha de exención para baterías'!M14="Óxido_de_cobalto_de_manganeso_y_litio",'Ficha de exención para baterías'!M14="Polímero_de_litio",'Ficha de exención para baterías'!M14="Titanato_de_litio",'Ficha de exención para baterías'!M14="Litio_Metal",'Ficha de exención para baterías'!M14="_CR2032_",'Ficha de exención para baterías'!M14="Litio_Cloruro_de_Tionilo",'Ficha de exención para baterías'!M14="Plomo_ácido",'Ficha de exención para baterías'!M14="Plomo_calcio") -> #REF! | G20: =OR('Ficha de exención para baterías'!M14="Plomo_ácido",'Ficha de exención para baterías'!M14="Plomo_calcio") -> #REF! | I20: =OR(LEN('Ficha de exención para baterías'!K14)>0) -> #REF!
A21: Una_sola_celda | E21: =OR('Ficha de exención para baterías'!M15="_18650_",'Ficha de exención para baterías'!M15="Óxido_cobalto_Litio",'Ficha de exención para baterías'!M15="Ion_litio",'Ficha de exención para baterías'!M15="Litio_ferrofosfato",'Ficha de exención para baterías'!M15="Óxido_de_cobalto_de_manganeso_y_litio",'Ficha de exención para baterías'!M15="Polímero_de_litio",'Ficha de exención para baterías'!M15="Titanato_de_litio",'Ficha de exención para baterías'!M15="Litio_Metal",'Ficha de exención para baterías'!M15="_CR2032_",'Ficha de exención para baterías'!M15="Litio_Cloruro_de_Tionilo",'Ficha de exención para baterías'!M15="Plomo_ácido",'Ficha de exención para baterías'!M15="Plomo_calcio") -> #REF! | G21: =OR('Ficha de exención para baterías'!M15="Plomo_ácido",'Ficha de exención para baterías'!M15="Plomo_calcio") -> #REF! | I21: =OR(LEN('Ficha de exención para baterías'!K15)>0) -> #REF!
A22: Varias_celdas | E22: =OR('Ficha de exención para baterías'!M16="_18650_",'Ficha de exención para baterías'!M16="Óxido_cobalto_Litio",'Ficha de exención para baterías'!M16="Ion_litio",'Ficha de exención para baterías'!M16="Litio_ferrofosfato",'Ficha de exención para baterías'!M16="Óxido_de_cobalto_de_manganeso_y_litio",'Ficha de exención para baterías'!M16="Polímero_de_litio",'Ficha de exención para baterías'!M16="Titanato_de_litio",'Ficha de exención para baterías'!M16="Litio_Metal",'Ficha de exención para baterías'!M16="_CR2032_",'Ficha de exención para baterías'!M16="Litio_Cloruro_de_Tionilo",'Ficha de exención para baterías'!M16="Plomo_ácido",'Ficha de exención para baterías'!M16="Plomo_calcio") -> #REF! | G22: =OR('Ficha de exención para baterías'!M16="Plomo_ácido",'Ficha de exención para baterías'!M16="Plomo_calcio") -> #REF! | I22: =OR(LEN('Ficha de exención para baterías'!K16)>0) -> #REF!
E23: =OR('Ficha de exención para baterías'!M17="_18650_",'Ficha de exención para baterías'!M17="Óxido_cobalto_Litio",'Ficha de exención para baterías'!M17="Ion_litio",'Ficha de exención para baterías'!M17="Litio_ferrofosfato",'Ficha de exención para baterías'!M17="Óxido_de_cobalto_de_manganeso_y_litio",'Ficha de exención para baterías'!M17="Polímero_de_litio",'Ficha de exención para baterías'!M17="Titanato_de_litio",'Ficha de exención para baterías'!M17="Litio_Metal",'Ficha de exención para baterías'!M17="_CR2032_",'Ficha de exención para baterías'!M17="Litio_Cloruro_de_Tionilo",'Ficha de exención para baterías'!M17="Plomo_ácido",'Ficha de exención para baterías'!M17="Plomo_calcio") -> #REF! | G23: =OR('Ficha de exención para baterías'!M17="Plomo_ácido",'Ficha de exención para baterías'!M17="Plomo_calcio") -> #REF! | I23: =OR(LEN('Ficha de exención para baterías'!K17)>0) -> #REF!
E24: =OR('Ficha de exención para baterías'!M18="_18650_",'Ficha de exención para baterías'!M18="Óxido_cobalto_Litio",'Ficha de exención para baterías'!M18="Ion_litio",'Ficha de exención para baterías'!M18="Litio_ferrofosfato",'Ficha de exención para baterías'!M18="Óxido_de_cobalto_de_manganeso_y_litio",'Ficha de exención para baterías'!M18="Polímero_de_litio",'Ficha de exención para baterías'!M18="Titanato_de_litio",'Ficha de exención para baterías'!M18="Litio_Metal",'Ficha de exención para baterías'!M18="_CR2032_",'Ficha de exención para baterías'!M18="Litio_Cloruro_de_Tionilo",'Ficha de exención para baterías'!M18="Plomo_ácido",'Ficha de exención para baterías'!M18="Plomo_calcio") -> #REF! | G24: =OR('Ficha de exención para baterías'!M18="Plomo_ácido",'Ficha de exención para baterías'!M18="Plomo_calcio") -> #REF! | I24: =OR(LEN('Ficha de exención para baterías'!K18)>0) -> #REF!
A25: Sí | B25: No | E25: =OR('Ficha de exención para baterías'!M19="_18650_",'Ficha de exención para baterías'!M19="Óxido_cobalto_Litio",'Ficha de exención para baterías'!M19="Ion_litio",'Ficha de exención para baterías'!M19="Litio_ferrofosfato",'Ficha de exención para baterías'!M19="Óxido_de_cobalto_de_manganeso_y_litio",'Ficha de exención para baterías'!M19="Polímero_de_litio",'Ficha de exención para baterías'!M19="Titanato_de_litio",'Ficha de exención para baterías'!M19="Litio_Metal",'Ficha de exención para baterías'!M19="_CR2032_",'Ficha de exención para baterías'!M19="Litio_Cloruro_de_Tionilo",'Ficha de exención para baterías'!M19="Plomo_ácido",'Ficha de exención para baterías'!M19="Plomo_calcio") -> #REF! | G25: =OR('Ficha de exención para baterías'!M19="Plomo_ácido",'Ficha de exención para baterías'!M19="Plomo_calcio") -> #REF! | I25: =OR(LEN('Ficha de exención para baterías'!K19)>0) -> #REF!
A26: _18650_ | C26: _18650_ | E26: =OR('Ficha de exención para baterías'!M20="_18650_",'Ficha de exención para baterías'!M20="Óxido_cobalto_Litio",'Ficha de exención para baterías'!M20="Ion_litio",'Ficha de exención para baterías'!M20="Litio_ferrofosfato",'Ficha de exención para baterías'!M20="Óxido_de_cobalto_de_manganeso_y_litio",'Ficha de exención para baterías'!M20="Polímero_de_litio",'Ficha de exención para baterías'!M20="Titanato_de_litio",'Ficha de exención para baterías'!M20="Litio_Metal",'Ficha de exención para baterías'!M20="_CR2032_",'Ficha de exención para baterías'!M20="Litio_Cloruro_de_Tionilo",'Ficha de exención para baterías'!M20="Plomo_ácido",'Ficha de exención para baterías'!M20="Plomo_calcio") -> #REF! | G26: =OR('Ficha de exención para baterías'!M20="Plomo_ácido",'Ficha de exención para baterías'!M20="Plomo_calcio") -> #REF! | I26: =OR(LEN('Ficha de exención para baterías'!K20)>0) -> #REF!
A27: Óxido_cobalto_Litio | C27: Óxido_de_litio_y_cobalto | E27: =OR('Ficha de exención para baterías'!M21="_18650_",'Ficha de exención para baterías'!M21="Óxido_cobalto_Litio",'Ficha de exención para baterías'!M21="Ion_litio",'Ficha de exención para baterías'!M21="Litio_ferrofosfato",'Ficha de exención para baterías'!M21="Óxido_de_cobalto_de_manganeso_y_litio",'Ficha de exención para baterías'!M21="Polímero_de_litio",'Ficha de exención para baterías'!M21="Titanato_de_litio",'Ficha de exención para baterías'!M21="Litio_Metal",'Ficha de exención para baterías'!M21="_CR2032_",'Ficha de exención para baterías'!M21="Litio_Cloruro_de_Tionilo",'Ficha de exención para baterías'!M21="Plomo_ácido",'Ficha de exención para baterías'!M21="Plomo_calcio") -> #REF! | G27: =OR('Ficha de exención para baterías'!M21="Plomo_ácido",'Ficha de exención para baterías'!M21="Plomo_calcio") -> #REF! | I27: =OR(LEN('Ficha de exención para baterías'!K21)>0) -> #REF!
A28: Ion_litio | C28: Ion_litio | E28: =OR('Ficha de exención para baterías'!M22="_18650_",'Ficha de exención para baterías'!M22="Óxido_cobalto_Litio",'Ficha de exención para baterías'!M22="Ion_litio",'Ficha de exención para baterías'!M22="Litio_ferrofosfato",'Ficha de exención para baterías'!M22="Óxido_de_cobalto_de_manganeso_y_litio",'Ficha de exención para baterías'!M22="Polímero_de_litio",'Ficha de exención para baterías'!M22="Titanato_de_litio",'Ficha de exención para baterías'!M22="Litio_Metal",'Ficha de exención para baterías'!M22="_CR2032_",'Ficha de exención para baterías'!M22="Litio_Cloruro_de_Tionilo",'Ficha de exención para baterías'!M22="Plomo_ácido",'Ficha de exención para baterías'!M22="Plomo_calcio") -> #REF! | G28: =OR('Ficha de exención para baterías'!M22="Plomo_ácido",'Ficha de exención para baterías'!M22="Plomo_calcio") -> #REF! | I28: =OR(LEN('Ficha de exención para baterías'!K22)>0) -> #REF!
A29: Litio_ferrofosfato | C29: Fosfato_de_hierro_y_litio | E29: =OR('Ficha de exención para baterías'!M23="_18650_",'Ficha de exención para baterías'!M23="Óxido_cobalto_Litio",'Ficha de exención para baterías'!M23="Ion_litio",'Ficha de exención para baterías'!M23="Litio_ferrofosfato",'Ficha de exención para baterías'!M23="Óxido_de_cobalto_de_manganeso_y_litio",'Ficha de exención para baterías'!M23="Polímero_de_litio",'Ficha de exención para baterías'!M23="Titanato_de_litio",'Ficha de exención para baterías'!M23="Litio_Metal",'Ficha de exención para baterías'!M23="_CR2032_",'Ficha de exención para baterías'!M23="Litio_Cloruro_de_Tionilo",'Ficha de exención para baterías'!M23="Plomo_ácido",'Ficha de exención para baterías'!M23="Plomo_calcio") -> #REF! | G29: =OR('Ficha de exención para baterías'!M23="Plomo_ácido",'Ficha de exención para baterías'!M23="Plomo_calcio") -> #REF! | I29: =OR(LEN('Ficha de exención para baterías'!K23)>0) -> #REF!
A30: Óxido_de_cobalto_de_manganeso_y_litio | C30: Óxido_de_litio_níquel_manganeso_y_cobalto | E30: =OR('Ficha de exención para baterías'!M24="_18650_",'Ficha de exención para baterías'!M24="Óxido_cobalto_Litio",'Ficha de exención para baterías'!M24="Ion_litio",'Ficha de exención para baterías'!M24="Litio_ferrofosfato",'Ficha de exención para baterías'!M24="Óxido_de_cobalto_de_manganeso_y_litio",'Ficha de exención para baterías'!M24="Polímero_de_litio",'Ficha de exención para baterías'!M24="Titanato_de_litio",'Ficha de exención para baterías'!M24="Litio_Metal",'Ficha de exención para baterías'!M24="_CR2032_",'Ficha de exención para baterías'!M24="Litio_Cloruro_de_Tionilo",'Ficha de exención para baterías'!M24="Plomo_ácido",'Ficha de exención para baterías'!M24="Plomo_calcio") -> #REF! | G30: =OR('Ficha de exención para baterías'!M24="Plomo_ácido",'Ficha de exención para baterías'!M24="Plomo_calcio") -> #REF! | I30: =OR(LEN('Ficha de exención para baterías'!K24)>0) -> #REF!
A31: Polímero_de_litio | C31: Polímero_de_litio | E31: =OR('Ficha de exención para baterías'!M25="_18650_",'Ficha de exención para baterías'!M25="Óxido_cobalto_Litio",'Ficha de exención para baterías'!M25="Ion_litio",'Ficha de exención para baterías'!M25="Litio_ferrofosfato",'Ficha de exención para baterías'!M25="Óxido_de_cobalto_de_manganeso_y_litio",'Ficha de exención para baterías'!M25="Polímero_de_litio",'Ficha de exención para baterías'!M25="Titanato_de_litio",'Ficha de exención para baterías'!M25="Litio_Metal",'Ficha de exención para baterías'!M25="_CR2032_",'Ficha de exención para baterías'!M25="Litio_Cloruro_de_Tionilo",'Ficha de exención para baterías'!M25="Plomo_ácido",'Ficha de exención para baterías'!M25="Plomo_calcio") -> #REF! | G31: =OR('Ficha de exención para baterías'!M25="Plomo_ácido",'Ficha de exención para baterías'!M25="Plomo_calcio") -> #REF! | I31: =OR(LEN('Ficha de exención para baterías'!K25)>0) -> #REF!
A32: Titanato_de_litio | C32: Titanato_de_litio | E32: =OR('Ficha de exención para baterías'!M26="_18650_",'Ficha de exención para baterías'!M26="Óxido_cobalto_Litio",'Ficha de exención para baterías'!M26="Ion_litio",'Ficha de exención para baterías'!M26="Litio_ferrofosfato",'Ficha de exención para baterías'!M26="Óxido_de_cobalto_de_manganeso_y_litio",'Ficha de exención para baterías'!M26="Polímero_de_litio",'Ficha de exención para baterías'!M26="Titanato_de_litio",'Ficha de exención para baterías'!M26="Litio_Metal",'Ficha de exención para baterías'!M26="_CR2032_",'Ficha de exención para baterías'!M26="Litio_Cloruro_de_Tionilo",'Ficha de exención para baterías'!M26="Plomo_ácido",'Ficha de exención para baterías'!M26="Plomo_calcio") -> #REF! | G32: =OR('Ficha de exención para baterías'!M26="Plomo_ácido",'Ficha de exención para baterías'!M26="Plomo_calcio") -> #REF! | I32: =OR(LEN('Ficha de exención para baterías'!K26)>0) -> #REF!
A33: Litio_Metal | C33: Metal_de_litio | E33: =OR('Ficha de exención para baterías'!M27="_18650_",'Ficha de exención para baterías'!M27="Óxido_cobalto_Litio",'Ficha de exención para baterías'!M27="Ion_litio",'Ficha de exención para baterías'!M27="Litio_ferrofosfato",'Ficha de exención para baterías'!M27="Óxido_de_cobalto_de_manganeso_y_litio",'Ficha de exención para baterías'!M27="Polímero_de_litio",'Ficha de exención para baterías'!M27="Titanato_de_litio",'Ficha de exención para baterías'!M27="Litio_Metal",'Ficha de exención para baterías'!M27="_CR2032_",'Ficha de exención para baterías'!M27="Litio_Cloruro_de_Tionilo",'Ficha de exención para baterías'!M27="Plomo_ácido",'Ficha de exención para baterías'!M27="Plomo_calcio") -> #REF! | G33: =OR('Ficha de exención para baterías'!M27="Plomo_ácido",'Ficha de exención para baterías'!M27="Plomo_calcio") -> #REF! | I33: =OR(LEN('Ficha de exención para baterías'!K27)>0) -> #REF!
A34: Litio_Cloruro_de_Tionilo | C34: Cloruro_de_tionilo_de_litio | E34: =OR('Ficha de exención para baterías'!M28="_18650_",'Ficha de exención para baterías'!M28="Óxido_cobalto_Litio",'Ficha de exención para baterías'!M28="Ion_litio",'Ficha de exención para baterías'!M28="Litio_ferrofosfato",'Ficha de exención para baterías'!M28="Óxido_de_cobalto_de_manganeso_y_litio",'Ficha de exención para baterías'!M28="Polímero_de_litio",'Ficha de exención para baterías'!M28="Titanato_de_litio",'Ficha de exención para baterías'!M28="Litio_Metal",'Ficha de exención para baterías'!M28="_CR2032_",'Ficha de exención para baterías'!M28="Litio_Cloruro_de_Tionilo",'Ficha de exención para baterías'!M28="Plomo_ácido",'Ficha de exención para baterías'!M28="Plomo_calcio") -> #REF! | G34: =OR('Ficha de exención para baterías'!M28="Plomo_ácido",'Ficha de exención para baterías'!M28="Plomo_calcio") -> #REF! | I34: =OR(LEN('Ficha de exención para baterías'!K28)>0) -> #REF!
A35: _LR44_ | C35: _LR44_ | E35: =OR('Ficha de exención para baterías'!M29="_18650_",'Ficha de exención para baterías'!M29="Óxido_cobalto_Litio",'Ficha de exención para baterías'!M29="Ion_litio",'Ficha de exención para baterías'!M29="Litio_ferrofosfato",'Ficha de exención para baterías'!M29="Óxido_de_cobalto_de_manganeso_y_litio",'Ficha de exención para baterías'!M29="Polímero_de_litio",'Ficha de exención para baterías'!M29="Titanato_de_litio",'Ficha de exención para baterías'!M29="Litio_Metal",'Ficha de exención para baterías'!M29="_CR2032_",'Ficha de exención para baterías'!M29="Litio_Cloruro_de_Tionilo",'Ficha de exención para baterías'!M29="Plomo_ácido",'Ficha de exención para baterías'!M29="Plomo_calcio") -> #REF! | G35: =OR('Ficha de exención para baterías'!M29="Plomo_ácido",'Ficha de exención para baterías'!M29="Plomo_calcio") -> #REF! | I35: =OR(LEN('Ficha de exención para baterías'!K29)>0) -> #REF!
A36: Alcalina | C36: Alcalina | E36: =OR('Ficha de exención para baterías'!M30="_18650_",'Ficha de exención para baterías'!M30="Óxido_cobalto_Litio",'Ficha de exención para baterías'!M30="Ion_litio",'Ficha de exención para baterías'!M30="Litio_ferrofosfato",'Ficha de exención para baterías'!M30="Óxido_de_cobalto_de_manganeso_y_litio",'Ficha de exención para baterías'!M30="Polímero_de_litio",'Ficha de exención para baterías'!M30="Titanato_de_litio",'Ficha de exención para baterías'!M30="Litio_Metal",'Ficha de exención para baterías'!M30="_CR2032_",'Ficha de exención para baterías'!M30="Litio_Cloruro_de_Tionilo",'Ficha de exención para baterías'!M30="Plomo_ácido",'Ficha de exención para baterías'!M30="Plomo_calcio") -> #REF! | G36: =OR('Ficha de exención para baterías'!M30="Plomo_ácido",'Ficha de exención para baterías'!M30="Plomo_calcio") -> #REF! | I36: =OR(LEN('Ficha de exención para baterías'!K30)>0) -> #REF!
A37: Carbono_zinc | C37: Carbono_zinc | E37: =OR('Ficha de exención para baterías'!M31="_18650_",'Ficha de exención para baterías'!M31="Óxido_cobalto_Litio",'Ficha de exención para baterías'!M31="Ion_litio",'Ficha de exención para baterías'!M31="Litio_ferrofosfato",'Ficha de exención para baterías'!M31="Óxido_de_cobalto_de_manganeso_y_litio",'Ficha de exención para baterías'!M31="Polímero_de_litio",'Ficha de exención para baterías'!M31="Titanato_de_litio",'Ficha de exención para baterías'!M31="Litio_Metal",'Ficha de exención para baterías'!M31="_CR2032_",'Ficha de exención para baterías'!M31="Litio_Cloruro_de_Tionilo",'Ficha de exención para baterías'!M31="Plomo_ácido",'Ficha de exención para baterías'!M31="Plomo_calcio") -> #REF! | G37: =OR('Ficha de exención para baterías'!M31="Plomo_ácido",'Ficha de exención para baterías'!M31="Plomo_calcio") -> #REF! | I37: =OR(LEN('Ficha de exención para baterías'!K31)>0) -> #REF!
A38: _CR2032_ | C38: _CR2032_ | E38: =OR('Ficha de exención para baterías'!M32="_18650_",'Ficha de exención para baterías'!M32="Óxido_cobalto_Litio",'Ficha de exención para baterías'!M32="Ion_litio",'Ficha de exención para baterías'!M32="Litio_ferrofosfato",'Ficha de exención para baterías'!M32="Óxido_de_cobalto_de_manganeso_y_litio",'Ficha de exención para baterías'!M32="Polímero_de_litio",'Ficha de exención para baterías'!M32="Titanato_de_litio",'Ficha de exención para baterías'!M32="Litio_Metal",'Ficha de exención para baterías'!M32="_CR2032_",'Ficha de exención para baterías'!M32="Litio_Cloruro_de_Tionilo",'Ficha de exención para baterías'!M32="Plomo_ácido",'Ficha de exención para baterías'!M32="Plomo_calcio") -> #REF! | G38: =OR('Ficha de exención para baterías'!M32="Plomo_ácido",'Ficha de exención para baterías'!M32="Plomo_calcio") -> #REF! | I38: =OR(LEN('Ficha de exención para baterías'!K32)>0) -> #REF!
A39: Plomo_ácido | C39: Plomo_ácido
A40: Plomo_calcio | C40: Plomo_calcio
A41: Níquel_cadmio | C41: Níquel_cadmio
A42: Níquel_metal_hidruro | C42: Níquel_metal_hidruro
A43: Óxido_de_plata | C43: Óxido_de_plata
A44: Zinc | C44: Zinc
A45: Zinc_aire | C45: Aire_de_zinc
A46: Zinc_carbono | C46: Zinc_carbono

Sheet Productos IQ TECH
A1: ASIN | B1: Nombre del Producto
A2: B0FBZFCL6Z | B2: IQ TECH Centro de Desayunos 3 en 1 1050 W | Tostador Horno + Cafetera + Plancha Antiadherente | Compacto, Temporizador, Fácil Limpieza
A3: B0FBT75NTR | B3: IQ Tech Cargador inalámbrico Plegable 3 en 1, Almohadilla magnética de Carga inalámbrica rápida, Compatible con iPhone 15/14/13/12 Series, Apple Watch, AirPods Pro (Adaptador no Incluido)
A4: B0FBQCMN4K | B4: IQ TECH Ventilador en la pared, ventilador de calentador pequeño con visualización digital, control remoto portátil para habitación, cocina, oficina, recámara Instalacion DOBLE FUNCION
A5: B0FGLL5RGB | B5: IQ Tech Bandeja de Brazo para sofá, con Clip en la Mesa Lateral, Mesa Plegable con Soporte para teléfono de 360°, bandejas de Comida para Comer/Bebidas/Aperitivos/Control Remoto
A6: B0FGKMQ5QW | B6: IQ Tech Espejo de Maquillaje con Luz LED, Espejo de Maquillaje Portátil con Brillo LED, Pantalla táctil, por USB, Espejo de Maquillaje Portátil Ultra Delgado Iluminado (Rosa)
A7: B0FGKTDTY9 | B7: IQ TECH Paquete de 3 luces hexagonales, paneles de pared RGB con control remoto y táctil, paneles de luz LED para sala de estar, recámara, decoración de sala de juegos
A8: B0FGKJ45HS | B8: IQ Tech Espejo de Maquillaje para Tocador Hollywood con Luz - Espejo con Luz para Makeup Hollywood Vintage, con 9 Focos LED Regulables de Blanca, Cálida y Neutra, Conexión USB (Blanco, 35.5x30.5 CM)
A9: B0GDRVJLTW | B9: IQ TECH- Masajeador térmico Bionic, masajeador Shiatsu portátil inalámbrico, cuello y espalda, masaje eléctrico de amasado 4D, diseño simulado de manos humanas para aliviar el dolor y relajación
A10: B0G88JK9SC | B10: IQ TECH Licuadora Portatil con 2 vasos Tazas, Mini Licuadora de 700ml 500W Licuadora Personal con Cuchillas Pro 304 Acero Inoxidable Extractoras de Nutrientes, para Smoothies, Batidos y Congeladas
A11: B0GXLFSD3K | B11: IQ TECH 1400W Donut Maker, Mini Donut Maker para 12 Mini Donuts, Antiadherente, Regulación automática de la temperatura, Libre de BPA
A12: B0GXLGPHRY | B12: IQ TECH Exprimidor de verduras y frutas de 800 W, con rendimiento de zumo optimizado, gran orificio de llenado de 65 mm, 2 niveles de velocidad, fácil de limpiar, negro/acero inoxidable
... A36: B0H2NHKK4G | B36: IQ-TECH 8 en 1 Esterilizador de Vapor de Biberones, Esterilización Biberones, Calentador de Biberones con Funciones de Descongelar, Esterilizar, Calentar Leche y Calentar Alimentos (Gris)

Sheet Copia de EKT
A1: ESTATUS | B1: SKU | C1: Codigo de Barras | D1: Sku | E1: ID Elektra.mx | F1: Nombre | G1: Categoria | H1: Marca | I1: Precio Regular | J1: Precio con Descuento | K1: Inventario | L1: MSI | M1: Comision MSI | N1: Envío | O1: Costo | P1: Retenciones | R1: FEE % | S1: FEE $ | T1: Envio | U1: Utilidad | V1: ROI | W1: LARGO | X1: ANCHO | Y1: ALTO | Z1: Peso | AA1: Peso Volumetrico | AB1: Peso cotizado
A2: Activa | B2: IQ1109 | C2: 622356564793 | D2: 80843691 | E2: 1301039665 | F2: Mini Licuadora Ninja SS101 | G2: Licuadoras | H2: NINJA | I2: 2599 | J2: 1899 | K2: 10 | L2: 12 | M2: =IFS(L2=0,0,L2=3,0.01,L2=6,0.03,L2=12,0.06) -> 0.06 | N2: Elektra envío gratis | O2: 896.34 | P2: =J2*0.08 -> 151.92 | Q2: =(J2-P2)*0.025 -> 43.677 | R2: =15%+M2 -> 0.21 | S2: =J2*R2 -> 398.79 | T2: =IF(AND(ISNUMBER(AB2)=TRUE(),AB2>0),SWITCH(TRUE(),AB2 <= 1, 129, AB2 <= 2, 139, AB2 <= 3, 149, AB2 <= 5, 169, AB2 <= 7, 179, AB2 <= 9, 209, AB2 <= 12, 249, AB2 <= 15, 299, AB2 <= 20, 390, AB2 <= 30, 420, AB2 <= 40, 525, AB2 <= 50, 859, AB2 <= 60, 1049, AB2 <= 70, 1099, AB2 <= 80, 1149, AB2 <= 90, 1169, AB2 <= 100, 1199, AB2 <= 125, 1449,AB2 <= 150, 1899, AB2 <= 175, 2349, AB2 <= 200, 2799, AB2 <= 225, 3299, AB2 <= 250, 379, AB2 <= 275, 4199, AB2 <= 300, 4699, AB2 <= 325, 5199, "Exceso de peso"),"Error") -> 169 | U2: =J2-O2-P2-Q2-S2-T2 -> 239.273 | V2: =U2/O2 -> 0.26694446 | W2: 30 | X2: 24 | Y2: 25 | Z2: 3.5 | AA2: =(W2*X2*Y2)/5000 -> 3.6 | AB2: =IF(Z2>AA2,Z2,AA2) -> 3.6
A3: Activa | B3: IQ1095 | C3: 622356322386 | D3: 80843624 | E3: 1301039689 | F3: Licuadora Ninja BN701 | G3: Licuadoras | H3: NINJA | I3: 2,599.00 | J3: 2299 | K3: 9 | L3: 3 | M3: =IFS(L3=0,0,L3=3,0.01,L3=6,0.03,L3=12,0.06) -> 0.01 | N3: Elektra envío gratis | O3: 1289 | P3: =J3*0.08 -> 183.92 | Q3: =(J3-P3)*0.025 -> 52.877 | R3: =15%+M3 -> 0.16 | S3: =J3*R3 -> 367.84 | T3: =IF(AND(ISNUMBER(AB3)=TRUE(),AB3>0),SWITCH(TRUE(),AB3 <= 1, 129, AB3 <= 2, 139, AB3 <= 3, 149, AB3 <= 5, 169, AB3 <= 7, 179, AB3 <= 9, 209, AB3 <= 12, 249, AB3 <= 15, 299, AB3 <= 20, 390, AB3 <= 30, 420, AB3 <= 40, 525, AB3 <= 50, 859, AB3 <= 60, 1049, AB3 <= 70, 1099, AB3 <= 80, 1149, AB3 <= 90, 1169, AB3 <= 100, 1199, AB3 <= 125, 1449,AB3 <= 150, 1899, AB3 <= 175, 2349, AB3 <= 200, 2799, AB3 <= 225, 3299, AB3 <= 250, 379, AB3 <= 275, 4199, AB3 <= 300, 4699, AB3 <= 325, 5199, "Exceso de peso"),"Error") -> 179 | U3: =J3-O3-P3-Q3-S3-T3 -> 226.363 | V3: =U3/O3 -> 0.17561133 | W3: 28 | X3: 24 | Y3: 40 | Z3: 4.8 | AA3: =(W3*X3*Y3)/5000 -> 5.376 | AB3: =IF(Z3>AA3,Z3,AA3) -> 5.376
A4: Apagada | B4: IQ965 | C4: 622356536820 | D4: 80843439 | E4: 1301039706 | F4: Licuadora Ninja BL610 | G4: Licuadoras | H4: NINJA | I4: 2,899.00 | J4: 1999 | K4: 9 | L4: 3 | M4: =IFS(L4=0,0,L4=3,0.01,L4=6,0.03,L4=12,0.06) -> 0.01 | N4: Elektra envío gratis | O4: 1142.64 | P4: =J4*0.08 -> 159.92 | Q4: =(J4-P4)*0.025 -> 45.977 | R4: =15%+M4 -> 0.16 | S4: =J4*R4 -> 319.84 | T4: =IF(AND(ISNUMBER(AB4)=TRUE(),AB4>0),SWITCH(TRUE(),AB4 <= 1, 129, AB4 <= 2, 139, AB4 <= 3, 149, AB4 <= 5, 169, AB4 <= 7, 179, AB4 <= 9, 209, AB4 <= 12, 249, AB4 <= 15, 299, AB4 <= 20, 390, AB4 <= 30, 420, AB4 <= 40, 525, AB4 <= 50, 859, AB4 <= 60, 1049, AB4 <= 70, 1099, AB4 <= 80, 1149, AB4 <= 90, 1169, AB4 <= 100, 1199, AB4 <= 125, 1449,AB4 <= 150, 1899, AB4 <= 175, 2349, AB4 <= 200, 2799, AB4 <= 225, 3299, AB4 <= 250, 379, AB4 <= 275, 4199, AB4 <= 300, 4699, AB4 <= 325, 5199, "Exceso de peso"),"Error") -> 169 | U4: =J4-O4-P4-Q4-S4-T4 -> 161.623 | V4: =U4/O4 -> 0.141447 | W4: 40 | X4: 21 | Y4: 27.5 | Z4: 4 | AA4: =(W4*X4*Y4)/5000 -> 4.62 | AB4: =IF(Z4>AA4,Z4,AA4) -> 4.62
A5: Apagada | B5: IQ964 | C5: 622356556897 | D5: 80843610 | E5: 1301039723 | F5: Licuadora Ninja BL710WM | G5: Licuadoras | H5: NINJA | I5: 2,399.00 | J5: 1619 | K5: 10 | L5: 3 | M5: =IFS(L5=0,0,L5=3,0.01,L5=6,0.03,L5=12,0.06) -> 0.01 | N5: Elektra envío gratis | O5: 1121.12 | P5: =J5*0.08 -> 129.52 | Q5: =(J5-P5)*0.025 -> 37.237 | R5: =15%+M5 -> 0.16 | S5: =J5*R5 -> 259.04 | T5: =IF(AND(ISNUMBER(AB5)=TRUE(),AB5>0),SWITCH(TRUE(),AB5 <= 1, 129, AB5 <= 2, 139, AB5 <= 3, 149, AB5 <= 5, 169, AB5 <= 7, 179, AB5 <= 9, 209, AB5 <= 12, 249, AB5 <= 15, 299, AB5 <= 20, 390, AB5 <= 30, 420, AB5 <= 40, 525, AB5 <= 50, 859, AB5 <= 60, 1049, AB5 <= 70, 1099, AB5 <= 80, 1149, AB5 <= 90, 1169, AB5 <= 100, 1199, AB5 <= 125, 1449,AB5 <= 150, 1899, AB5 <= 175, 2349, AB5 <= 200, 2799, AB5 <= 225, 3299, AB5 <= 250, 379, AB5 <= 275, 4199, AB5 <= 300, 4699, AB5 <= 325, 5199, "Exceso de peso"),"Error") -> 169 | U5: =J5-O5-P5-Q5-S5-T5 -> -96.917 | V5: =U5/O5 -> -0.086446589 | W5: 27.3 | X5: 21.5 | Y5: 41 | Z5: 4.5 | AA5: =(W5*X5*Y5)/5000 -> 4.81299 | AB5: =IF(Z5>AA5,Z5,AA5) -> 4.81299
A6: Apagada | B6: IQ1286 | C6: 622356561891 | D6: 80843657 | E6: 1301039776 | F6: Licuadora Ninja BN751 | G6: Licuadoras | H6: NINJA | I6: 3,799.00 | J6: 2099 | K6: 9 | L6: 3 | M6: =IFS(L6=0,0,L6=3,0.01,L6=6,0.03,L6=12,0.06) -> 0.01 | N6: Elektra envío gratis | O6: 1349.49 | P6: =J6*0.08 -> 167.92 | Q6: =(J6-P6)*0.025 -> 48.277 | R6: =15%+M6 -> 0.16 | S6: =J6*R6 -> 335.84 | T6: =IF(AND(ISNUMBER(AB6)=TRUE(),AB6>0),SWITCH(TRUE(),AB6 <= 1, 129, AB6 <= 2, 139, AB6 <= 3, 149, AB6 <= 5, 169, AB6 <= 7, 179, AB6 <= 9, 209, AB6 <= 12, 249, AB6 <= 15, 299, AB6 <= 20, 390, AB6 <= 30, 420, AB6 <= 40, 525, AB6 <= 50, 859, AB6 <= 60, 1049, AB6 <= 70, 1099, AB6 <= 80, 1149, AB6 <= 90, 1169, AB6 <= 100, 1199, AB6 <= 125, 1449,AB6 <= 150, 1899, AB6 <= 175, 2349, AB6 <= 200, 2799, AB6 <= 225, 3299, AB6 <= 250, 379, AB6 <= 275, 4199, AB6 <= 300, 4699, AB6 <= 325, 5199, "Exceso de peso"),"Error") -> 209 | U6: =J6-O6-P6-Q6-S6-T6 -> -11.527 | V6: =U6/O6 -> -0.0085417454 | W6: 33.02 | X6: 27.69 | Y6: 40.9 | Z6: 5.61 | AA6: =(W6*X6*Y6)/5000 -> 7.4791687 | AB6: =IF(Z6>AA6,Z6,AA6) -> 7.4791687
A7: Apagada | B7: IQ972 | C7: 622356603911 | D7: 80843697 | E7: 1301039823 | F7: Ninja Juicer JC151 | G7: Extractores y Exprimidores | H7: NINJA | I7: 4,999.00 | J7: 2799 | K7: 10 | L7: 3 | M7: =IFS(L7=0,0,L7=3,0.01,L7=6,0.03,L7=12,0.06) -> 0.01 | N7: Elektra envío gratis | O7: 1667.66 | P7: =J7*0.08 -> 223.92 | Q7: =(J7-P7)*0.025 -> 64.377 | R7: =15%+M7 -> 0.16 | S7: =J7*R7 -> 447.84 | T7: =IF(AND(ISNUMBER(AB7)=TRUE(),AB7>0),SWITCH(TRUE(),AB7 <= 1, 129, AB7 <= 2, 139, AB7 <= 3, 149, AB7 <= 5, 169, AB7 <= 7, 179, AB7 <= 9, 209, AB7 <= 12, 249, AB7 <= 15, 299, AB7 <= 20, 390, AB7 <= 30, 420, AB7 <= 40, 525, AB7 <= 50, 859, AB7 <= 60, 1049, AB7 <= 70, 1099, AB7 <= 80, 1149, AB7 <= 90, 1169, AB7 <= 100, 1199, AB7 <= 125, 1449,AB7 <= 150, 1899, AB7 <= 175, 2349, AB7 <= 200, 2799, AB7 <= 225, 3299, AB7 <= 250, 379, AB7 <= 275, 4199, AB7 <= 300, 4699, AB7 <= 325, 5199, "Exceso de peso"),"Error") -> 209 | U7: =J7-O7-P7-Q7-S7-T7 -> 186.203 | V7: =U7/O7 -> 0.11165525 | W7: 36.4 | X7: 29.1 | Y7: 39.2 | Z7: 5 | AA7: =(W7*X7*Y7)/5000 -> 8.3044416 | AB7: =IF(Z7>AA7,Z7,AA7) -> 8.3044416
A8: Apagada | B8: IQ1127 | C8: 7506478067482 | D8: 80843705 | E8: 1301039831 | F8: Trapeador Shark S1000LAA | G8: Limpieza | H8: SHARK | I8: 2,099.00 | J8: 1799 | K8: 10 | L8: 3 | M8: =IFS(L8=0,0,L8=3,0.01,L8=6,0.03,L8=12,0.06) -> 0.01 | N8: Elektra envío gratis | O8: 1012.49 | P8: =J8*0.08 -> 143.92 | Q8: =(J8-P8)*0.025 -> 41.377 | R8: =15%+M8 -> 0.16 | S8: =J8*R8 -> 287.84 | T8: =IF(AND(ISNUMBER(AB8)=TRUE(),AB8>0),SWITCH(TRUE(),AB8 <= 1, 129, AB8 <= 2, 139, AB8 <= 3, 149, AB8 <= 5, 169, AB8 <= 7, 179, AB8 <= 9, 209, AB8 <= 12, 249, AB8 <= 15, 299, AB8 <= 20, 390, AB8 <= 30, 420, AB8 <= 40, 525, AB8 <= 50, 859, AB8 <= 60, 1049, AB8 <= 70, 1099, AB8 <= 80, 1149, AB8 <= 90, 1169, AB8 <= 100, 1199, AB8 <= 125, 1449,AB8 <= 150, 1899, AB8 <= 175, 2349, AB8 <= 200, 2799, AB8 <= 225, 3299, AB8 <= 250, 379, AB8 <= 275, 4199, AB8 <= 300, 4699, AB8 <= 325, 5199, "Exceso de peso"),"Error") -> 169 | U8: =J8-O8-P8-Q8-S8-T8 -> 144.373 | V8: =U8/O8 -> 0.14259203 | W8: 15 | X8: 17.5 | Y8: 61 | Z8: 2 | AA8: =(W8*X8*Y8)/5000 -> 3.2025 | AB8: =IF(Z8>AA8,Z8,AA8) -> 3.2025
A9: Apagada | B9: IQ1111 | C9: 622356532099 | D9: 80832272 | E9: 1301029310 | F9: Licuadora Ninja Bl660 | G9: Licuadoras | H9: NINJA | I9: 3,599.00 | J9: 3199 | K9: 10 | L9: 12 | M9: =IFS(L9=0,0,L9=3,0.01,L9=6,0.03,L9=12,0.06) -> 0.06 | N9: Elektra envío gratis | O9: 1785.06 | P9: =J9*0.08 -> 255.92 | Q9: =(J9-P9)*0.025 -> 73.577 | R9: =15%+M9 -> 0.21 | S9: =J9*R9 -> 671.79 | T9: =IF(AND(ISNUMBER(AB9)=TRUE(),AB9>0),SWITCH(TRUE(),AB9 <= 1, 129, AB9 <= 2, 139, AB9 <= 3, 149, AB9 <= 5, 169, AB9 <= 7, 179, AB9 <= 9, 209, AB9 <= 12, 249, AB9 <= 15, 299, AB9 <= 20, 390, AB9 <= 30, 420, AB9 <= 40, 525, AB9 <= 50, 859, AB9 <= 60, 1049, AB9 <= 70, 1099, AB9 <= 80, 1149, AB9 <= 90, 1169, AB9 <= 100, 1199, AB9 <= 125, 1449,AB9 <= 150, 1899, AB9 <= 175, 2349, AB9 <= 200, 2799, AB9 <= 225, 3299, AB9 <= 250, 379, AB9 <= 275, 4199, AB9 <= 300, 4699, AB9 <= 325, 5199, "Exceso de peso"),"Error") -> 179 | U9: =J9-O9-P9-Q9-S9-T9 -> 233.653 | V9: =U9/O9 -> 0.13089364 | W9: 34.5 | X9: 21 | Y9: 41 | Z9: 5 | AA9: =(W9*X9*Y9)/5000 -> 5.9409 | AB9: =IF(Z9>AA9,Z9,AA9) -> 5.9409
A10: Activa | B10: IQ1126 | C10: 622356320658 | D10: 80887805 | E10: 1301063828 | F10: Ninja Slushi Fs301laa | G10: Otros | H10: Ninja | I10: 11999 | J10: 7499 | L10: 3 | M10: =IFS(L10=0,0,L10=3,0.01,L10=6,0.03,L10=12,0.06) -> 0.01 | N10: Elektra envío gratis | O10: 3099 | P10: =J10*0.08 -> 599.92 | Q10: =(J10-P10)*0.025 -> 172.477 | R10: =15%+M10 -> 0.16 | S10: =J10*R10 -> 1199.84 | T10: =IF(AND(ISNUMBER(AB10)=TRUE(),AB10>0),SWITCH(TRUE(),AB10 <= 1, 129, AB10 <= 2, 139, AB10 <= 3, 149, AB10 <= 5, 169, AB10 <= 7, 179, AB10 <= 9, 209, AB10 <= 12, 249, AB10 <= 15, 299, AB10 <= 20, 390, AB10 <= 30, 420, AB10 <= 40, 525, AB10 <= 50, 859, AB10 <= 60, 1049, AB10 <= 70, 1099, AB10 <= 80, 1149, AB10 <= 90, 1169, AB10 <= 100, 1199, AB10 <= 125, 1449,AB10 <= 150, 1899, AB10 <= 175, 2349, AB10 <= 200, 2799, AB10 <= 225, 3299, AB10 <= 250, 379, AB10 <= 275, 4199, AB10 <= 300, 4699, AB10 <= 325, 5199, "Exceso de peso"),"Error") -> 299 | U10: =J10-O10-P10-Q10-S10-T10 -> 2128.763 | V10: =U10/O10 -> 0.68691933 | W10: 51 | X10: 26 | Y10: 52 | Z10: 12.7 | AA10: =(W10*X10*Y10)/5000 -> 13.7904 | AB10: =IF(Z10>AA10,Z10,AA10) -> 13.7904
A11: Apagada | B11: IQ1386 | C11: 622356641012 | D11: 80887611 | E11: 1301063640 | F11: Ninja Creami Nc701 | G11: Otros | H11: Ninja | I11: 9999 | J11: 9199 | K11: 10 | L11: 6 | M11: =IFS(L11=0,0,L11=3,0.01,L11=6,0.03,L11=12,0.06) -> 0.03 | N11: Elektra envío gratis | O11: 5730.09 | P11: =J11*0.08 -> 735.92 | Q11: =(J11-P11)*0.025 -> 211.577 | R11: =15%+M11 -> 0.18 | S11: =J11*R11 -> 1655.82 | T11: =IF(AND(ISNUMBER(AB11)=TRUE(),AB11>0),SWITCH(TRUE(),AB11 <= 1, 129, AB11 <= 2, 139, AB11 <= 3, 149, AB11 <= 5, 169, AB11 <= 7, 179, AB11 <= 9, 209, AB11 <= 12, 249, AB11 <= 15, 299, AB11 <= 20, 390, AB11 <= 30, 420, AB11 <= 40, 525, AB11 <= 50, 859, AB11 <= 60, 1049, AB11 <= 70, 1099, AB11 <= 80, 1149, AB11 <= 90, 1169, AB11 <= 100, 1199, AB11 <= 125, 1449,AB11 <= 150, 1899, AB11 <= 175, 2349, AB11 <= 200, 2799, AB11 <= 225, 3299, AB11 <= 250, 379, AB11 <= 275, 4199, AB11 <= 300, 4699, AB11 <= 325, 5199, "Exceso de peso"),"Error") -> 299 | U11: =J11-O11-P11-Q11-S11-T11 -> 566.593 | V11: =U11/O11 -> 0.098880297 | W11: 47.19 | X11: 30.61 | Y11: 51.79 | Z11: 11 | AA11: =(W11*X11*Y11)/5000 -> 14.961985 | AB11: =IF(Z11>AA11,Z11,AA11) -> 14.961985
A12: Apagada | B12: IQ1385 | C12: 622356617338 | D12: 80887621 | E12: 1301063615 | F12: Cafetera Ninja Pb051cco | G12: Cafeteras Y Teteras | H12: Ninja | I12: 3299 | J12: 2699 | K12: 10 | L12: 3 | M12: =IFS(L12=0,0,L12=3,0.01,L12=6,0.03,L12=12,0.06) -> 0.01 | N12: Elektra envío gratis | O12: 1580.23 | P12: =J12*0.08 -> 215.92 | Q12: =(J12-P12)*0.025 -> 62.077 | R12: =15%+M12 -> 0.16 | S12: =J12*R12 -> 431.84 | T12: =IF(AND(ISNUMBER(AB12)=TRUE(),AB12>0),SWITCH(TRUE(),AB12 <= 1, 129, AB12 <= 2, 139, AB12 <= 3, 149, AB12 <= 5, 169, AB12 <= 7, 179, AB12 <= 9, 209, AB12 <= 12, 249, AB12 <= 15, 299, AB12 <= 20, 390, AB12 <= 30, 420, AB12 <= 40, 525, AB12 <= 50, 859, AB12 <= 60, 1049, AB12 <= 70, 1099, AB12 <= 80, 1149, AB12 <= 90, 1169, AB12 <= 100, 1199, AB12 <= 125, 1449,AB12 <= 150, 1899, AB12 <= 175, 2349, AB12 <= 200, 2799, AB12 <= 225, 3299, AB12 <= 250, 379, AB12 <= 275, 4199, AB12 <= 300, 4699, AB12 <= 325, 5199, "Exceso de peso"),"Error") -> 179 | U12: =J12-O12-P12-Q12-S12-T12 -> 229.933 | V12: =U12/O12 -> 0.14550603 | W12: 19 | X12: 38 | Y12: 40 | Z12: 3.9 | AA12: =(W12*X12*Y12)/5000 -> 5.776 | AB12: =IF(Z12>AA12,Z12,AA12) -> 5.776
A13: Apagada | B13: IQ1395 | C13: 622356659833 | D13: 80915427 | E13: 1301107998 | F13: Licuadora Ninja Blast Max ‎Bc251 | G13: Licuadoras | H13: NINJA | I13: 2299 | J13: 2299 | K13: 50 | L13: 3 | M13: =IFS(L13=0,0,L13=3,0.01,L13=6,0.03,L13=12,0.06) -> 0.01 | N13: Elektra envío gratis | O13: 1411.6683 | P13: =J13*0.08 -> 183.92 | Q13: =(J13-P13)*0.025 -> 52.877 | R13: =15%+M13 -> 0.16 | S13: =J13*R13 -> 367.84 | T13: =IF(AND(ISNUMBER(AB13)=TRUE(),AB13>0),SWITCH(TRUE(),AB13 <= 1, 129, AB13 <= 2, 139, AB13 <= 3, 149, AB13 <= 5, 169, AB13 <= 7, 179, AB13 <= 9, 209, AB13 <= 12, 249, AB13 <= 15, 299, AB13 <= 20, 390, AB13 <= 30, 420, AB13 <= 40, 525, AB13 <= 50, 859, AB13 <= 60, 1049, AB13 <= 70, 1099, AB13 <= 80, 1149, AB13 <= 90, 1169, AB13 <= 100, 1199, AB13 <= 125, 1449,AB13 <= 150, 1899, AB13 <= 175, 2349, AB13 <= 200, 2799, AB13 <= 225, 3299, AB13 <= 250, 379, AB13 <= 275, 4199, AB13 <= 300, 4699, AB13 <= 325, 5199, "Exceso de peso"),"Error") -> 139 | U13: =J13-O13-P13-Q13-S13-T13 -> 143.6947 | V13: =U13/O13 -> 0.1017907 | W13: 12 | X13: 15 | Y13: 32 | Z13: 1.35 | AA13: =(W13*X13*Y13)/5000 -> 1.152 | AB13: =IF(Z13>AA13,Z13,AA13) -> 1.35
A14: Apagada | B14: IQ1122 | C14: 622356309486 | D14: 80887303 | E14: 1301106140 | F14: Aspiradora Inalámbrica Bu3120laa | G14: Aspiradoras | H14: Shark | I14: 10999 | J14: 6499 | K14: 3 | L14: 12 | M14: =IFS(L14=0,0,L14=3,0.01,L14=6,0.03,L14=12,0.06) -> 0.06 | N14: Elektra envío gratis | O14: 3082.77 | P14: =J14*0.08 -> 519.92 | Q14: =(J14-P14)*0.025 -> 149.477 | R14: =15%+M14 -> 0.21 | S14: =J14*R14 -> 1364.79 | T14: =IF(AND(ISNUMBER(AB14)=TRUE(),AB14>0),SWITCH(TRUE(),AB14 <= 1, 129, AB14 <= 2, 139, AB14 <= 3, 149, AB14 <= 5, 169, AB14 <= 7, 179, AB14 <= 9, 209, AB14 <= 12, 249, AB14 <= 15, 299, AB14 <= 20, 390, AB14 <= 30, 420, AB14 <= 40, 525, AB14 <= 50, 859, AB14 <= 60, 1049, AB14 <= 70, 1099, AB14 <= 80, 1149, AB14 <= 90, 1169, AB14 <= 100, 1199, AB14 <= 125, 1449,AB14 <= 150, 1899, AB14 <= 175, 2349, AB14 <= 200, 2799, AB14 <= 225, 3299, AB14 <= 250, 379, AB14 <= 275, 4199, AB14 <= 300, 4699, AB14 <= 325, 5199, "Exceso de peso"),"Error") -> 249 | U14: =J14-O14-P14-Q14-S14-T14 -> 1133.043 | V14: =U14/O14 -> 0.36754056 | W14: 36 | X14: 26.5 | Y14: 52 | Z14: 8 | AA14: =(W14*X14*Y14)/5000 -> 9.9216 | AB14: =IF(Z14>AA14,Z14,AA14) -> 9.9216
A15: Apagada | B15: IQ1128 | C15: 622356311656 | D15: 80887302 | E15: 1301106312 | F15: Aspiradora Inalámbrica Shark Ix141laa | G15: Aspiradoras | H15: Shark | I15: 6999 | J15: 5299 | K15: 10 | L15: 12 | M15: =IFS(L15=0,0,L15=3,0.01,L15=6,0.03,L15=12,0.06) -> 0.06 | N15: Elektra envío gratis | O15: 2967.2 | P15: =J15*0.08 -> 423.92 | Q15: =(J15-P15)*0.025 -> 121.877 | R15: =15%+M15 -> 0.21 | S15: =J15*R15 -> 1112.79 | T15: =IF(AND(ISNUMBER(AB15)=TRUE(),AB15>0),SWITCH(TRUE(),AB15 <= 1, 129, AB15 <= 2, 139, AB15 <= 3, 149, AB15 <= 5, 169, AB15 <= 7, 179, AB15 <= 9, 209, AB15 <= 12, 249, AB15 <= 15, 299, AB15 <= 20, 390, AB15 <= 30, 420, AB15 <= 40, 525, AB15 <= 50, 859, AB15 <= 60, 1049, AB15 <= 70, 1099, AB15 <= 80, 1149, AB15 <= 90, 1169, AB15 <= 100, 1199, AB15 <= 125, 1449,AB15 <= 150, 1899, AB15 <= 175, 2349, AB15 <= 200, 2799, AB15 <= 225, 3299, AB15 <= 250, 379, AB15 <= 275, 4199, AB15 <= 300, 4699, AB15 <= 325, 5199, "Exceso de peso"),"Error") -> 209 | U15: =J15-O15-P15-Q15-S15-T15 -> 464.213 | V15: =U15/O15 -> 0.15644817 | W15: 29 | X15: 18.5 | Y15: 72.5 | Z15: 5 | AA15: =(W15*X15*Y15)/5000 -> 7.77925 | AB15: =IF(Z15>AA15,Z15,AA15) -> 7.77925
A16: Activa | B16: IQ1118 | C16: 622356305761 | D16: 80887299 | E16: 1301106351 | F16: Aspiradora Inalámbrica Shark Iz492hlaa | G16: Aspiradoras | H16: Shark | I16: 9999 | J16: 5799 | L16: 3 | M16: =IFS(L16=0,0,L16=3,0.01,L16=6,0.03,L16=12,0.06) -> 0.01 | N16: Elektra envío gratis | O16: 3576.01 | P16: =J16*0.08 -> 463.92 | Q16: =(J16-P16)*0.025 -> 133.377 | R16: =15%+M16 -> 0.16 | S16: =J16*R16 -> 927.84 | T16: =IF(AND(ISNUMBER(AB16)=TRUE(),AB16>0),SWITCH(TRUE(),AB16 <= 1, 129, AB16 <= 2, 139, AB16 <= 3, 149, AB16 <= 5, 169, AB16 <= 7, 179, AB16 <= 9, 209, AB16 <= 12, 249, AB16 <= 15, 299, AB16 <= 20, 390, AB16 <= 30, 420, AB16 <= 40, 525, AB16 <= 50, 859, AB16 <= 60, 1049, AB16 <= 70, 1099, AB16 <= 80, 1149, AB16 <= 90, 1169, AB16 <= 100, 1199, AB16 <= 125, 1449,AB16 <= 150, 1899, AB16 <= 175, 2349, AB16 <= 200, 2799, AB16 <= 225, 3299, AB16 <= 250, 379, AB16 <= 275, 4199, AB16 <= 300, 4699, AB16 <= 325, 5199, "Exceso de peso"),"Error") -> 209 | U16: =J16-O16-P16-Q16-S16-T16 -> 488.853 | V16: =U16/O16 -> 0.13670348 | W16: 28.5 | X16: 18.5 | Y16: 74 | Z16: 6 | AA16: =(W16*X16*Y16)/5000 -> 7.8033 | AB16: =IF(Z16>AA16,Z16,AA16) -> 7.8033
A17: Apagada | B17: IQ977 | C17: 622356309912 | D17: 80887312 | E17: 1301106198 | F17: Multiestilizador Shark Blanco Hd435laa | G17: Secadoras | H17: Shark | I17: 6999 | J17: 5999 | K17: 20 | L17: 3 | M17: =IFS(L17=0,0,L17=3,0.01,L17=6,0.03,L17=12,0.06) -> 0.01 | N17: Elektra envío gratis | O17: 3868.99 | P17: =J17*0.08 -> 479.92 | Q17: =(J17-P17)*0.025 -> 137.977 | R17: =15%+M17 -> 0.16 | S17: =J17*R17 -> 959.84 | T17: =IF(AND(ISNUMBER(AB17)=TRUE(),AB17>0),SWITCH(TRUE(),AB17 <= 1, 129, AB17 <= 2, 139, AB17 <= 3, 149, AB17 <= 5, 169, AB17 <= 7, 179, AB17 <= 9, 209, AB17 <= 12, 249, AB17 <= 15, 299, AB17 <= 20, 390, AB17 <= 30, 420, AB17 <= 40, 525, AB17 <= 50, 859, AB17 <= 60, 1049, AB17 <= 70, 1099, AB17 <= 80, 1149, AB17 <= 90, 1169, AB17 <= 100, 1199, AB17 <= 125, 1449,AB17 <= 150, 1899, AB17 <= 175, 2349, AB17 <= 200, 2799, AB17 <= 225, 3299, AB17 <= 250, 379, AB17 <= 275, 4199, AB17 <= 300, 4699, AB17 <= 325, 5199, "Exceso de peso"),"Error") -> 139 | U17: =J17-O17-P17-Q17-S17-T17 -> 413.273 | V17: =U17/O17 -> 0.10681677 | W17: 37.4 | X17: 21.9 | Y17: 11 | Z17: 1.85 | AA17: =(W17*X17*Y17)/5000 -> 1.801932 | AB17: =IF(Z17>AA17,Z17,AA17) -> 1.85
A18: Apagada | B18: IQ978 | C18: 622356634946 | D18: 80887305 | E18: 1301106314 | F18: Multiestilizador Shark Hd442bp Rosa | G18: Secadoras | H18: Shark | I18: 6999 | J18: 6699 | K18: 20 | L18: 12 | M18: =IFS(L18=0,0,L18=3,0.01,L18=6,0.03,L18=12,0.06) -> 0.06 | N18: Elektra envío gratis | O18: 4421.7 | P18: =J18*0.08 -> 535.92 | Q18: =(J18-P18)*0.025 -> 154.077 | R18: =15%+M18 -> 0.21 | S18: =J18*R18 -> 1406.79 | T18: =IF(AND(ISNUMBER(AB18)=TRUE(),AB18>0),SWITCH(TRUE(),AB18 <= 1, 129, AB18 <= 2, 139, AB18 <= 3, 149, AB18 <= 5, 169, AB18 <= 7, 179, AB18 <= 9, 209, AB18 <= 12, 249, AB18 <= 15, 299, AB18 <= 20, 390, AB18 <= 30, 420, AB18 <= 40, 525, AB18 <= 50, 859, AB18 <= 60, 1049, AB18 <= 70, 1099, AB18 <= 80, 1149, AB18 <= 90, 1169, AB18 <= 100, 1199, AB18 <= 125, 1449,AB18 <= 150, 1899, AB18 <= 175, 2349, AB18 <= 200, 2799, AB18 <= 225, 3299, AB18 <= 250, 379, AB18 <= 275, 4199, AB18 <= 300, 4699, AB18 <= 325, 5199, "Exceso de peso"),"Error") -> 169 | U18: =J18-O18-P18-Q18-S18-T18 -> 11.513 | V18: =U18/O18 -> 0.0026037497 | W18: 39.5 | X18: 19.5 | Y18: 19.01 | Z18: 3.18 | AA18: =(W18*X18*Y18)/5000 -> 2.9284905 | AB18: =IF(Z18>AA18,Z18,AA18) -> 3.18
A19: Apagada | F19: Secador De Pelo Dyson Edición Especial Supersonic Nural | G19: Secadoras | H19: Dyson | I19: 11999 | J19: 10999 | K19: 15 | L19: 3 | M19: =IFS(L19=0,0,L19=3,0.01,L19=6,0.03,L19=12,0.06) -> 0.01 | N19: Elektra envío gratis | O19: 7990 | P19: =J19*0.08 -> 879.92 | Q19: =(J19-P19)*0.025 -> 252.977 | R19: =15%+M19 -> 0.16 | S19: =J19*R19 -> 1759.84 | T19: =IF(AND(ISNUMBER(AB19)=TRUE(),AB19>0),SWITCH(TRUE(),AB19 <= 1, 129, AB19 <= 2, 139, AB19 <= 3, 149, AB19 <= 5, 169, AB19 <= 7, 179, AB19 <= 9, 209, AB19 <= 12, 249, AB19 <= 15, 299, AB19 <= 20, 390, AB19 <= 30, 420, AB19 <= 40, 525, AB19 <= 50, 859, AB19 <= 60, 1049, AB19 <= 70, 1099, AB19 <= 80, 1149, AB19 <= 90, 1169, AB19 <= 100, 1199, AB19 <= 125, 1449,AB19 <= 150, 1899, AB19 <= 175, 2349, AB19 <= 200, 2799, AB19 <= 225, 3299, AB19 <= 250, 379, AB19 <= 275, 4199, AB19 <= 300, 4699, AB19 <= 325, 5199, "Exceso de peso"),"Error") -> 299 | U19: =J19-O19-P19-Q19-S19-T19 -> -182.737 | V19: =U19/O19 -> -0.022870713 | W19: 60 | X19: 26 | Y19: 45 | Z19: 6.05 | AA19: =(W19*X19*Y19)/5000 -> 14.04 | AB19: =IF(Z19>AA19,Z19,AA19) -> 14.04
A20: Apagada | B20: IQ1129 | C20: 622356561440 | D20: 80886179 | E20: 1301113753 | F20: Aspiradora De Mano Shark Ch951 | G20: Aspiradoras | H20: Shark | I20: 3499 | J20: 2899 | K20: 7 | L20: 3 | M20: =IFS(L20=0,0,L20=3,0.01,L20=6,0.03,L20=12,0.06) -> 0.01 | N20: Elektra envío gratis | O20: 1979.4 | P20: =J20*0.08 -> 231.92 | Q20: =(J20-P20)*0.025 -> 66.677 | R20: =15%+M20 -> 0.16 | S20: =J20*R20 -> 463.84 | T20: =IF(AND(ISNUMBER(AB20)=TRUE(),AB20>0),SWITCH(TRUE(),AB20 <= 1, 129, AB20 <= 2, 139, AB20 <= 3, 149, AB20 <= 5, 169, AB20 <= 7, 179, AB20 <= 9, 209, AB20 <= 12, 249, AB20 <= 15, 299, AB20 <= 20, 390, AB20 <= 30, 420, AB20 <= 40, 525, AB20 <= 50, 859, AB20 <= 60, 1049, AB20 <= 70, 1099, AB20 <= 80, 1149, AB20 <= 90, 1169, AB20 <= 100, 1199, AB20 <= 125, 1449,AB20 <= 150, 1899, AB20 <= 175, 2349, AB20 <= 200, 2799, AB20 <= 225, 3299, AB20 <= 250, 379, AB20 <= 275, 4199, AB20 <= 300, 4699, AB20 <= 325, 5199, "Exceso de peso"),"Error") -> 139 | U20: =J20-O20-P20-Q20-S20-T20 -> 18.163 | V20: =U20/O20 -> 0.0091760129 | W20: 14.5 | X20: 12.1 | Y20: 54.1 | Z20: 1.4 | AA20: =(W20*X20*Y20)/5000 -> 1.898369 | AB20: =IF(Z20>AA20,Z20,AA20) -> 1.898369
A21: Apagada | B21: IQ1383 | F21: Licuadora Xinest | G21: Licuadoras | H21: GENERICO | I21: 799 | J21: 629 | K21: 10 | L21: 3 | M21: =IFS(L21=0,0,L21=3,0.01,L21=6,0.03,L21=12,0.06) -> 0.01 | N21: Elektra envío gratis | O21: 270 | P21: =J21*0.08 -> 50.32 | Q21: =(J21-P21)*0.025 -> 14.467 | R21: =15%+M21 -> 0.16 | S21: =J21*R21 -> 100.64 | T21: =IF(AND(ISNUMBER(AB21)=TRUE(),AB21>0),SWITCH(TRUE(),AB21 <= 1, 129, AB21 <= 2, 139, AB21 <= 3, 149, AB21 <= 5, 169, AB21 <= 7, 179, AB21 <= 9, 209, AB21 <= 12, 249, AB21 <= 15, 299, AB21 <= 20, 390, AB21 <= 30, 420, AB21 <= 40, 525, AB21 <= 50, 859, AB21 <= 60, 1049, AB21 <= 70, 1099, AB21 <= 80, 1149, AB21 <= 90, 1169, AB21 <= 100, 1199, AB21 <= 125, 1449,AB21 <= 150, 1899, AB21 <= 175, 2349, AB21 <= 200, 2799, AB21 <= 225, 3299, AB21 <= 250, 379, AB21 <= 275, 4199, AB21 <= 300, 4699, AB21 <= 325, 5199, "Exceso de peso"),"Error") -> 149 | U21: =J21-O21-P21-Q21-S21-T21 -> 44.573 | V21: =U21/O21 -> 0.16508519 | W21: 25 | X21: 20 | Y21: 28 | Z21: 2.6 | AA21: =(W21*X21*Y21)/5000 -> 2.8 | AB21: =IF(Z21>AA21,Z21,AA21) -> 2.8
A22: Activa | B22: IQ1297 | C22: 622356564380 | D22: 80831781 | E22: 1301028501 | F22: Freidora de Aire Ninja DZ201 | G22: Freidoras de Aire | H22: NINJA | I22: 5,199.00 | J22: 3399 | L22: 3 | M22: =IFS(L22=0,0,L22=3,0.01,L22=6,0.03,L22=12,0.06) -> 0.01 | N22: Elektra envío gratis | O22: 1985 | P22: =J22*0.08 -> 271.92 | Q22: =(J22-P22)*0.025 -> 78.177 | R22: =15%+M22 -> 0.16 | S22: =J22*R22 -> 543.84 | T22: =IF(AND(ISNUMBER(AB22)=TRUE(),AB22>0),SWITCH(TRUE(),AB22 <= 1, 129, AB22 <= 2, 139, AB22 <= 3, 149, AB22 <= 5, 169, AB22 <= 7, 179, AB22 <= 9, 209, AB22 <= 12, 249, AB22 <= 15, 299, AB22 <= 20, 390, AB22 <= 30, 420, AB22 <= 40, 525, AB22 <= 50, 859, AB22 <= 60, 1049, AB22 <= 70, 1099, AB22 <= 80, 1149, AB22 <= 90, 1169, AB22 <= 100, 1199, AB22 <= 125, 1449,AB22 <= 150, 1899, AB22 <= 175, 2349, AB22 <= 200, 2799, AB22 <= 225, 3299, AB22 <= 250, 379, AB22 <= 275, 4199, AB22 <= 300, 4699, AB22 <= 325, 5199, "Exceso de peso"),"Error") -> 249 | U22: =J22-O22-P22-Q22-S22-T22 -> 271.063 | V22: =U22/O22 -> 0.13655567 | W22: 43.61 | X22: 38.61 | Y22: 35.6 | Z22: 9.72 | AA22: =(W22*X22*Y22)/5000 -> 11.988529 | AB22: =IF(Z22>AA22,Z22,AA22) -> 11.988529
A23: Apagada | B23: IQ1286 | C23: 622356561891 | D23: 80843657 | E23: 1301039776 | F23: Licuadora Ninja BN751 | G23: Licuadoras | H23: NINJA | I23: 3,799.00 | J23: 1999 | K23: 500 | L23: 3 | M23: =IFS(L23=0,0,L23=3,0.01,L23=6,0.03,L23=12,0.06) -> 0.01 | N23: Elektra envío gratis | O23: 1319.49 | P23: =J23*0.08 -> 159.92 | Q23: =(J23-P23)*0.025 -> 45.977 | R23: =15%+M23 -> 0.16 | S23: =J23*R23 -> 319.84 | T23: =IF(AND(ISNUMBER(AB23)=TRUE(),AB23>0),SWITCH(TRUE(),AB23 <= 1, 129, AB23 <= 2, 139, AB23 <= 3, 149, AB23 <= 5, 169, AB23 <= 7, 179, AB23 <= 9, 209, AB23 <= 12, 249, AB23 <= 15, 299, AB23 <= 20, 390, AB23 <= 30, 420, AB23 <= 40, 525, AB23 <= 50, 859, AB23 <= 60, 1049, AB23 <= 70, 1099, AB23 <= 80, 1149, AB23 <= 90, 1169, AB23 <= 100, 1199, AB23 <= 125, 1449,AB23 <= 150, 1899, AB23 <= 175, 2349, AB23 <= 200, 2799, AB23 <= 225, 3299, AB23 <= 250, 379, AB23 <= 275, 4199, AB23 <= 300, 4699, AB23 <= 325, 5199, "Exceso de peso"),"Error") -> 209 | U23: =J23-O23-P23-Q23-S23-T23 -> -55.227 | V23: =U23/O23 -> -0.041854808 | W23: 33.02 | X23: 27.69 | Y23: 40.9 | Z23: 5.61 | AA23: =(W23*X23*Y23)/5000 -> 7.4791687 | AB23: =IF(Z23>AA23,Z23,AA23) -> 7.4791687
A24: Activa | B24: IQ1296 | C24: 622356635042 | F24: Freidora de Aire AF141LAA | G24: Freidoras de Aire | H24: NINJA | I24: 3999 | J24: 3039.99 | L24: 12 | M24: =IFS(L24=0,0,L24=3,0.01,L24=6,0.03,L24=12,0.06) -> 0.06 | N24: Elektra envío gratis | O24: 1290 | P24: =J24*0.08 -> 243.1992 | Q24: =(J24-P24)*0.025 -> 69.91977 | R24: =15%+M24 -> 0.21 | S24: =J24*R24 -> 638.3979 | T24: =IF(AND(ISNUMBER(AB24)=TRUE(),AB24>0),SWITCH(TRUE(),AB24 <= 1, 129, AB24 <= 2, 139, AB24 <= 3, 149, AB24 <= 5, 169, AB24 <= 7, 179, AB24 <= 9, 209, AB24 <= 12, 249, AB24 <= 15, 299, AB24 <= 20, 390, AB24 <= 30, 420, AB24 <= 40, 525, AB24 <= 50, 859, AB24 <= 60, 1049, AB24 <= 70, 1099, AB24 <= 80, 1149, AB24 <= 90, 1169, AB24 <= 100, 1199, AB24 <= 125, 1449,AB24 <= 150, 1899, AB24 <= 175, 2349, AB24 <= 200, 2799, AB24 <= 225, 3299, AB24 <= 250, 379, AB24 <= 275, 4199, AB24 <= 300, 4699, AB24 <= 325, 5199, "Exceso de peso"),"Error") -> 209 | U24: =J24-O24-P24-Q24-S24-T24 -> 589.47313 | V24: =U24/O24 -> 0.45695591 | W24: 40.6 | X24: 31.2 | Y24: 32.48 | Z24: 5.4 | AA24: =(W24*X24*Y24)/5000 -> 8.2286131 | AB24: =IF(Z24>AA24,Z24,AA24) -> 8.2286131
A25: Apagada | B25: IQ1398 | C25: 622356631211 | F25: Freidora de Aire SL401 | G25: Freidoras de Aire | H25: NINJA | I25: 5999 | J25: 4899 | K25: 50 | L25: 3 | M25: =IFS(L25=0,0,L25=3,0.01,L25=6,0.03,L25=12,0.06) -> 0.01 | N25: Elektra envío gratis | O25: 2850 | P25: =J25*0.08 -> 391.92 | Q25: =(J25-P25)*0.025 -> 112.677 | R25: =15%+M25 -> 0.16 | S25: =J25*R25 -> 783.84 | T25: =IF(AND(ISNUMBER(AB25)=TRUE(),AB25>0),SWITCH(TRUE(),AB25 <= 1, 129, AB25 <= 2, 139, AB25 <= 3, 149, AB25 <= 5, 169, AB25 <= 7, 179, AB25 <= 9, 209, AB25 <= 12, 249, AB25 <= 15, 299, AB25 <= 20, 390, AB25 <= 30, 420, AB25 <= 40, 525, AB25 <= 50, 859, AB25 <= 60, 1049, AB25 <= 70, 1099, AB25 <= 80, 1149, AB25 <= 90, 1169, AB25 <= 100, 1199, AB25 <= 125, 1449,AB25 <= 150, 1899, AB25 <= 175, 2349, AB25 <= 200, 2799, AB25 <= 225, 3299, AB25 <= 250, 379, AB25 <= 275, 4199, AB25 <= 300, 4699, AB25 <= 325, 5199, "Exceso de peso"),"Error") -> 390 | U25: =J25-O25-P25-Q25-S25-T25 -> 370.563 | V25: =U25/O25 -> 0.13002211 | W25: 52.91 | X25: 33.2 | Y25: 45.01 | Z25: 12.25 | AA25: =(W25*X25*Y25)/5000 -> 15.813021 | AB25: =IF(Z25>AA25,Z25,AA25) -> 15.813021
A26: Apagada | B26: IQ1124 | C26: 622356559133 | F26: Freidora de Aire AF161 | G26: Freidoras de Aire | H26: NINJA | I26: 4999 | J26: 2899 | K26: 30 | L26: 3 | M26: =IFS(L26=0,0,L26=3,0.01,L26=6,0.03,L26=12,0.06) -> 0.01 | N26: Elektra envío gratis | O26: 1653.62 | P26: =J26*0.08 -> 231.92 | Q26: =(J26-P26)*0.025 -> 66.677 | R26: =15%+M26 -> 0.16 | S26: =J26*R26 -> 463.84 | T26: =IF(AND(ISNUMBER(AB26)=TRUE(),AB26>0),SWITCH(TRUE(),AB26 <= 1, 129, AB26 <= 2, 139, AB26 <= 3, 149, AB26 <= 5, 169, AB26 <= 7, 179, AB26 <= 9, 209, AB26 <= 12, 249, AB26 <= 15, 299, AB26 <= 20, 390, AB26 <= 30, 420, AB26 <= 40, 525, AB26 <= 50, 859, AB26 <= 60, 1049, AB26 <= 70, 1099, AB26 <= 80, 1149, AB26 <= 90, 1169, AB26 <= 100, 1199, AB26 <= 125, 1449,AB26 <= 150, 1899, AB26 <= 175, 2349, AB26 <= 200, 2799, AB26 <= 225, 3299, AB26 <= 250, 379, AB26 <= 275, 4199, AB26 <= 300, 4699, AB26 <= 325, 5199, "Exceso de peso"),"Error") -> 249 | U26: =J26-O26-P26-Q26-S26-T26 -> 233.943 | V26: =U26/O26 -> 0.14147325 | W26: 38.71 | X26: 30.51 | Y26: 40.79 | Z26: 6.11 | AA26: =(W26*X26*Y26)/5000 -> 9.6349415 | AB26: =IF(Z26>AA26,Z26,AA26) -> 9.6349415
A27: Apagada | B27: IQ973 | C27: 622356304900 | F27: TB401LAA | G27: Licuadoras | H27: NINJA | I27: 5999 | J27: 4599 | K27: 70 | L27: 3 | M27: =IFS(L27=0,0,L27=3,0.01,L27=6,0.03,L27=12,0.06) -> 0.01 | N27: Elektra envío gratis | O27: 2758 | P27: =J27*0.08 -> 367.92 | Q27: =(J27-P27)*0.025 -> 105.777 | R27: =15%+M27 -> 0.16 | S27: =J27*R27 -> 735.84 | T27: =IF(AND(ISNUMBER(AB27)=TRUE(),AB27>0),SWITCH(TRUE(),AB27 <= 1, 129, AB27 <= 2, 139, AB27 <= 3, 149, AB27 <= 5, 169, AB27 <= 7, 179, AB27 <= 9, 209, AB27 <= 12, 249, AB27 <= 15, 299, AB27 <= 20, 390, AB27 <= 30, 420, AB27 <= 40, 525, AB27 <= 50, 859, AB27 <= 60, 1049, AB27 <= 70, 1099, AB27 <= 80, 1149, AB27 <= 90, 1169, AB27 <= 100, 1199, AB27 <= 125, 1449,AB27 <= 150, 1899, AB27 <= 175, 2349, AB27 <= 200, 2799, AB27 <= 225, 3299, AB27 <= 250, 379, AB27 <= 275, 4199, AB27 <= 300, 4699, AB27 <= 325, 5199, "Exceso de peso"),"Error") -> 299 | U27: =J27-O27-P27-Q27-S27-T27 -> 332.463 | V27: =U27/O27 -> 0.12054496 | W27: 46.2 | X27: 29.7 | Y27: 46 | Z27: 8.1 | AA27: =(W27*X27*Y27)/5000 -> 12.623688 | AB27: =IF(Z27>AA27,Z27,AA27) -> 12.623688
A28: Activa | B28: IQ983 | C28: 622356642040 | F28: NC301LAA | G28: Otros | H28: NINJA | I28: 5999 | J28: 4499 | L28: 12 | M28: =IFS(L28=0,0,L28=3,0.01,L28=6,0.03,L28=12,0.06) -> 0.06 | N28: Elektra envío gratis | O28: 2043.16 | P28: =J28*0.08 -> 359.92 | Q28: =(J28-P28)*0.025 -> 103.477 | R28: =15%+M28 -> 0.21 | S28: =J28*R28 -> 944.79 | T28: =IF(AND(ISNUMBER(AB28)=TRUE(),AB28>0),SWITCH(TRUE(),AB28 <= 1, 129, AB28 <= 2, 139, AB28 <= 3, 149, AB28 <= 5, 169, AB28 <= 7, 179, AB28 <= 9, 209, AB28 <= 12, 249, AB28 <= 15, 299, AB28 <= 20, 390, AB28 <= 30, 420, AB28 <= 40, 525, AB28 <= 50, 859, AB28 <= 60, 1049, AB28 <= 70, 1099, AB28 <= 80, 1149, AB28 <= 90, 1169, AB28 <= 100, 1199, AB28 <= 125, 1449,AB28 <= 150, 1899, AB28 <= 175, 2349, AB28 <= 200, 2799, AB28 <= 225, 3299, AB28 <= 250, 379, AB28 <= 275, 4199, AB28 <= 300, 4699, AB28 <= 325, 5199, "Exceso de peso"),"Error") -> 209 | U28: =J28-O28-P28-Q28-S28-T28 -> 838.653 | V28: =U28/O28 -> 0.41046859 | W28: 43.5 | X28: 21.5 | Y28: 46 | Z28: 8 | AA28: =(W28*X28*Y28)/5000 -> 8.6043 | AB28: =IF(Z28>AA28,Z28,AA28) -> 8.6043
A29: Apagada | B29: IQ1316 | C29: 622356278164 | F29: BC151BK | G29: Licuadoras | H29: NINJA | I29: 1499 | J29: 1099 | K29: 85 | L29: 3 | M29: =IFS(L29=0,0,L29=3,0.01,L29=6,0.03,L29=12,0.06) -> 0.01 | N29: Elektra envío gratis | O29: 550.3 | P29: =J29*0.08 -> 87.92 | Q29: =(J29-P29)*0.025 -> 25.277 | R29: =15%+M29 -> 0.16 | S29: =J29*R29 -> 175.84 | T29: =IF(AND(ISNUMBER(AB29)=TRUE(),AB29>0),SWITCH(TRUE(),AB29 <= 1, 129, AB29 <= 2, 139, AB29 <= 3, 149, AB29 <= 5, 169, AB29 <= 7, 179, AB29 <= 9, 209, AB29 <= 12, 249, AB29 <= 15, 299, AB29 <= 20, 390, AB29 <= 30, 420, AB29 <= 40, 525, AB29 <= 50, 859, AB29 <= 60, 1049, AB29 <= 70, 1099, AB29 <= 80, 1149, AB29 <= 90, 1169, AB29 <= 100, 1199, AB29 <= 125, 1449,AB29 <= 150, 1899, AB29 <= 175, 2349, AB29 <= 200, 2799, AB29 <= 225, 3299, AB29 <= 250, 379, AB29 <= 275, 4199, AB29 <= 300, 4699, AB29 <= 325, 5199, "Exceso de peso"),"Error") -> 139 | U29: =J29-O29-P29-Q29-S29-T29 -> 120.663 | V29: =U29/O29 -> 0.21926767 | W29: 15 | X29: 12 | Y29: 28 | Z29: 1 | AA29: =(W29*X29*Y29)/5000 -> 1.008 | AB29: =IF(Z29>AA29,Z29,AA29) -> 1.008
A30: Apagada | B30: IQ1131 | C30: 622356557856 | D30: 80971225 | E30: 1301192911 | F30: Sistema De Cocina Ninja Ct672a | G30: Licuadoras | H30: Ninja | I30: 5999 | J30: 5199 | K30: 85 | L30: 3 | M30: =IFS(L30=0,0,L30=3,0.01,L30=6,0.03,L30=12,0.06) -> 0.01 | N30: Elektra envío gratis | O30: 3245.24 | P30: =J30*0.08 -> 415.92 | Q30: =(J30-P30)*0.025 -> 119.577 | R30: =15%+M30 -> 0.16 | S30: =J30*R30 -> 831.84 | T30: =IF(AND(ISNUMBER(AB30)=TRUE(),AB30>0),SWITCH(TRUE(),AB30 <= 1, 129, AB30 <= 2, 139, AB30 <= 3, 149, AB30 <= 5, 169, AB30 <= 7, 179, AB30 <= 9, 209, AB30 <= 12, 249, AB30 <= 15, 299, AB30 <= 20, 390, AB30 <= 30, 420, AB30 <= 40, 525, AB30 <= 50, 859, AB30 <= 60, 1049, AB30 <= 70, 1099, AB30 <= 80, 1149, AB30 <= 90, 1169, AB30 <= 100, 1199, AB30 <= 125, 1449,AB30 <= 150, 1899, AB30 <= 175, 2349, AB30 <= 200, 2799, AB30 <= 225, 3299, AB30 <= 250, 379, AB30 <= 275, 4199, AB30 <= 300, 4699, AB30 <= 325, 5199, "Exceso de peso"),"Error") -> 209 | U30: =J30-O30-P30-Q30-S30-T30 -> 377.423 | V30: =U30/O30 -> 0.11630049 | W30: 40.64 | X30: 26.67 | Y30: 41.28 | Z30: 6.43 | AA30: =(W30*X30*Y30)/5000 -> 8.9484208 | AB30: =IF(Z30>AA30,Z30,AA30) -> 8.9484208
A31: Apagada | B31: IQ1112 | C31: 622356304870 | D31: 80971224 | E31: 1301192947 | F31: Licuadora Ninja Tb201laa | G31: Licuadoras | H31: Ninja | I31: 4999 | J31: 3199 | K31: 85 | L31: 3 | M31: =IFS(L31=0,0,L31=3,0.01,L31=6,0.03,L31=12,0.06) -> 0.01 | N31: Elektra envío gratis | O31: 1814.25 | P31: =J31*0.08 -> 255.92 | Q31: =(J31-P31)*0.025 -> 73.577 | R31: =15%+M31 -> 0.16 | S31: =J31*R31 -> 511.84 | T31: =IF(AND(ISNUMBER(AB31)=TRUE(),AB31>0),SWITCH(TRUE(),AB31 <= 1, 129, AB31 <= 2, 139, AB31 <= 3, 149, AB31 <= 5, 169, AB31 <= 7, 179, AB31 <= 9, 209, AB31 <= 12, 249, AB31 <= 15, 299, AB31 <= 20, 390, AB31 <= 30, 420, AB31 <= 40, 525, AB31 <= 50, 859, AB31 <= 60, 1049, AB31 <= 70, 1099, AB31 <= 80, 1149, AB31 <= 90, 1169, AB31 <= 100, 1199, AB31 <= 125, 1449,AB31 <= 150, 1899, AB31 <= 175, 2349, AB31 <= 200, 2799, AB31 <= 225, 3299, AB31 <= 250, 379, AB31 <= 275, 4199, AB31 <= 300, 4699, AB31 <= 325, 5199, "Exceso de peso"),"Error") -> 249 | U31: =J31-O31-P31-Q31-S31-T31 -> 294.413 | V31: =U31/O31 -> 0.16227808 | W31: 36.5 | X31: 29.5 | Y31: 43 | Z31: 6 | AA31: =(W31*X31*Y31)/5000 -> 9.26005 | AB31: =IF(Z31>AA31,Z31,AA31) -> 9.26005
A32: Apagada | B32: IQ1108 | C32: 622356551625 | D32: 80971640 | E32: 1301193474 | F32: Licuadora Ninja Ct800 | G32: Licuadoras | H32: Ninja | I32: 4999 | J32: 4399 | K32: 85 | L32: 12 | M32: =IFS(L32=0,0,L32=3,0.01,L32=6,0.03,L32=12,0.06) -> 0.06 | N32: Elektra envío gratis | O32: 2233.92 | P32: =J32*0.08 -> 351.92 | Q32: =(J32-P32)*0.025 -> 101.177 | R32: =15%+M32 -> 0.21 | S32: =J32*R32 -> 923.79 | T32: =IF(AND(ISNUMBER(AB32)=TRUE(),AB32>0),SWITCH(TRUE(),AB32 <= 1, 129, AB32 <= 2, 139, AB32 <= 3, 149, AB32 <= 5, 169, AB32 <= 7, 179, AB32 <= 9, 209, AB32 <= 12, 249, AB32 <= 15, 299, AB32 <= 20, 390, AB32 <= 30, 420, AB32 <= 40, 525, AB32 <= 50, 859, AB32 <= 60, 1049, AB32 <= 70, 1099, AB32 <= 80, 1149, AB32 <= 90, 1169, AB32 <= 100, 1199, AB32 <= 125, 1449,AB32 <= 150, 1899, AB32 <= 175, 2349, AB32 <= 200, 2799, AB32 <= 225, 3299, AB32 <= 250, 379, AB32 <= 275, 4199, AB32 <= 300, 4699, AB32 <= 325, 5199, "Exceso de peso"),"Error") -> 249 | U32: =J32-O32-P32-Q32-S32-T32 -> 539.193 | V32: =U32/O32 -> 0.2413663 | W32: 36.5 | X32: 29.5 | Y32: 43 | Z32: 6 | AA32: =(W32*X32*Y32)/5000 -> 9.26005 | AB32: =IF(Z32>AA32,Z32,AA32) -> 9.26005
A33: Apagada | B33: IQ966 | C33: 622356569446 | D33: 80978160 | E33: 1301200377 | F33: Nutri Blender Bn401 | G33: Licuadoras | H33: Ninja | I33: 2999 | J33: 1599 | K33: 85 | L33: 3 | M33: =IFS(L33=0,0,L33=3,0.01,L33=6,0.03,L33=12,0.06) -> 0.01 | N33: Elektra envío gratis | O33: 1439.99 | P33: =J33*0.08 -> 127.92 | Q33: =(J33-P33)*0.025 -> 36.777 | R33: =15%+M33 -> 0.16 | S33: =J33*R33 -> 255.84 | T33: =IF(AND(ISNUMBER(AB33)=TRUE(),AB33>0),SWITCH(TRUE(),AB33 <= 1, 129, AB33 <= 2, 139, AB33 <= 3, 149, AB33 <= 5, 169, AB33 <= 7, 179, AB33 <= 9, 209, AB33 <= 12, 249, AB33 <= 15, 299, AB33 <= 20, 390, AB33 <= 30, 420, AB33 <= 40, 525, AB33 <= 50, 859, AB33 <= 60, 1049, AB33 <= 70, 1099, AB33 <= 80, 1149, AB33 <= 90, 1169, AB33 <= 100, 1199, AB33 <= 125, 1449,AB33 <= 150, 1899, AB33 <= 175, 2349, AB33 <= 200, 2799, AB33 <= 225, 3299, AB33 <= 250, 379, AB33 <= 275, 4199, AB33 <= 300, 4699, AB33 <= 325, 5199, "Exceso de peso"),"Error") -> 169 | U33: =J33-O33-P33-Q33-S33-T33 -> -430.527 | V33: =U33/O33 -> -0.29897916 | W33: 28.45 | X33: 21.34 | Y33: 24.13 | Z33: 3.27 | AA33: =(W33*X33*Y33)/5000 -> 2.9299756 | AB33: =IF(Z33>AA33,Z33,AA33) -> 3.27
A34: Apagada | B34: IQ974 | C34: 622356557535 | D34: 80978157 | E34: 1301200378 | F34: Cafetera Ninja Cm401 | G34: Cafeteras Y Teteras | H34: Ninja | I34: 5999 | J34: 4899 | K34: 85 | L34: 3 | M34: =IFS(L34=0,0,L34=3,0.01,L34=6,0.03,L34=12,0.06) -> 0.01 | N34: Elektra envío gratis | O34: 3039.92 | P34: =J34*0.08 -> 391.92 | Q34: =(J34-P34)*0.025 -> 112.677 | R34: =15%+M34 -> 0.16 | S34: =J34*R34 -> 783.84 | T34: =IF(AND(ISNUMBER(AB34)=TRUE(),AB34>0),SWITCH(TRUE(),AB34 <= 1, 129, AB34 <= 2, 139, AB34 <= 3, 149, AB34 <= 5, 169, AB34 <= 7, 179, AB34 <= 9, 209, AB34 <= 12, 249, AB34 <= 15, 299, AB34 <= 20, 390, AB34 <= 30, 420, AB34 <= 40, 525, AB34 <= 50, 859, AB34 <= 60, 1049, AB34 <= 70, 1099, AB34 <= 80, 1149, AB34 <= 90, 1169, AB34 <= 100, 1199, AB34 <= 125, 1449,AB34 <= 150, 1899, AB34 <= 175, 2349, AB34 <= 200, 2799, AB34 <= 225, 3299, AB34 <= 250, 379, AB34 <= 275, 4199, AB34 <= 300, 4699, AB34 <= 325, 5199, "Exceso de peso"),"Error") -> 209 | U34: =J34-O34-P34-Q34-S34-T34 -> 361.643 | V34: =U34/O34 -> 0.11896464 | W34: 34.2 | X34: 27.9 | Y34: 41.2 | Z34: 5.39 | AA34: =(W34*X34*Y34)/5000 -> 7.8624432 | AB34: =IF(Z34>AA34,Z34,AA34) -> 7.8624432
A35: Apagada | B35: IQ1117 | C35: 622356549271 | D35: 80978522 | E35: 1301200698 | F35: Licuadora Ninja Ct610 | G35: Licuadoras | H35: Ninja | I35: 3999 | J35: 2399 | K35: 85 | L35: 3 | M35: =IFS(L35=0,0,L35=3,0.01,L35=6,0.03,L35=12,0.06) -> 0.01 | N35: Elektra envío gratis | O35: 1404.41 | P35: =J35*0.08 -> 191.92 | Q35: =(J35-P35)*0.025 -> 55.177 | R35: =15%+M35 -> 0.16 | S35: =J35*R35 -> 383.84 | T35: =IF(AND(ISNUMBER(AB35)=TRUE(),AB35>0),SWITCH(TRUE(),AB35 <= 1, 129, AB35 <= 2, 139, AB35 <= 3, 149, AB35 <= 5, 169, AB35 <= 7, 179, AB35 <= 9, 209, AB35 <= 12, 249, AB35 <= 15, 299, AB35 <= 20, 390, AB35 <= 30, 420, AB35 <= 40, 525, AB35 <= 50, 859, AB35 <= 60, 1049, AB35 <= 70, 1099, AB35 <= 80, 1149, AB35 <= 90, 1169, AB35 <= 100, 1199, AB35 <= 125, 1449,AB35 <= 150, 1899, AB35 <= 175, 2349, AB35 <= 200, 2799, AB35 <= 225, 3299, AB35 <= 250, 379, AB35 <= 275, 4199, AB35 <= 300, 4699, AB35 <= 325, 5199, "Exceso de peso"),"Error") -> 169 | U35: =J35-O35-P35-Q35-S35-T35 -> 194.653 | V35: =U35/O35 -> 0.13860126 | W35: 27.2 | X35: 21.01 | Y35: 40.5 | Z35: 4.21 | AA35: =(W35*X35*Y35)/5000 -> 4.6289232 | AB35: =IF(Z35>AA35,Z35,AA35) -> 4.6289232
A36: Apagada | B36: 2694276 | C36: 6932554403867 | D36: 80965680 | E36: 1301186660 | F36: Cafetera Espresso Xiaomi | G36: Cafeteras Y Teteras | H36: Xiaomi | I36: 3599 | J36: 2899 | K36: 85 | L36: 3 | M36: =IFS(L36=0,0,L36=3,0.01,L36=6,0.03,L36=12,0.06) -> 0.01 | N36: Elektra envío gratis | O36: 1730 | P36: =J36*0.08 -> 231.92 | Q36: =(J36-P36)*0.025 -> 66.677 | R36: =15%+M36 -> 0.16 | S36: =J36*R36 -> 463.84 | T36: =IF(AND(ISNUMBER(AB36)=TRUE(),AB36>0),SWITCH(TRUE(),AB36 <= 1, 129, AB36 <= 2, 139, AB36 <= 3, 149, AB36 <= 5, 169, AB36 <= 7, 179, AB36 <= 9, 209, AB36 <= 12, 249, AB36 <= 15, 299, AB36 <= 20, 390, AB36 <= 30, 420, AB36 <= 40, 525, AB36 <= 50, 859, AB36 <= 60, 1049, AB36 <= 70, 1099, AB36 <= 80, 1149, AB36 <= 90, 1169, AB36 <= 100, 1199, AB36 <= 125, 1449,AB36 <= 150, 1899, AB36 <= 175, 2349, AB36 <= 200, 2799, AB36 <= 225, 3299, AB36 <= 250, 379, AB36 <= 275, 4199, AB36 <= 300, 4699, AB36 <= 325, 5199, "Exceso de peso"),"Error") -> 169 | U36: =J36-O36-P36-Q36-S36-T36 -> 237.563 | V36: =U36/O36 -> 0.13731965 | W36: 35 | X36: 19 | Y36: 33 | Z36: 4.2 | AA36: =(W36*X36*Y36)/5000 -> 4.389 | AB36: =IF(Z36>AA36,Z36,AA36) -> 4.389
A37: Apagada | B37: IQ1453 | C37: 40094191048 | D37: 81032645 | E37: 1301276510 | F37: Plancha Hamilton Beach | G37: Planchas | H37: Hamilton Beach | I37: 599 | J37: 419 | K37: 10 | L37: 3 | M37: =IFS(L37=0,0,L37=3,0.01,L37=6,0.03,L37=12,0.06) -> 0.01 | N37: Elektra envío gratis | O37: 150 | P37: =J37*0.08 -> 33.52 | Q37: =(J37-P37)*0.025 -> 9.637 | R37: =15%+M37 -> 0.16 | S37: =J37*R37 -> 67.04 | T37: =IF(AND(ISNUMBER(AB37)=TRUE(),AB37>0),SWITCH(TRUE(),AB37 <= 1, 129, AB37 <= 2, 139, AB37 <= 3, 149, AB37 <= 5, 169, AB37 <= 7, 179, AB37 <= 9, 209, AB37 <= 12, 249, AB37 <= 15, 299, AB37 <= 20, 390, AB37 <= 30, 420, AB37 <= 40, 525, AB37 <= 50, 859, AB37 <= 60, 1049, AB37 <= 70, 1099, AB37 <= 80, 1149, AB37 <= 90, 1169, AB37 <= 100, 1199, AB37 <= 125, 1449,AB37 <= 150, 1899, AB37 <= 175, 2349, AB37 <= 200, 2799, AB37 <= 225, 3299, AB37 <= 250, 379, AB37 <= 275, 4199, AB37 <= 300, 4699, AB37 <= 325, 5199, "Exceso de peso"),"Error") -> 139 | U37: =J37-O37-P37-Q37-S37-T37 -> 19.803 | V37: =U37/O37 -> 0.13202 | W37: 30.1 | X37: 16.5 | Y37: 12.4 | Z37: 1.12 | AA37: =(W37*X37*Y37)/5000 -> 1.231692 | AB37: =IF(Z37>AA37,Z37,AA37) -> 1.231692
A38: Apagada | B38: IQ1448 | C38: 622356688420 | D38: 81035608 | E38: 1301279704 | F38: Ventilador Torre Shark Turbolade TF202S | G38: Ventiladores | H38: Shark | J38: 4999 | K38: 10 | L38: 3 | M38: =IFS(L38=0,0,L38=3,0.01,L38=6,0.03,L38=12,0.06) -> 0.01 | N38: Elektra envío gratis | O38: 2993.03 | P38: =J38*0.08 -> 399.92 | Q38: =(J38-P38)*0.025 -> 114.977 | R38: =15%+M38 -> 0.16 | S38: =J38*R38 -> 799.84 | T38: =IF(AND(ISNUMBER(AB38)=TRUE(),AB38>0),SWITCH(TRUE(),AB38 <= 1, 129, AB38 <= 2, 139, AB38 <= 3, 149, AB38 <= 5, 169, AB38 <= 7, 179, AB38 <= 9, 209, AB38 <= 12, 249, AB38 <= 15, 299, AB38 <= 20, 390, AB38 <= 30, 420, AB38 <= 40, 525, AB38 <= 50, 859, AB38 <= 60, 1049, AB38 <= 70, 1099, AB38 <= 80, 1149, AB38 <= 90, 1169, AB38 <= 100, 1199, AB38 <= 125, 1449,AB38 <= 150, 1899, AB38 <= 175, 2349, AB38 <= 200, 2799, AB38 <= 225, 3299, AB38 <= 250, 379, AB38 <= 275, 4199, AB38 <= 300, 4699, AB38 <= 325, 5199, "Exceso de peso"),"Error") -> 299 | U38: =J38-O38-P38-Q38-S38-T38 -> 392.233 | V38: =U38/O38 -> 0.1310488 | W38: 44 | X38: 30.5 | Y38: 55 | Z38: 9.42 | AA38: =(W38*X38*Y38)/5000 -> 14.762 | AB38: =IF(Z38>AA38,Z38,AA38) -> 14.762
A39: Apagada | B39: IQ1361 | C39: 6291100130498 | D39: 81035777 | E39: 1301279920 | F39: Al Haramain Amber Oud Gold 120 mL | G39: Hombre | H39: Al Haramain | I39: 1599 | J39: 1329 | L39: 3 | M39: =IFS(L39=0,0,L39=3,0.01,L39=6,0.03,L39=12,0.06) -> 0.01 | N39: Elektra envío gratis | O39: 932.68 | P39: =J39*0.08 -> 106.32 | Q39: =(J39-P39)*0.025 -> 30.567 | R39: =15%+M39 -> 0.16 | S39: =J39*R39 -> 212.64 | T39: =IF(AND(ISNUMBER(AB39)=TRUE(),AB39>0),SWITCH(TRUE(),AB39 <= 1, 129, AB39 <= 2, 139, AB39 <= 3, 149, AB39 <= 5, 169, AB39 <= 7, 179, AB39 <= 9, 209, AB39 <= 12, 249, AB39 <= 15, 299, AB39 <= 20, 390, AB39 <= 30, 420, AB39 <= 40, 525, AB39 <= 50, 859, AB39 <= 60, 1049, AB39 <= 70, 1099, AB39 <= 80, 1149, AB39 <= 90, 1169, AB39 <= 100, 1199, AB39 <= 125, 1449,AB39 <= 150, 1899, AB39 <= 175, 2349, AB39 <= 200, 2799, AB39 <= 225, 3299, AB39 <= 250, 379, AB39 <= 275, 4199, AB39 <= 300, 4699, AB39 <= 325, 5199, "Exceso de peso"),"Error") -> 129 | U39: =J39-O39-P39-Q39-S39-T39 -> -82.207 | V39: =U39/O39 -> -0.088140627 | W39: 9 | X39: 9 | Y39: 17 | Z39: 0.6 | AA39: =(W39*X39*Y39)/5000 -> 0.2754 | AB39: =IF(Z39>AA39,Z39,AA39) -> 0.6
A40: Apagada | B40: IQ1075 | C40: 50036405850 | D40: 81035966 | E40: 1301280067 | F40: Jbl Tune Beam 2 Negro | G40: Audífonos | H40: Jbl | I40: 1999 | J40: 1899 | K40: 15 | L40: 3 | M40: =IFS(L40=0,0,L40=3,0.01,L40=6,0.03,L40=12,0.06) -> 0.01 | N40: Elektra envío gratis | O40: 1203.69 | P40: =J40*0.08 -> 151.92 | Q40: =(J40-P40)*0.025 -> 43.677 | R40: =11%+M40 -> 0.12 | S40: =J40*R40 -> 227.88 | T40: =IF(AND(ISNUMBER(AB40)=TRUE(),AB40>0),SWITCH(TRUE(),AB40 <= 1, 129, AB40 <= 2, 139, AB40 <= 3, 149, AB40 <= 5, 169, AB40 <= 7, 179, AB40 <= 9, 209, AB40 <= 12, 249, AB40 <= 15, 299, AB40 <= 20, 390, AB40 <= 30, 420, AB40 <= 40, 525, AB40 <= 50, 859, AB40 <= 60, 1049, AB40 <= 70, 1099, AB40 <= 80, 1149, AB40 <= 90, 1169, AB40 <= 100, 1199, AB40 <= 125, 1449,AB40 <= 150, 1899, AB40 <= 175, 2349, AB40 <= 200, 2799, AB40 <= 225, 3299, AB40 <= 250, 379, AB40 <= 275, 4199, AB40 <= 300, 4699, AB40 <= 325, 5199, "Exceso de peso"),"Error") -> 129 | U40: =J40-O40-P40-Q40-S40-T40 -> 142.833 | V40: =U40/O40 -> 0.11866261 | W40: 10 | X40: 10 | Y40: 4.5 | Z40: 0.2 | AA40: =(W40*X40*Y40)/5000 -> 0.09 | AB40: =IF(Z40>AA40,Z40,AA40) -> 0.2
A41: Apagada | F41: JBL Quantum 100 M2 Blanco | J41: 859 | K41: 20 | L41: 3 | M41: =IFS(L41=0,0,L41=3,0.01,L41=6,0.03,L41=12,0.06) -> 0.01 | N41: Elektra envío gratis | O41: 432.37 | P41: =J41*0.08 -> 68.72 | Q41: =(J41-P41)*0.025 -> 19.757 | R41: =16%+M41 -> 0.17 | S41: =J41*R41 -> 146.03 | T41: =IF(AND(ISNUMBER(AB41)=TRUE(),AB41>0),SWITCH(TRUE(),AB41 <= 1, 129, AB41 <= 2, 139, AB41 <= 3, 149, AB41 <= 5, 169, AB41 <= 7, 179, AB41 <= 9, 209, AB41 <= 12, 249, AB41 <= 15, 299, AB41 <= 20, 390, AB41 <= 30, 420, AB41 <= 40, 525, AB41 <= 50, 859, AB41 <= 60, 1049, AB41 <= 70, 1099, AB41 <= 80, 1149, AB41 <= 90, 1169, AB41 <= 100, 1199, AB41 <= 125, 1449,AB41 <= 150, 1899, AB41 <= 175, 2349, AB41 <= 200, 2799, AB41 <= 225, 3299, AB41 <= 250, 379, AB41 <= 275, 4199, AB41 <= 300, 4699, AB41 <= 325, 5199, "Exceso de peso"),"Error") -> 129 | U41: =J41-O41-P41-Q41-S41-T41 -> 63.123 | V41: =U41/O41 -> 0.14599302 | W41: 10.5 | X41: 20 | Y41: 22 | Z41: 0.6 | AA41: =(W41*X41*Y41)/5000 -> 0.924 | AB41: =IF(Z41>AA41,Z41,AA41) -> 0.924
A42: Apagada | B42: IQ1071 | C42: 50036404709 | D42: 81054864 | E42: 1301319043 | F42: JBL Endurance race 2 headphones NC Black | G42: Audífonos | H42: JBL | I42: 1999 | J42: 1579 | K42: 20 | L42: 3 | M42: =IFS(L42=0,0,L42=3,0.01,L42=6,0.03,L42=12,0.06) -> 0.01 | N42: Elektra envío gratis | O42: 899.69 | P42: =J42*0.08 -> 126.32 | Q42: =(J42-P42)*0.025 -> 36.317 | R42: =16%+M42 -> 0.17 | S42: =J42*R42 -> 268.43 | T42: =IF(AND(ISNUMBER(AB42)=TRUE(),AB42>0),SWITCH(TRUE(),AB42 <= 1, 129, AB42 <= 2, 139, AB42 <= 3, 149, AB42 <= 5, 169, AB42 <= 7, 179, AB42 <= 9, 209, AB42 <= 12, 249, AB42 <= 15, 299, AB42 <= 20, 390, AB42 <= 30, 420, AB42 <= 40, 525, AB42 <= 50, 859, AB42 <= 60, 1049, AB42 <= 70, 1099, AB42 <= 80, 1149, AB42 <= 90, 1169, AB42 <= 100, 1199, AB42 <= 125, 1449,AB42 <= 150, 1899, AB42 <= 175, 2349, AB42 <= 200, 2799, AB42 <= 225, 3299, AB42 <= 250, 379, AB42 <= 275, 4199, AB42 <= 300, 4699, AB42 <= 325, 5199, "Exceso de peso"),"Error") -> 129 | U42: =J42-O42-P42-Q42-S42-T42 -> 119.243 | V42: =U42/O42 -> 0.13253787 | W42: 10.5 | X42: 10 | Y42: 4.5 | Z42: 0.22 | AA42: =(W42*X42*Y42)/5000 -> 0.0945 | AB42: =IF(Z42>AA42,Z42,AA42) -> 0.22
A43: Apagada | B43: IQ700 | C43: 28292290343 | D43: 81054857 | E43: 1301319048 | F43: Harman Kardon Go Play 3 Black | G43: Bocinas | H43: Harman Kardon | I43: 7999 | J43: 5799 | K43: 20 | L43: 3 | M43: =IFS(L43=0,0,L43=3,0.01,L43=6,0.03,L43=12,0.06) -> 0.01 | N43: Elektra envío gratis | O43: 3742.79 | P43: =J43*0.08 -> 463.92 | Q43: =(J43-P43)*0.025 -> 133.377 | R43: =11%+M43 -> 0.12 | S43: =J43*R43 -> 695.88 | T43: =IF(AND(ISNUMBER(AB43)=TRUE(),AB43>0),SWITCH(TRUE(),AB43 <= 1, 129, AB43 <= 2, 139, AB43 <= 3, 149, AB43 <= 5, 169, AB43 <= 7, 179, AB43 <= 9, 209, AB43 <= 12, 249, AB43 <= 15, 299, AB43 <= 20, 390, AB43 <= 30, 420, AB43 <= 40, 525, AB43 <= 50, 859, AB43 <= 60, 1049, AB43 <= 70, 1099, AB43 <= 80, 1149, AB43 <= 90, 1169, AB43 <= 100, 1199, AB43 <= 125, 1449,AB43 <= 150, 1899, AB43 <= 175, 2349, AB43 <= 200, 2799, AB43 <= 225, 3299, AB43 <= 250, 379, AB43 <= 275, 4199, AB43 <= 300, 4699, AB43 <= 325, 5199, "Exceso de peso"),"Error") -> 249 | U43: =J43-O43-P43-Q43-S43-T43 -> 514.033 | V43: =U43/O43 -> 0.13733952 | W43: 51.5 | X43: 27.5 | Y43: 32.5 | Z43: 6.3 | AA43: =(W43*X43*Y43)/5000 -> 9.205625 | AB43: =IF(Z43>AA43,Z43,AA43) -> 9.205625
A44: Apagada | B44: IQ739 | C44: 50036390934 | D44: 81050755 | E44: 1301293797 | F44: Jbl Wave Beam Negro | G44: Audífonos | H44: JBL | I44: 1299 | J44: 749 | K44: 60 | L44: 3 | M44: =IFS(L44=0,0,L44=3,0.01,L44=6,0.03,L44=12,0.06) -> 0.01 | N44: Elektra envío gratis | O44: 377.67 | P44: =J44*0.08 -> 59.92 | Q44: =(J44-P44)*0.025 -> 17.227 | R44: =11%+M44 -> 0.12 | S44: =J44*R44 -> 89.88 | T44: =IF(AND(ISNUMBER(AB44)=TRUE(),AB44>0),SWITCH(TRUE(),AB44 <= 1, 129, AB44 <= 2, 139, AB44 <= 3, 149, AB44 <= 5, 169, AB44 <= 7, 179, AB44 <= 9, 209, AB44 <= 12, 249, AB44 <= 15, 299, AB44 <= 20, 390, AB44 <= 30, 420, AB44 <= 40, 525, AB44 <= 50, 859, AB44 <= 60, 1049, AB44 <= 70, 1099, AB44 <= 80, 1149, AB44 <= 90, 1169, AB44 <= 100, 1199, AB44 <= 125, 1449,AB44 <= 150, 1899, AB44 <= 175, 2349, AB44 <= 200, 2799, AB44 <= 225, 3299, AB44 <= 250, 379, AB44 <= 275, 4199, AB44 <= 300, 4699, AB44 <= 325, 5199, "Exceso de peso"),"Error") -> 129 | U44: =J44-O44-P44-Q44-S44-T44 -> 75.303 | V44: =U44/O44 -> 0.19938835 | W44: 10.5 | X44: 10 | Y44: 4.5 | Z44: 0.19 | AA44: =(W44*X44*Y44)/5000 -> 0.0945 | AB44: =IF(Z44>AA44,Z44,AA44) -> 0.19
A45: Apagada | B45: IQ729 | C45: 50036382953 | D45: 81055647 | E45: 1301319714 | F45: JBL Wave 200 Blanco | G45: Audífonos | H45: JBL | I45: 1199 | J45: 659 | K45: 50 | L45: 3 | M45: =IFS(L45=0,0,L45=3,0.01,L45=6,0.03,L45=12,0.06) -> 0.01 | N45: Elektra envío gratis | O45: 318.04 | P45: =J45*0.08 -> 52.72 | Q45: =(J45-P45)*0.025 -> 15.157 | R45: =11%+M45 -> 0.12 | S45: =J45*R45 -> 79.08 | T45: =IF(AND(ISNUMBER(AB45)=TRUE(),AB45>0),SWITCH(TRUE(),AB45 <= 1, 129, AB45 <= 2, 139, AB45 <= 3, 149, AB45 <= 5, 169, AB45 <= 7, 179, AB45 <= 9, 209, AB45 <= 12, 249, AB45 <= 15, 299, AB45 <= 20, 390, AB45 <= 30, 420, AB45 <= 40, 525, AB45 <= 50, 859, AB45 <= 60, 1049, AB45 <= 70, 1099, AB45 <= 80, 1149, AB45 <= 90, 1169, AB45 <= 100, 1199, AB45 <= 125, 1449,AB45 <= 150, 1899, AB45 <= 175, 2349, AB45 <= 200, 2799, AB45 <= 225, 3299, AB45 <= 250, 379, AB45 <= 275, 4199, AB45 <= 300, 4699, AB45 <= 325, 5199, "Exceso de peso"),"Error") -> 129 | U45: =J45-O45-P45-Q45-S45-T45 -> 65.003 | V45: =U45/O45 -> 0.20438624 | W45: 10 | X45: 10 | Y45: 4 | Z45: 0.18 | AA45: =(W45*X45*Y45)/5000 -> 0.08 | AB45: =IF(Z45>AA45,Z45,AA45) -> 0.18
A46: Apagada | B46: IQ730 | C46: 50036382946 | D46: 81055650 | E46: 1301319754 | F46: JBL Wave 200 Negro | G46: Audífonos | H46: JBL | I46: 1199 | J46: 659 | K46: 50 | L46: 3 | M46: =IFS(L46=0,0,L46=3,0.01,L46=6,0.03,L46=12,0.06) -> 0.01 | N46: Elektra envío gratis | O46: 318.04 | P46: =J46*0.08 -> 52.72 | Q46: =(J46-P46)*0.025 -> 15.157 | R46: =11%+M46 -> 0.12 | S46: =J46*R46 -> 79.08 | T46: =IF(AND(ISNUMBER(AB46)=TRUE(),AB46>0),SWITCH(TRUE(),AB46 <= 1, 129, AB46 <= 2, 139, AB46 <= 3, 149, AB46 <= 5, 169, AB46 <= 7, 179, AB46 <= 9, 209, AB46 <= 12, 249, AB46 <= 15, 299, AB46 <= 20, 390, AB46 <= 30, 420, AB46 <= 40, 525, AB46 <= 50, 859, AB46 <= 60, 1049, AB46 <= 70, 1099, AB46 <= 80, 1149, AB46 <= 90, 1169, AB46 <= 100, 1199, AB46 <= 125, 1449,AB46 <= 150, 1899, AB46 <= 175, 2349, AB46 <= 200, 2799, AB46 <= 225, 3299, AB46 <= 250, 379, AB46 <= 275, 4199, AB46 <= 300, 4699, AB46 <= 325, 5199, "Exceso de peso"),"Error") -> 129 | U46: =J46-O46-P46-Q46-S46-T46 -> 65.003 | V46: =U46/O46 -> 0.20438624 | W46: 10 | X46: 10 | Y46: 4 | Z46: 0.18 | AA46: =(W46*X46*Y46)/5000 -> 0.08 | AB46: =IF(Z46>AA46,Z46,AA46) -> 0.18
A47: Apagada | B47: IQ1312 | C47: 840080503653 | D47: 81055651 | E47: 1301319773 | F47: Amazon Echo Dot 5ta Generación Negro | G47: Asistentes Virtuales | H47: Amazon | I47: 1799 | J47: 1389 | K47: 100 | L47: 3 | M47: =IFS(L47=0,0,L47=3,0.01,L47=6,0.03,L47=12,0.06) -> 0.01 | N47: Elektra envío gratis | O47: 763.4 | P47: =J47*0.08 -> 111.12 | Q47: =(J47-P47)*0.025 -> 31.947 | R47: =16%+M47 -> 0.17 | S47: =J47*R47 -> 236.13 | T47: =IF(AND(ISNUMBER(AB47)=TRUE(),AB47>0),SWITCH(TRUE(),AB47 <= 1, 129, AB47 <= 2, 139, AB47 <= 3, 149, AB47 <= 5, 169, AB47 <= 7, 179, AB47 <= 9, 209, AB47 <= 12, 249, AB47 <= 15, 299, AB47 <= 20, 390, AB47 <= 30, 420, AB47 <= 40, 525, AB47 <= 50, 859, AB47 <= 60, 1049, AB47 <= 70, 1099, AB47 <= 80, 1149, AB47 <= 90, 1169, AB47 <= 100, 1199, AB47 <= 125, 1449,AB47 <= 150, 1899, AB47 <= 175, 2349, AB47 <= 200, 2799, AB47 <= 225, 3299, AB47 <= 250, 379, AB47 <= 275, 4199, AB47 <= 300, 4699, AB47 <= 325, 5199, "Exceso de peso"),"Error") -> 129 | U47: =J47-O47-P47-Q47-S47-T47 -> 117.403 | V47: =U47/O47 -> 0.15378963 | W47: 10 | X47: 10 | Y47: 9 | Z47: 0.45 | AA47: =(W47*X47*Y47)/5000 -> 0.18 | AB47: =IF(Z47>AA47,Z47,AA47) -> 0.45
A48: Apagada | B48: IQ1063 | C48: 6941812743669 | D48: 81106537 | E48: 1301362770 | F48: Xiaomi 33w Powwerbank 10000 Cable Beige | G48: Pilas Y Cargadores | H48: Xiaomi | I48: 999 | J48: 719 | K48: 5 | L48: 3 | M48: =IFS(L48=0,0,L48=3,0.01,L48=6,0.03,L48=12,0.06) -> 0.01 | N48: Elektra envío gratis | O48: 350 | P48: =J48*0.08 -> 57.52 | Q48: =(J48-P48)*0.025 -> 16.537 | R48: =16%+M48 -> 0.17 | S48: =J48*R48 -> 122.23 | T48: =IF(AND(ISNUMBER(AB48)=TRUE(),AB48>0),SWITCH(TRUE(),AB48 <= 1, 129, AB48 <= 2, 139, AB48 <= 3, 149, AB48 <= 5, 169, AB48 <= 7, 179, AB48 <= 9, 209, AB48 <= 12, 249, AB48 <= 15, 299, AB48 <= 20, 390, AB48 <= 30, 420, AB48 <= 40, 525, AB48 <= 50, 859, AB48 <= 60, 1049, AB48 <= 70, 1099, AB48 <= 80, 1149, AB48 <= 90, 1169, AB48 <= 100, 1199, AB48 <= 125, 1449,AB48 <= 150, 1899, AB48 <= 175, 2349, AB48 <= 200, 2799, AB48 <= 225, 3299, AB48 <= 250, 379, AB48 <= 275, 4199, AB48 <= 300, 4699, AB48 <= 325, 5199, "Exceso de peso"),"Error") -> 129 | U48: =J48-O48-P48-Q48-S48-T48 -> 43.713 | V48: =U48/O48 -> 0.12489429 | W48: 14.5 | X48: 9 | Y48: 3 | Z48: 0.3 | AA48: =(W48*X48*Y48)/5000 -> 0.0783 | AB48: =IF(Z48>AA48,Z48,AA48) -> 0.3
A49: Apagada | B49: IQ36 | C49: 6971408153473 | D49: 81106538 | E49: 1301362679 | F49: Xiaomi Mi Portable Speaker 16w Azul | G49: Bocinas | H49: Xiaomi | I49: 1299 | J49: 799 | L49: 3 | M49: =IFS(L49=0,0,L49=3,0.01,L49=6,0.03,L49=12,0.06) -> 0.01 | N49: Elektra envío gratis | O49: 440 | P49: =J49*0.08 -> 63.92 | Q49: =(J49-P49)*0.025 -> 18.377 | R49: =11%+M49 -> 0.12 | S49: =J49*R49 -> 95.88 | T49: =IF(AND(ISNUMBER(AB49)=TRUE(),AB49>0),SWITCH(TRUE(),AB49 <= 1, 129, AB49 <= 2, 139, AB49 <= 3, 149, AB49 <= 5, 169, AB49 <= 7, 179, AB49 <= 9, 209, AB49 <= 12, 249, AB49 <= 15, 299, AB49 <= 20, 390, AB49 <= 30, 420, AB49 <= 40, 525, AB49 <= 50, 859, AB49 <= 60, 1049, AB49 <= 70, 1099, AB49 <= 80, 1149, AB49 <= 90, 1169, AB49 <= 100, 1199, AB49 <= 125, 1449,AB49 <= 150, 1899, AB49 <= 175, 2349, AB49 <= 200, 2799, AB49 <= 225, 3299, AB49 <= 250, 379, AB49 <= 275, 4199, AB49 <= 300, 4699, AB49 <= 325, 5199, "Exceso de peso"),"Error") -> 139 | U49: =J49-O49-P49-Q49-S49-T49 -> 41.823 | V49: =U49/O49 -> 0.095052273 | W49: 24 | X49: 9.5 | Y49: 9.5 | Z49: 1.05 | AA49: =(W49*X49*Y49)/5000 -> 0.4332 | AB49: =IF(Z49>AA49,Z49,AA49) -> 1.05
A50: Apagada | B50: IQ1084 | C50: 190997007080 | D50: 81209724 | E50: 1301466516 | F50: Xiaomi Sound Outdoor 30w Negro | G50: Bocinas | H50: Xiaomi | I50: 1399 | J50: 1099 | L50: 3 | M50: =IFS(L50=0,0,L50=3,0.01,L50=6,0.03,L50=12,0.06) -> 0.01 | N50: Elektra envío gratis | O50: 630 | P50: =J50*0.08 -> 87.92 | Q50: =(J50-P50)*0.025 -> 25.277 | R50: =11%+M50 -> 0.12 | S50: =J50*R50 -> 131.88 | T50: =IF(AND(ISNUMBER(AB50)=TRUE(),AB50>0),SWITCH(TRUE(),AB50 <= 1, 129, AB50 <= 2, 139, AB50 <= 3, 149, AB50 <= 5, 169, AB50 <= 7, 179, AB50 <= 9, 209, AB50 <= 12, 249, AB50 <= 15, 299, AB50 <= 20, 390, AB50 <= 30, 420, AB50 <= 40, 525, AB50 <= 50, 859, AB50 <= 60, 1049, AB50 <= 70, 1099, AB50 <= 80, 1149, AB50 <= 90, 1169, AB50 <= 100, 1199, AB50 <= 125, 1449,AB50 <= 150, 1899, AB50 <= 175, 2349, AB50 <= 200, 2799, AB50 <= 225, 3299, AB50 <= 250, 379, AB50 <= 275, 4199, AB50 <= 300, 4699, AB50 <= 325, 5199, "Exceso de peso"),"Error") -> 139 | U50: =J50-O50-P50-Q50-S50-T50 -> 84.923 | V50: =U50/O50 -> 0.13479841 | W50: 24 | X50: 9.5 | Y50: 9.5 | Z50: 1.05 | AA50: =(W50*X50*Y50)/5000 -> 0.4332 | AB50: =IF(Z50>AA50,Z50,AA50) -> 1.05
A51: Apagada | B51: IQ1458 | C51: 190997007103 | D51: 81209718 | E51: 1301466526 | F51: Xiaomi Sound Outdoor 30w Azul | G51: Bocinas | H51: Xiaomi | I51: 1399 | J51: 1099 | L51: 3 | M51: =IFS(L51=0,0,L51=3,0.01,L51=6,0.03,L51=12,0.06) -> 0.01 | N51: Elektra envío gratis | O51: 630 | P51: =J51*0.08 -> 87.92 | Q51: =(J51-P51)*0.025 -> 25.277 | R51: =11%+M51 -> 0.12 | S51: =J51*R51 -> 131.88 | T51: =IF(AND(ISNUMBER(AB51)=TRUE(),AB51>0),SWITCH(TRUE(),AB51 <= 1, 129, AB51 <= 2, 139, AB51 <= 3, 149, AB51 <= 5, 169, AB51 <= 7, 179, AB51 <= 9, 209, AB51 <= 12, 249, AB51 <= 15, 299, AB51 <= 20, 390, AB51 <= 30, 420, AB51 <= 40, 525, AB51 <= 50, 859, AB51 <= 60, 1049, AB51 <= 70, 1099, AB51 <= 80, 1149, AB51 <= 90, 1169, AB51 <= 100, 1199, AB51 <= 125, 1449,AB51 <= 150, 1899, AB51 <= 175, 2349, AB51 <= 200, 2799, AB51 <= 225, 3299, AB51 <= 250, 379, AB51 <= 275, 4199, AB51 <= 300, 4699, AB51 <= 325, 5199, "Exceso de peso"),"Error") -> 139 | U51: =J51-O51-P51-Q51-S51-T51 -> 84.923 | V51: =U51/O51 -> 0.13479841 | W51: 24 | X51: 9.5 | Y51: 9.5 | Z51: 1.05 | AA51: =(W51*X51*Y51)/5000 -> 0.4332 | AB51: =IF(Z51>AA51,Z51,AA51) -> 1.05
A52: Apagada | B52: IQ1035 | C52: 6941812743768 | D52: 81209719 | E52: 1301466519 | F52: Xiaomi Outdoor Cámara Cw300 | G52: De Seguridad | H52: Xiaomi | I52: 1499 | J52: 1299 | L52: 3 | M52: =IFS(L52=0,0,L52=3,0.01,L52=6,0.03,L52=12,0.06) -> 0.01 | N52: Elektra envío gratis | O52: 700 | P52: =J52*0.08 -> 103.92 | Q52: =(J52-P52)*0.025 -> 29.877 | R52: =16%+M52 -> 0.17 | S52: =J52*R52 -> 220.83 | T52: =IF(AND(ISNUMBER(AB52)=TRUE(),AB52>0),SWITCH(TRUE(),AB52 <= 1, 129, AB52 <= 2, 139, AB52 <= 3, 149, AB52 <= 5, 169, AB52 <= 7, 179, AB52 <= 9, 209, AB52 <= 12, 249, AB52 <= 15, 299, AB52 <= 20, 390, AB52 <= 30, 420, AB52 <= 40, 525, AB52 <= 50, 859, AB52 <= 60, 1049, AB52 <= 70, 1099, AB52 <= 80, 1149, AB52 <= 90, 1169, AB52 <= 100, 1199, AB52 <= 125, 1449,AB52 <= 150, 1899, AB52 <= 175, 2349, AB52 <= 200, 2799, AB52 <= 225, 3299, AB52 <= 250, 379, AB52 <= 275, 4199, AB52 <= 300, 4699, AB52 <= 325, 5199, "Exceso de peso"),"Error") -> 139 | U52: =J52-O52-P52-Q52-S52-T52 -> 105.373 | V52: =U52/O52 -> 0.15053286 | W52: 20.5 | X52: 12 | Y52: 12 | Z52: 1.05 | AA52: =(W52*X52*Y52)/5000 -> 0.5904 | AB52: =IF(Z52>AA52,Z52,AA52) -> 1.05
A53: Apagada | B53: IQ1167 | C53: 6932554418427 | D53: 81218861 | E53: 1301473519 | F53: Xiaomi Photo Printer 1s | G53: Impresoras | H53: Xiaomi | I53: 1999 | J53: 1799 | L53: 3 | M53: =IFS(L53=0,0,L53=3,0.01,L53=6,0.03,L53=12,0.06) -> 0.01 | N53: Elektra envío gratis | O53: 1040 | P53: =J53*0.08 -> 143.92 | Q53: =(J53-P53)*0.025 -> 41.377 | R53: =16%+M53 -> 0.17 | S53: =J53*R53 -> 305.83 | T53: =IF(AND(ISNUMBER(AB53)=TRUE(),AB53>0),SWITCH(TRUE(),AB53 <= 1, 129, AB53 <= 2, 139, AB53 <= 3, 149, AB53 <= 5, 169, AB53 <= 7, 179, AB53 <= 9, 209, AB53 <= 12, 249, AB53 <= 15, 299, AB53 <= 20, 390, AB53 <= 30, 420, AB53 <= 40, 525, AB53 <= 50, 859, AB53 <= 60, 1049, AB53 <= 70, 1099, AB53 <= 80, 1149, AB53 <= 90, 1169, AB53 <= 100, 1199, AB53 <= 125, 1449,AB53 <= 150, 1899, AB53 <= 175, 2349, AB53 <= 200, 2799, AB53 <= 225, 3299, AB53 <= 250, 379, AB53 <= 275, 4199, AB53 <= 300, 4699, AB53 <= 325, 5199, "Exceso de peso"),"Error") -> 139 | U53: =J53-O53-P53-Q53-S53-T53 -> 128.873 | V53: =U53/O53 -> 0.12391635 | W53: 15.5 | X53: 23.5 | Y53: 11 | Z53: 1.6 | AA53: =(W53*X53*Y53)/5000 -> 0.80135 | AB53: =IF(Z53>AA53,Z53,AA53) -> 1.6
A54: Apagada | B54: IQ17 | C54: 791797074106 | D54: 81106573 | E54: 1301362756 | F54: Razer Deathadder Essential Blanco | G54: Teclados Y Mouse | H54: Razer | I54: 999 | J54: 599 | L54: 3 | M54: =IFS(L54=0,0,L54=3,0.01,L54=6,0.03,L54=12,0.06) -> 0.01 | N54: Elektra envío gratis | O54: 276.75 | P54: =J54*0.08 -> 47.92 | Q54: =(J54-P54)*0.025 -> 13.777 | R54: =16%+M54 -> 0.17 | S54: =J54*R54 -> 101.83 | T54: =IF(AND(ISNUMBER(AB54)=TRUE(),AB54>0),SWITCH(TRUE(),AB54 <= 1, 129, AB54 <= 2, 139, AB54 <= 3, 149, AB54 <= 5, 169, AB54 <= 7, 179, AB54 <= 9, 209, AB54 <= 12, 249, AB54 <= 15, 299, AB54 <= 20, 390, AB54 <= 30, 420, AB54 <= 40, 525, AB54 <= 50, 859, AB54 <= 60, 1049, AB54 <= 70, 1099, AB54 <= 80, 1149, AB54 <= 90, 1169, AB54 <= 100, 1199, AB54 <= 125, 1449,AB54 <= 150, 1899, AB54 <= 175, 2349, AB54 <= 200, 2799, AB54 <= 225, 3299, AB54 <= 250, 379, AB54 <= 275, 4199, AB54 <= 300, 4699, AB54 <= 325, 5199, "Exceso de peso"),"Error") -> 129 | U54: =J54-O54-P54-Q54-S54-T54 -> 29.723 | V54: =U54/O54 -> 0.10740018 | W54: 16 | X54: 10 | Y54: 5.5 | Z54: 0.18 | AA54: =(W54*X54*Y54)/5000 -> 0.176 | AB54: =IF(Z54>AA54,Z54,AA54) -> 0.18
A55: Apagada | B55: IQ60 | C55: 791797074106 | D55: 81106573 | E55: 1301362756 | F55: Razer Deathadder Essential Negro | G55: Teclados Y Mouse | H55: Razer | I55: 999 | J55: 599 | L55: 3 | M55: =IFS(L55=0,0,L55=3,0.01,L55=6,0.03,L55=12,0.06) -> 0.01 | N55: Elektra envío gratis | O55: 276.75 | P55: =J55*0.08 -> 47.92 | Q55: =(J55-P55)*0.025 -> 13.777 | R55: =16%+M55 -> 0.17 | S55: =J55*R55 -> 101.83 | T55: =IF(AND(ISNUMBER(AB55)=TRUE(),AB55>0),SWITCH(TRUE(),AB55 <= 1, 129, AB55 <= 2, 139, AB55 <= 3, 149, AB55 <= 5, 169, AB55 <= 7, 179, AB55 <= 9, 209, AB55 <= 12, 249, AB55 <= 15, 299, AB55 <= 20, 390, AB55 <= 30, 420, AB55 <= 40, 525, AB55 <= 50, 859, AB55 <= 60, 1049, AB55 <= 70, 1099, AB55 <= 80, 1149, AB55 <= 90, 1169, AB55 <= 100, 1199, AB55 <= 125, 1449,AB55 <= 150, 1899, AB55 <= 175, 2349, AB55 <= 200, 2799, AB55 <= 225, 3299, AB55 <= 250, 379, AB55 <= 275, 4199, AB55 <= 300, 4699, AB55 <= 325, 5199, "Exceso de peso"),"Error") -> 129 | U55: =J55-O55-P55-Q55-S55-T55 -> 29.723 | V55: =U55/O55 -> 0.10740018 | W55: 16 | X55: 10 | Y55: 5.5 | Z55: 0.18 | AA55: =(W55*X55*Y55)/5000 -> 0.176 | AB55: =IF(Z55>AA55,Z55,AA55) -> 0.18
A56: Apagada | F56: Smart Band 9 Active | J56: 599 | L56: 3 | M56: =IFS(L56=0,0,L56=3,0.01,L56=6,0.03,L56=12,0.06) -> 0.01 | N56: Elektra envío gratis | O56: 276.75 | P56: =J56*0.08 -> 47.92 | Q56: =(J56-P56)*0.025 -> 13.777 | R56: =17%+M56 -> 0.18 | S56: =J56*R56 -> 107.82 | T56: =IF(AND(ISNUMBER(AB56)=TRUE(),AB56>0),SWITCH(TRUE(),AB56 <= 1, 129, AB56 <= 2, 139, AB56 <= 3, 149, AB56 <= 5, 169, AB56 <= 7, 179, AB56 <= 9, 209, AB56 <= 12, 249, AB56 <= 15, 299, AB56 <= 20, 390, AB56 <= 30, 420, AB56 <= 40, 525, AB56 <= 50, 859, AB56 <= 60, 1049, AB56 <= 70, 1099, AB56 <= 80, 1149, AB56 <= 90, 1169, AB56 <= 100, 1199, AB56 <= 125, 1449,AB56 <= 150, 1899, AB56 <= 175, 2349, AB56 <= 200, 2799, AB56 <= 225, 3299, AB56 <= 250, 379, AB56 <= 275, 4199, AB56 <= 300, 4699, AB56 <= 325, 5199, "Exceso de peso"),"Error") -> 129 | U56: =J56-O56-P56-Q56-S56-T56 -> 23.733 | V56: =U56/O56 -> 0.085756098 | W56: 16 | X56: 10 | Y56: 5.5 | Z56: 0.18 | AA56: =(W56*X56*Y56)/5000 -> 0.176 | AB56: =IF(Z56>AA56,Z56,AA56) -> 0.18
A57: Apagada | B57: IQ1463 | C57: 50036414289 | D57: 81103634 | E57: 1301385342 | F57: Partybox 720 | G57: Bocinas | H57: Jbl | I57: 21999 | J57: 18399 | L57: 6 | M57: =IFS(L57=0,0,L57=3,0.01,L57=6,0.03,L57=12,0.06) -> 0.03 | N57: Elektra envío gratis | O57: 11855 | P57: =J57*0.08 -> 1471.92 | Q57: =(J57-P57)*0.025 -> 423.177 | R57: =11%+M57 -> 0.14 | S57: =J57*R57 -> 2575.86 | T57: =IF(AND(ISNUMBER(AB57)=TRUE(),AB57>0),SWITCH(TRUE(),AB57 <= 1, 129, AB57 <= 2, 139, AB57 <= 3, 149, AB57 <= 5, 169, AB57 <= 7, 179, AB57 <= 9, 209, AB57 <= 12, 249, AB57 <= 15, 299, AB57 <= 20, 390, AB57 <= 30, 420, AB57 <= 40, 525, AB57 <= 50, 859, AB57 <= 60, 1049, AB57 <= 70, 1099, AB57 <= 80, 1149, AB57 <= 90, 1169, AB57 <= 100, 1199, AB57 <= 125, 1449,AB57 <= 150, 1899, AB57 <= 175, 2349, AB57 <= 200, 2799, AB57 <= 225, 3299, AB57 <= 250, 379, AB57 <= 275, 4199, AB57 <= 300, 4699, AB57 <= 325, 5199, "Exceso de peso"),"Error") -> 859 | U57: =J57-O57-P57-Q57-S57-T57 -> 1214.043 | V57: =U57/O57 -> 0.10240768 | W57: 46.8 | X57: 49.1 | Y57: 102.7 | Z57: 0.18 | AA57: =(W57*X57*Y57)/5000 -> 47.198455 | AB57: =IF(Z57>AA57,Z57,AA57) -> 47.198455
A58: Apagada | B58: IQ1381 | C58: 50036408608 | D58: 81103629 | E58: 1301385343 | F58: Partybox 520 | G58: Bocinas | H58: Jbl | J58: 13299 | L58: 3 | M58: =IFS(L58=0,0,L58=3,0.01,L58=6,0.03,L58=12,0.06) -> 0.01 | N58: Elektra envío gratis | O58: 8599 | P58: =J58*0.08 -> 1063.92 | Q58: =(J58-P58)*0.025 -> 305.877 | R58: =11%+M58 -> 0.12 | S58: =J58*R58 -> 1595.88 | T58: =IF(AND(ISNUMBER(AB58)=TRUE(),AB58>0),SWITCH(TRUE(),AB58 <= 1, 129, AB58 <= 2, 139, AB58 <= 3, 149, AB58 <= 5, 169, AB58 <= 7, 179, AB58 <= 9, 209, AB58 <= 12, 249, AB58 <= 15, 299, AB58 <= 20, 390, AB58 <= 30, 420, AB58 <= 40, 525, AB58 <= 50, 859, AB58 <= 60, 1049, AB58 <= 70, 1099, AB58 <= 80, 1149, AB58 <= 90, 1169, AB58 <= 100, 1199, AB58 <= 125, 1449,AB58 <= 150, 1899, AB58 <= 175, 2349, AB58 <= 200, 2799, AB58 <= 225, 3299, AB58 <= 250, 379, AB58 <= 275, 4199, AB58 <= 300, 4699, AB58 <= 325, 5199, "Exceso de peso"),"Error") -> 859 | U58: =J58-O58-P58-Q58-S58-T58 -> 875.323 | V58: =U58/O58 -> 0.10179358 | W58: 48.9 | X58: 85.4 | Y58: 48 | Z58: 29.4 | AA58: =(W58*X58*Y58)/5000 -> 40.090176 | AB58: =IF(Z58>AA58,Z58,AA58) -> 40.090176
A59: Apagada | B59: IQ1223 | C59: 6941812701867 | D59: 81209730 | E59: 1301466535 | F59: Xiaomi Vacuum S40c Us | G59: Aspiradoras | H59: Xiaomi | I59: 4999 | J59: 3799 | L59: 3 | M59: =IFS(L59=0,0,L59=3,0.01,L59=6,0.03,L59=12,0.06) -> 0.01 | N59: Elektra envío gratis | O59: 2300 | P59: =J59*0.08 -> 303.92 | Q59: =(J59-P59)*0.025 -> 87.377 | R59: =15%+M59 -> 0.16 | S59: =J59*R59 -> 607.84 | T59: =IF(AND(ISNUMBER(AB59)=TRUE(),AB59>0),SWITCH(TRUE(),AB59 <= 1, 129, AB59 <= 2, 139, AB59 <= 3, 149, AB59 <= 5, 169, AB59 <= 7, 179, AB59 <= 9, 209, AB59 <= 12, 249, AB59 <= 15, 299, AB59 <= 20, 390, AB59 <= 30, 420, AB59 <= 40, 525, AB59 <= 50, 859, AB59 <= 60, 1049, AB59 <= 70, 1099, AB59 <= 80, 1149, AB59 <= 90, 1169, AB59 <= 100, 1199, AB59 <= 125, 1449,AB59 <= 150, 1899, AB59 <= 175, 2349, AB59 <= 200, 2799, AB59 <= 225, 3299, AB59 <= 250, 379, AB59 <= 275, 4199, AB59 <= 300, 4699, AB59 <= 325, 5199, "Exceso de peso"),"Error") -> 179 | U59: =J59-O59-P59-Q59-S59-T59 -> 320.863 | V59: =U59/O59 -> 0.13950565 | W59: 49 | X59: 39 | Y59: 14 | Z59: 5.2 | AA59: =(W59*X59*Y59)/5000 -> 5.3508 | AB59: =IF(Z59>AA59,Z59,AA59) -> 5.3508
A60: Apagada | B60: IQ635 | C60: 6941812708477 | D60: 81209728 | E60: 1301466530 | F60: Xiaomi Robot Vacuum E10 Us | G60: Aspiradoras | H60: Xiaomi | I60: 5199 | J60: 3899 | L60: 3 | M60: =IFS(L60=0,0,L60=3,0.01,L60=6,0.03,L60=12,0.06) -> 0.01 | N60: Elektra envío gratis | O60: 2380 | P60: =J60*0.08 -> 311.92 | Q60: =(J60-P60)*0.025 -> 89.677 | R60: =15%+M60 -> 0.16 | S60: =J60*R60 -> 623.84 | T60: =IF(AND(ISNUMBER(AB60)=TRUE(),AB60>0),SWITCH(TRUE(),AB60 <= 1, 129, AB60 <= 2, 139, AB60 <= 3, 149, AB60 <= 5, 169, AB60 <= 7, 179, AB60 <= 9, 209, AB60 <= 12, 249, AB60 <= 15, 299, AB60 <= 20, 390, AB60 <= 30, 420, AB60 <= 40, 525, AB60 <= 50, 859, AB60 <= 60, 1049, AB60 <= 70, 1099, AB60 <= 80, 1149, AB60 <= 90, 1169, AB60 <= 100, 1199, AB60 <= 125, 1449,AB60 <= 150, 1899, AB60 <= 175, 2349, AB60 <= 200, 2799, AB60 <= 225, 3299, AB60 <= 250, 379, AB60 <= 275, 4199, AB60 <= 300, 4699, AB60 <= 325, 5199, "Exceso de peso"),"Error") -> 169 | U60: =J60-O60-P60-Q60-S60-T60 -> 324.563 | V60: =U60/O60 -> 0.13637101 | W60: 40 | X60: 13 | Y60: 45 | Z60: 5 | AA60: =(W60*X60*Y60)/5000 -> 4.68 | AB60: =IF(Z60>AA60,Z60,AA60) -> 5
A61: Apagada | B61: IQ1225 | C61: 878615093218 | D61: 81106574 | E61: 1301362843 | F61: Skullcandy Riff Negro | G61: Audífonos | H61: Skullcandy | I61: 699 | J61: 479 | L61: 3 | M61: =IFS(L61=0,0,L61=3,0.01,L61=6,0.03,L61=12,0.06) -> 0.01 | N61: Elektra envío gratis | O61: 249 | P61: =J61*0.08 -> 38.32 | Q61: =(J61-P61)*0.025 -> 11.017 | R61: =11%+M61 -> 0.12 | S61: =J61*R61 -> 57.48 | T61: =IF(AND(ISNUMBER(AB61)=TRUE(),AB61>0),SWITCH(TRUE(),AB61 <= 1, 129, AB61 <= 2, 139, AB61 <= 3, 149, AB61 <= 5, 169, AB61 <= 7, 179, AB61 <= 9, 209, AB61 <= 12, 249, AB61 <= 15, 299, AB61 <= 20, 390, AB61 <= 30, 420, AB61 <= 40, 525, AB61 <= 50, 859, AB61 <= 60, 1049, AB61 <= 70, 1099, AB61 <= 80, 1149, AB61 <= 90, 1169, AB61 <= 100, 1199, AB61 <= 125, 1449,AB61 <= 150, 1899, AB61 <= 175, 2349, AB61 <= 200, 2799, AB61 <= 225, 3299, AB61 <= 250, 379, AB61 <= 275, 4199, AB61 <= 300, 4699, AB61 <= 325, 5199, "Exceso de peso"),"Error") -> 129 | U61: =J61-O61-P61-Q61-S61-T61 -> -5.817 | V61: =U61/O61 -> -0.023361446 | W61: 19.5 | X61: 0.18 | Y61: 8.5 | Z61: 0.3 | AA61: =(W61*X61*Y61)/5000 -> 0.005967 | AB61: =IF(Z61>AA61,Z61,AA61) -> 0.3
A62: Apagada | B62: IQ890 | C62: 6941812706251 | D62: 81218865 | E62: 1301473427 | F62: Xiaomi Smart Band 9 Active Beige | G62: Fit Bands | H62: Xiaomi | I62: 999 | J62: 729 | L62: 3 | M62: =IFS(L62=0,0,L62=3,0.01,L62=6,0.03,L62=12,0.06) -> 0.01 | N62: Elektra envío gratis | O62: 360.98 | P62: =J62*0.08 -> 58.32 | Q62: =(J62-P62)*0.025 -> 16.767 | R62: =17%+M62 -> 0.18 | S62: =J62*R62 -> 131.22 | T62: =IF(AND(ISNUMBER(AB62)=TRUE(),AB62>0),SWITCH(TRUE(),AB62 <= 1, 129, AB62 <= 2, 139, AB62 <= 3, 149, AB62 <= 5, 169, AB62 <= 7, 179, AB62 <= 9, 209, AB62 <= 12, 249, AB62 <= 15, 299, AB62 <= 20, 390, AB62 <= 30, 420, AB62 <= 40, 525, AB62 <= 50, 859, AB62 <= 60, 1049, AB62 <= 70, 1099, AB62 <= 80, 1149, AB62 <= 90, 1169, AB62 <= 100, 1199, AB62 <= 125, 1449,AB62 <= 150, 1899, AB62 <= 175, 2349, AB62 <= 200, 2799, AB62 <= 225, 3299, AB62 <= 250, 379, AB62 <= 275, 4199, AB62 <= 300, 4699, AB62 <= 325, 5199, "Exceso de peso"),"Error") -> 129 | U62: =J62-O62-P62-Q62-S62-T62 -> 32.713 | V62: =U62/O62 -> 0.090622749 | W62: 9 | X62: 9 | Y62: 3 | Z62: 0.12 | AA62: =(W62*X62*Y62)/5000 -> 0.0486 | AB62: =IF(Z62>AA62,Z62,AA62) -> 0.12
A63: Apagada | B63: IQ892 | C63: 6932554415389 | D63: 81218875 | E63: 1301473579 | F63: Xiaomi Smart Band 9 Active Rosa | G63: Fit Bands | H63: Xiaomi | I63: 999 | J63: 769 | L63: 3 | M63: =IFS(L63=0,0,L63=3,0.01,L63=6,0.03,L63=12,0.06) -> 0.01 | N63: Elektra envío gratis | O63: 389 | P63: =J63*0.08 -> 61.52 | Q63: =(J63-P63)*0.025 -> 17.687 | R63: =17%+M63 -> 0.18 | S63: =J63*R63 -> 138.42 | T63: =IF(AND(ISNUMBER(AB63)=TRUE(),AB63>0),SWITCH(TRUE(),AB63 <= 1, 129, AB63 <= 2, 139, AB63 <= 3, 149, AB63 <= 5, 169, AB63 <= 7, 179, AB63 <= 9, 209, AB63 <= 12, 249, AB63 <= 15, 299, AB63 <= 20, 390, AB63 <= 30, 420, AB63 <= 40, 525, AB63 <= 50, 859, AB63 <= 60, 1049, AB63 <= 70, 1099, AB63 <= 80, 1149, AB63 <= 90, 1169, AB63 <= 100, 1199, AB63 <= 125, 1449,AB63 <= 150, 1899, AB63 <= 175, 2349, AB63 <= 200, 2799, AB63 <= 225, 3299, AB63 <= 250, 379, AB63 <= 275, 4199, AB63 <= 300, 4699, AB63 <= 325, 5199, "Exceso de peso"),"Error") -> 129 | U63: =J63-O63-P63-Q63-S63-T63 -> 33.373 | V63: =U63/O63 -> 0.085791774 | W63: 9 | X63: 9 | Y63: 3 | Z63: 0.12 | AA63: =(W63*X63*Y63)/5000 -> 0.0486 | AB63: =IF(Z63>AA63,Z63,AA63) -> 0.12
A64: Apagada | B64: IQ1032 | C64: 6932554419813 | D64: 81218866 | E64: 1301473470 | F64: Xiaomi Mi Band 10 Gris | G64: Fit Bands | H64: Xiaomi | I64: 1499 | J64: 1149 | K64: 50 | L64: 3 | M64: =IFS(L64=0,0,L64=3,0.01,L64=6,0.03,L64=12,0.06) -> 0.01 | N64: Elektra envío gratis | O64: 638.63 | P64: =J64*0.08 -> 91.92 | Q64: =(J64-P64)*0.025 -> 26.427 | R64: =17%+M64 -> 0.18 | S64: =J64*R64 -> 206.82 | T64: =IF(AND(ISNUMBER(AB64)=TRUE(),AB64>0),SWITCH(TRUE(),AB64 <= 1, 129, AB64 <= 2, 139, AB64 <= 3, 149, AB64 <= 5, 169, AB64 <= 7, 179, AB64 <= 9, 209, AB64 <= 12, 249, AB64 <= 15, 299, AB64 <= 20, 390, AB64 <= 30, 420, AB64 <= 40, 525, AB64 <= 50, 859, AB64 <= 60, 1049, AB64 <= 70, 1099, AB64 <= 80, 1149, AB64 <= 90, 1169, AB64 <= 100, 1199, AB64 <= 125, 1449,AB64 <= 150, 1899, AB64 <= 175, 2349, AB64 <= 200, 2799, AB64 <= 225, 3299, AB64 <= 250, 379, AB64 <= 275, 4199, AB64 <= 300, 4699, AB64 <= 325, 5199, "Exceso de peso"),"Error") -> 129 | U64: =J64-O64-P64-Q64-S64-T64 -> 56.203 | V64: =U64/O64 -> 0.088005574 | W64: 12.5 | X64: 12.5 | Y64: 8.5 | Z64: 0.5 | AA64: =(W64*X64*Y64)/5000 -> 0.265625 | AB64: =IF(Z64>AA64,Z64,AA64) -> 0.5
A65: Apagada | B65: IQ1047 | C65: 6941812784563 | D65: 81218867 | E65: 1301473472 | F65: Xiaomi Watch 5 Negro | G65: Smartwatch | H65: Xiaomi | I65: 2999 | J65: 2599 | L65: 3 | M65: =IFS(L65=0,0,L65=3,0.01,L65=6,0.03,L65=12,0.06) -> 0.01 | N65: Elektra envío gratis | O65: 1600 | P65: =J65*0.08 -> 207.92 | Q65: =(J65-P65)*0.025 -> 59.777 | R65: =10%+M65 -> 0.11 | S65: =J65*R65 -> 285.89 | T65: =IF(AND(ISNUMBER(AB65)=TRUE(),AB65>0),SWITCH(TRUE(),AB65 <= 1, 129, AB65 <= 2, 139, AB65 <= 3, 149, AB65 <= 5, 169, AB65 <= 7, 179, AB65 <= 9, 209, AB65 <= 12, 249, AB65 <= 15, 299, AB65 <= 20, 390, AB65 <= 30, 420, AB65 <= 40, 525, AB65 <= 50, 859, AB65 <= 60, 1049, AB65 <= 70, 1099, AB65 <= 80, 1149, AB65 <= 90, 1169, AB65 <= 100, 1199, AB65 <= 125, 1449,AB65 <= 150, 1899, AB65 <= 175, 2349, AB65 <= 200, 2799, AB65 <= 225, 3299, AB65 <= 250, 379, AB65 <= 275, 4199, AB65 <= 300, 4699, AB65 <= 325, 5199, "Exceso de peso"),"Error") -> 129 | U65: =J65-O65-P65-Q65-S65-T65 -> 316.413 | V65: =U65/O65 -> 0.19775813 | W65: 12.5 | X65: 12.5 | Y65: 8.5 | Z65: 0.15 | AA65: =(W65*X65*Y65)/5000 -> 0.265625 | AB65: =IF(Z65>AA65,Z65,AA65) -> 0.265625
A66: Apagada | B66: IQ1472 | C66: 4897116931801 | D66: 81209726 | E66: 1301466514 | F66: Kodak Charmera | G66: Digitales | H66: Kodak | I66: 1299 | J66: 979 | K66: 40 | L66: 3 | M66: =IFS(L66=0,0,L66=3,0.01,L66=6,0.03,L66=12,0.06) -> 0.01 | N66: Elektra envío gratis | O66: 522.16 | P66: =J66*0.08 -> 78.32 | Q66: =(J66-P66)*0.025 -> 22.517 | R66: =16%+M66 -> 0.17 | S66: =J66*R66 -> 166.43 | T66: =IF(AND(ISNUMBER(AB66)=TRUE(),AB66>0),SWITCH(TRUE(),AB66 <= 1, 129, AB66 <= 2, 139, AB66 <= 3, 149, AB66 <= 5, 169, AB66 <= 7, 179, AB66 <= 9, 209, AB66 <= 12, 249, AB66 <= 15, 299, AB66 <= 20, 390, AB66 <= 30, 420, AB66 <= 40, 525, AB66 <= 50, 859, AB66 <= 60, 1049, AB66 <= 70, 1099, AB66 <= 80, 1149, AB66 <= 90, 1169, AB66 <= 100, 1199, AB66 <= 125, 1449,AB66 <= 150, 1899, AB66 <= 175, 2349, AB66 <= 200, 2799, AB66 <= 225, 3299, AB66 <= 250, 379, AB66 <= 275, 4199, AB66 <= 300, 4699, AB66 <= 325, 5199, "Exceso de peso"),"Error") -> 129 | U66: =J66-O66-P66-Q66-S66-T66 -> 60.573 | V66: =U66/O66 -> 0.11600467 | W66: 10.5 | X66: 8 | Y66: 4.5 | Z66: 0.1 | AA66: =(W66*X66*Y66)/5000 -> 0.0756 | AB66: =IF(Z66>AA66,Z66,AA66) -> 0.1
A67: Apagada | B67: IQ1037 | C67: 8720389033971 | D67: 81209727 | E67: 1301466525 | F67: Cafetera Phillips Baristina | G67: Cafeteras Y Teteras | H67: Phillips | I67: 7999 | J67: 5999 | L67: 3 | M67: =IFS(L67=0,0,L67=3,0.01,L67=6,0.03,L67=12,0.06) -> 0.01 | N67: Elektra envío gratis | O67: 3884.6 | P67: =J67*0.08 -> 479.92 | Q67: =(J67-P67)*0.025 -> 137.977 | R67: =15%+M67 -> 0.16 | S67: =J67*R67 -> 959.84 | T67: =IF(AND(ISNUMBER(AB67)=TRUE(),AB67>0),SWITCH(TRUE(),AB67 <= 1, 129, AB67 <= 2, 139, AB67 <= 3, 149, AB67 <= 5, 169, AB67 <= 7, 179, AB67 <= 9, 209, AB67 <= 12, 249, AB67 <= 15, 299, AB67 <= 20, 390, AB67 <= 30, 420, AB67 <= 40, 525, AB67 <= 50, 859, AB67 <= 60, 1049, AB67 <= 70, 1099, AB67 <= 80, 1149, AB67 <= 90, 1169, AB67 <= 100, 1199, AB67 <= 125, 1449,AB67 <= 150, 1899, AB67 <= 175, 2349, AB67 <= 200, 2799, AB67 <= 225, 3299, AB67 <= 250, 379, AB67 <= 275, 4199, AB67 <= 300, 4699, AB67 <= 325, 5199, "Exceso de peso"),"Error") -> 249 | U67: =J67-O67-P67-Q67-S67-T67 -> 287.663 | V67: =U67/O67 -> 0.074052155 | W67: 48 | X67: 23 | Y67: 38 | Z67: 9.5 | AA67: =(W67*X67*Y67)/5000 -> 8.3904 | AB67: =IF(Z67>AA67,Z67,AA67) -> 9.5
A68: Apagada | B68: IQ872 | C68: 6941812791530 | D68: 81218869 | E68: 1301473462 | F68: Xiaomi Redmi Watch 5 Lite Black | G68: Smartwatch | H68: Xiaomi | I68: 1999 | J68: 1249 | L68: 3 | M68: =IFS(L68=0,0,L68=3,0.01,L68=6,0.03,L68=12,0.06) -> 0.01 | N68: Elektra envío gratis | O68: 700 | P68: =J68*0.08 -> 99.92 | Q68: =(J68-P68)*0.025 -> 28.727 | R68: =10%+M68 -> 0.11 | S68: =J68*R68 -> 137.39 | T68: =IF(AND(ISNUMBER(AB68)=TRUE(),AB68>0),SWITCH(TRUE(),AB68 <= 1, 129, AB68 <= 2, 139, AB68 <= 3, 149, AB68 <= 5, 169, AB68 <= 7, 179, AB68 <= 9, 209, AB68 <= 12, 249, AB68 <= 15, 299, AB68 <= 20, 390, AB68 <= 30, 420, AB68 <= 40, 525, AB68 <= 50, 859, AB68 <= 60, 1049, AB68 <= 70, 1099, AB68 <= 80, 1149, AB68 <= 90, 1169, AB68 <= 100, 1199, AB68 <= 125, 1449,AB68 <= 150, 1899, AB68 <= 175, 2349, AB68 <= 200, 2799, AB68 <= 225, 3299, AB68 <= 250, 379, AB68 <= 275, 4199, AB68 <= 300, 4699, AB68 <= 325, 5199, "Exceso de peso"),"Error") -> 129 | U68: =J68-O68-P68-Q68-S68-T68 -> 153.963 | V68: =U68/O68 -> 0.21994714 | W68: 3 | X68: 9.5 | Y68: 9 | Z68: 0.15 | AA68: =(W68*X68*Y68)/5000 -> 0.0513 | AB68: =IF(Z68>AA68,Z68,AA68) -> 0.15
A69: Apagada | B69: IQ871 | C69: 6941812791554 | D69: 81218868 | E69: 1301473566 | F69: Xiaomi Redmi Watch 5 Lite Gold | G69: Smartwatch | H69: Xiaomi | I69: 1599 | J69: 1249 | L69: 3 | M69: =IFS(L69=0,0,L69=3,0.01,L69=6,0.03,L69=12,0.06) -> 0.01 | N69: Elektra envío gratis | O69: 700 | P69: =J69*0.08 -> 99.92 | Q69: =(J69-P69)*0.025 -> 28.727 | R69: =10%+M69 -> 0.11 | S69: =J69*R69 -> 137.39 | T69: =IF(AND(ISNUMBER(AB69)=TRUE(),AB69>0),SWITCH(TRUE(),AB69 <= 1, 129, AB69 <= 2, 139, AB69 <= 3, 149, AB69 <= 5, 169, AB69 <= 7, 179, AB69 <= 9, 209, AB69 <= 12, 249, AB69 <= 15, 299, AB69 <= 20, 390, AB69 <= 30, 420, AB69 <= 40, 525, AB69 <= 50, 859, AB69 <= 60, 1049, AB69 <= 70, 1099, AB69 <= 80, 1149, AB69 <= 90, 1169, AB69 <= 100, 1199, AB69 <= 125, 1449,AB69 <= 150, 1899, AB69 <= 175, 2349, AB69 <= 200, 2799, AB69 <= 225, 3299, AB69 <= 250, 379, AB69 <= 275, 4199, AB69 <= 300, 4699, AB69 <= 325, 5199, "Exceso de peso"),"Error") -> 129 | U69: =J69-O69-P69-Q69-S69-T69 -> 153.963 | V69: =U69/O69 -> 0.21994714 | W69: 3 | X69: 9.5 | Y69: 9 | Z69: 0.15 | AA69: =(W69*X69*Y69)/5000 -> 0.0513 | AB69: =IF(Z69>AA69,Z69,AA69) -> 0.15
A70: Apagada | B70: IQ856 | C70: 6941812769454 | D70: 81218836 | E70: 1301483065 | F70: Xiaomi Vacuum E5 Blanco | G70: Aspiradoras | H70: Xiaomi | I70: 3499 | J70: 2799 | L70: 3 | M70: =IFS(L70=0,0,L70=3,0.01,L70=6,0.03,L70=12,0.06) -> 0.01 | N70: Elektra envío gratis | O70: 1670 | P70: =J70*0.08 -> 223.92 | Q70: =(J70-P70)*0.025 -> 64.377 | R70: =15%+M70 -> 0.16 | S70: =J70*R70 -> 447.84 | T70: =IF(AND(ISNUMBER(AB70)=TRUE(),AB70>0),SWITCH(TRUE(),AB70 <= 1, 129, AB70 <= 2, 139, AB70 <= 3, 149, AB70 <= 5, 169, AB70 <= 7, 179, AB70 <= 9, 209, AB70 <= 12, 249, AB70 <= 15, 299, AB70 <= 20, 390, AB70 <= 30, 420, AB70 <= 40, 525, AB70 <= 50, 859, AB70 <= 60, 1049, AB70 <= 70, 1099, AB70 <= 80, 1149, AB70 <= 90, 1169, AB70 <= 100, 1199, AB70 <= 125, 1449,AB70 <= 150, 1899, AB70 <= 175, 2349, AB70 <= 200, 2799, AB70 <= 225, 3299, AB70 <= 250, 379, AB70 <= 275, 4199, AB70 <= 300, 4699, AB70 <= 325, 5199, "Exceso de peso"),"Error") -> 169 | U70: =J70-O70-P70-Q70-S70-T70 -> 223.863 | V70: =U70/O70 -> 0.1340497 | W70: 36.5 | X70: 13.5 | Y70: 43.5 | Z70: 3.2 | AA70: =(W70*X70*Y70)/5000 -> 4.286925 | AB70: =IF(Z70>AA70,Z70,AA70) -> 4.286925
A71: Apagada | B71: IQ1164 | C71: 6941812773147 | D71: 81218842 | E71: 1301483042 | F71: Xiaomi Vacuum G20 Lite | G71: Aspiradoras | H71: Xiaomi | I71: 3999 | J71: 2899 | L71: 3 | M71: =IFS(L71=0,0,L71=3,0.01,L71=6,0.03,L71=12,0.06) -> 0.01 | N71: Elektra envío gratis | O71: 1650 | P71: =J71*0.08 -> 231.92 | Q71: =(J71-P71)*0.025 -> 66.677 | R71: =15%+M71 -> 0.16 | S71: =J71*R71 -> 463.84 | T71: =IF(AND(ISNUMBER(AB71)=TRUE(),AB71>0),SWITCH(TRUE(),AB71 <= 1, 129, AB71 <= 2, 139, AB71 <= 3, 149, AB71 <= 5, 169, AB71 <= 7, 179, AB71 <= 9, 209, AB71 <= 12, 249, AB71 <= 15, 299, AB71 <= 20, 390, AB71 <= 30, 420, AB71 <= 40, 525, AB71 <= 50, 859, AB71 <= 60, 1049, AB71 <= 70, 1099, AB71 <= 80, 1149, AB71 <= 90, 1169, AB71 <= 100, 1199, AB71 <= 125, 1449,AB71 <= 150, 1899, AB71 <= 175, 2349, AB71 <= 200, 2799, AB71 <= 225, 3299, AB71 <= 250, 379, AB71 <= 275, 4199, AB71 <= 300, 4699, AB71 <= 325, 5199, "Exceso de peso"),"Error") -> 249 | U71: =J71-O71-P71-Q71-S71-T71 -> 237.563 | V71: =U71/O71 -> 0.14397758 | W71: 74 | X71: 29 | Y71: 21.5 | Z71: 3.6 | AA71: =(W71*X71*Y71)/5000 -> 9.2278 | AB71: =IF(Z71>AA71,Z71,AA71) -> 9.2278
A72: Apagada | B72: IQ1266 | C72: 799991620259 | D72: 81218843 | E72: 1301483069 | F72: Auriculares Inalámbricos A9 Con Pantalla | G72: Audífonos | H72: Generico | I72: 499 | J72: 359 | L72: 3 | M72: =IFS(L72=0,0,L72=3,0.01,L72=6,0.03,L72=12,0.06) -> 0.01 | N72: Elektra envío gratis | O72: 133.26 | P72: =J72*0.08 -> 28.72 | Q72: =(J72-P72)*0.025 -> 8.257 | R72: =11%+M72 -> 0.12 | S72: =J72*R72 -> 43.08 | T72: =IF(AND(ISNUMBER(AB72)=TRUE(),AB72>0),SWITCH(TRUE(),AB72 <= 1, 129, AB72 <= 2, 139, AB72 <= 3, 149, AB72 <= 5, 169, AB72 <= 7, 179, AB72 <= 9, 209, AB72 <= 12, 249, AB72 <= 15, 299, AB72 <= 20, 390, AB72 <= 30, 420, AB72 <= 40, 525, AB72 <= 50, 859, AB72 <= 60, 1049, AB72 <= 70, 1099, AB72 <= 80, 1149, AB72 <= 90, 1169, AB72 <= 100, 1199, AB72 <= 125, 1449,AB72 <= 150, 1899, AB72 <= 175, 2349, AB72 <= 200, 2799, AB72 <= 225, 3299, AB72 <= 250, 379, AB72 <= 275, 4199, AB72 <= 300, 4699, AB72 <= 325, 5199, "Exceso de peso"),"Error") -> 129 | U72: =J72-O72-P72-Q72-S72-T72 -> 16.683 | V72: =U72/O72 -> 0.12519136 | W72: 9 | X72: 9 | Y72: 4 | Z72: 0.18 | AA72: =(W72*X72*Y72)/5000 -> 0.0648 | AB72: =IF(Z72>AA72,Z72,AA72) -> 0.18
A73: Apagada | B73: IQ807 | C73: 6941812777527 | D73: 81218844 | E73: 1301483044 | F73: Redmi Buds 6 Active Blanco | G73: Audífonos | H73: Xiaomi | I73: 699 | J73: 519 | L73: 3 | M73: =IFS(L73=0,0,L73=3,0.01,L73=6,0.03,L73=12,0.06) -> 0.01 | N73: Elektra envío gratis | O73: 242 | P73: =J73*0.08 -> 41.52 | Q73: =(J73-P73)*0.025 -> 11.937 | R73: =11%+M73 -> 0.12 | S73: =J73*R73 -> 62.28 | T73: =IF(AND(ISNUMBER(AB73)=TRUE(),AB73>0),SWITCH(TRUE(),AB73 <= 1, 129, AB73 <= 2, 139, AB73 <= 3, 149, AB73 <= 5, 169, AB73 <= 7, 179, AB73 <= 9, 209, AB73 <= 12, 249, AB73 <= 15, 299, AB73 <= 20, 390, AB73 <= 30, 420, AB73 <= 40, 525, AB73 <= 50, 859, AB73 <= 60, 1049, AB73 <= 70, 1099, AB73 <= 80, 1149, AB73 <= 90, 1169, AB73 <= 100, 1199, AB73 <= 125, 1449,AB73 <= 150, 1899, AB73 <= 175, 2349, AB73 <= 200, 2799, AB73 <= 225, 3299, AB73 <= 250, 379, AB73 <= 275, 4199, AB73 <= 300, 4699, AB73 <= 325, 5199, "Exceso de peso"),"Error") -> 129 | U73: =J73-O73-P73-Q73-S73-T73 -> 32.263 | V73: =U73/O73 -> 0.13331818 | W73: 10 | X73: 10 | Y73: 4.5 | Z73: 0.16 | AA73: =(W73*X73*Y73)/5000 -> 0.09 | AB73: =IF(Z73>AA73,Z73,AA73) -> 0.16
A74: Apagada | B74: IQ809 | C74: 6941812777572 | D74: 81218849 | E74: 1301483070 | F74: Redmi Buds 6 Active Negro | G74: Audífonos | H74: Xiaomi | I74: 599 | J74: 519 | L74: 3 | M74: =IFS(L74=0,0,L74=3,0.01,L74=6,0.03,L74=12,0.06) -> 0.01 | N74: Elektra envío gratis | O74: 220 | P74: =J74*0.08 -> 41.52 | Q74: =(J74-P74)*0.025 -> 11.937 | R74: =11%+M74 -> 0.12 | S74: =J74*R74 -> 62.28 | T74: =IF(AND(ISNUMBER(AB74)=TRUE(),AB74>0),SWITCH(TRUE(),AB74 <= 1, 129, AB74 <= 2, 139, AB74 <= 3, 149, AB74 <= 5, 169, AB74 <= 7, 179, AB74 <= 9, 209, AB74 <= 12, 249, AB74 <= 15, 299, AB74 <= 20, 390, AB74 <= 30, 420, AB74 <= 40, 525, AB74 <= 50, 859, AB74 <= 60, 1049, AB74 <= 70, 1099, AB74 <= 80, 1149, AB74 <= 90, 1169, AB74 <= 100, 1199, AB74 <= 125, 1449,AB74 <= 150, 1899, AB74 <= 175, 2349, AB74 <= 200, 2799, AB74 <= 225, 3299, AB74 <= 250, 379, AB74 <= 275, 4199, AB74 <= 300, 4699, AB74 <= 325, 5199, "Exceso de peso"),"Error") -> 129 | U74: =J74-O74-P74-Q74-S74-T74 -> 54.263 | V74: =U74/O74 -> 0.24665 | W74: 10 | X74: 10 | Y74: 4.5 | Z74: 0.16 | AA74: =(W74*X74*Y74)/5000 -> 0.09 | AB74: =IF(Z74>AA74,Z74,AA74) -> 0.16
